Workbook

Sheet Start Here
A1: Start Here — Future Turtles 2026 Drinks, orientation for whoever builds the menu
A3: A free bar at Burning Man 2026. Non-alcoholic 'dirty sodas' built to order, with an optional shot for anyone who wants one. No money changes hands. THE WORKBOOK IS FINISHED AS A PLAN — what is wanted next is two pieces of design: (1) a guest-facing MENU, and (2) BARTENDER INSTRUCTIONS for people who have never made these drinks and will be reading in the dark, dusty and probably impaired.
A6: THE SHAPE OF IT
A7: Roughly 1,460 servings across 8 days — Sunday through the closing Sunday, with that last one a daytime cafe rather than a night. 16 built-to-order recipes available all week (including Root Access, the dirty root beer float, and the two tequila builds below), 3 Saturday-only reveals, one 33-serving jug special per service, and Turtle Soup on its own standalone sign. THE JUG CHANGES EVERY DAY EXCEPT ONE: Saturday and the closing Sunday pour the same peach green iced tea, deliberately, so that the busiest night of the week has one thing on it that needs no attention. TWO DRINKS BREAK THE LIQUOR-IS-OPTIONAL RULE — Rawhide and Localhost are tequila builds, sized at 100% uptake (Assumptions B222); both have non-alcoholic versions from stock on hand, and Rawhide’s is already on the standing board as salted soda water + lime. *** AS OF 11 Aug 2026 NEITHER PRINTS IN A BLOCK THAT SAYS SO: *** the old tequila-builds block is gone, Localhost sits among the built drinks and Rawhide in LESS SWEET, but both are still costed at a full shot on every serving. If you are designing the menu, the tequila needs to be visible on those two lines — the liquor column says 'IN THE BUILD, not optional' for exactly that reason. On top of that, 128 servings are cold cans a camper takes from the cooler with no bartender involved — Red Bull, coconut water and the Grapefruit Radler. Live figure for total servings is ‘Totals by Type’ B12.
A9: TABS YOU NEED FOR DESIGN
A10: 'Service Availability' — START HERE. What is on offer and when. Three groups: all-week, Saturday-only, and the nightly jug. This is the tab that decides the menu's structure. 'Dirty Soda - Built Drinks' — the build spec for every drink: base, per-serving oz of each ingredient, garnish, and the optional liquor. This is where bartender instructions come from. (Older notes across the workbook call this tab 'Recipes'; same tab, it was renamed.) 'Jug Recipes' — the nightly jug specials, one per night, with their own ingredients. 'Bar Add-Ons' — no-prep items a bartender hands over or splashes in. Free menu extensions, and where the LESS SWEET items are costed. 'Menu Board' — the existing rough board layout, live-linked to the names. THE 'LESS SWEET' BLOCK IS THE ONE TO GIVE REAL SPACE TO — it is the answer to 'have you got anything not too sweet?', which is the question this bar gets most often by Wednesday.
A12: TABS THAT ARE PROCUREMENT ONLY — IGNORE FOR DESIGN
A13: 'Purchase List', 'Packaged Sizing', 'Packaged Prices', 'Ingredient Pricing', 'Assumptions', 'Other Consumables', 'Base Soda — Cans', 'Beverage Lines', 'Totals by Type', 'Camp Drinks', 'Supplies'. These size and cost the shopping trip. Nothing in them belongs on a menu.
A15: HOUSE CONVENTIONS
A16: Standard pour is 8 oz over ice — small on purpose, so people can try several and nothing gets abandoned half-drunk. Liquor is always optional and always a 1.5 oz shot; the model assumes 35% of drinks get one. Six liquors behind the bar: vodka, coconut rum, bourbon, blanco tequila, spiced rum, whiskey. Several drinks take a Tajin rim. Cans of beer, cider, Red Bull and coconut water are handed over sealed, not poured.
A18: HARD RULES — DO NOT DESIGN AROUND THESE
A19: The three Saturday reveals (Sakura Kisses, Catboy Snot, Catboy Piss) MUST NOT appear on any menu shown before Saturday. They need their own separate card. Turtle Soup is NOT one of them — it is a standalone sign with no day attached, see 'Service Availability' section 4.
... A26: This plan originally ran on 8 kegs across two tap lines, which is why some tabs still carry keg vocabulary as a costing baseline. That is gone: everything is now bottles and cans on ice, which saved ~$870 and removed the jockey box, CO2 and deposits. The practical consequence for the menu is that the old day-by-day rotation is dead — almost everything is available all week. 'Beverage Lines' and the 'old keg $' columns are historical reference only.

Sheet Dirty Soda - Built Drinks
A1: Drink Recipes — absolute drink counts (per-serving oz)
A2: Recipe | B2: Servings | C2: (share) | D2: Base soda | E2: Base oz | F2: Syrup A | G2: A oz | H2: Syrup B | I2: B oz | J2: Soda water oz | K2: Coconut cream oz | L2: Special / garnish | M2: Liquor (optional) | N2: Liquor oz needed | O2: Tested?
A3: Tang Dynasty | B3: 30 | C3: =B3/$B$24 | D3: Kombucha (Island Mango) | E3: 4 | F3: Tangerine juice | G3: 2 | H3: Passion fruit purée | I3: 0.75 | J3: 0 | K3: 0 | L3: ISLAND MANGO KOMBUCHA as of 14 Aug 2026 — was passionfruit, which is not in the Brew Dr. variety pack. The passion fruit purée is still in the build, so the flavour is still there; mango + tangerine + purée reads rounder and slightly less sharp. Kombucha + tangerine + passion fruit over ice, fresh lime squeeze (Assumptions B113), slapped mint or basil leaf; stir. | M3: Vodka | N3: =B3*Assumptions!$B$39*Assumptions!$B$40 | O3: Yes
A4: Michelada | B4: =Assumptions!$B$60 | C4: =B4/$B$24 | D4: Mexican Lager | E4: 6 | F4: Tres Agaves Bloody Mary Mix | G4: 2.5 | H4: Lime juice (fresh) | I4: 0.5 | J4: 0 | K4: 0 | L4: Chelada built to order off the Mexican Lager keg: 2.5 oz Tres Agaves Bloody Mary Mix + fresh lime + Tajin rim. SWAPPED OFF CLAMATO + HOT SAUCE 18 Aug 2026 — the Bloody Mary mix (tomato, lime, chili pepper, onion, garlic, organic spices) already carries its own spice, so the separate hot sauce dash is dropped; lime squeeze stays. NOTE: this trades away the briny clam-broth character that's traditionally what makes a Michelada a Michelada — it reads more like a straight spicy tomato beer cocktail now, closer to a chelada preparada than an authentic michelada. Flavor call, not a math problem; revert Syrup A to 'Clamato' at 3 oz + restore Assumptions B105 to 0.25 if that's not the direction you want. Extras itemized on Other Consumables rows 39-42. OPTIONAL PREP, ADDED 18 Aug 2026 — PREFERRED IF ON HAND: if tomato juice / V8 turns up on the Reno grocery run (Purchase List row 100), build it as 1 oz Tres Agaves Bloody Mary Mix + 3 oz tomato/V8 juice instead of the default 2.5 oz Bloody Mary Mix alone — less clammy, closer to a straight tomato michelada. NOT SCALED INTO THE BUY: this is bartender's-choice per cup depending on what's in the cooler that day, not a guaranteed swap, so the Bloody Mary Mix purchase quantity (row 23) still assumes the 2.5 oz default for all 30 servings. Practical consequence: if V8 shows up and gets used often, the Bloody Mary Mix draw per serving drops from 2.5 oz to 1 oz, so the 4 bottles already on order will stretch considerably further than planned — that's headroom, not a shortfall. | N4: 0
A5: Vanilla Cherry Grove | B5: 130 | C5: =B5/$B$24 | D5: Coke | E5: 4 | F5: Vanilla | G5: 0.25 | H5: Cherry | I5: 0.25 | J5: 2 | K5: 0 | L5: DOSED DOWN 21 Aug 2026 (back-propagated from the bar guide) — vanilla and cherry cut from 2 pumps (0.5oz) to 1 pump (0.25oz) each, soda water raised 0.5oz to 2oz. Lighter syrup, longer pour. | M5: Bourbon | N5: =B5*Assumptions!$B$39*Assumptions!$B$40 | O5: yes
A6: Orange Cream-sicle | B6: 50 | C6: =B6/$B$24 | D6: Orange Fanta | E6: 4 | G6: 0 | I6: 0 | J6: 1 | K6: 1 | M6: Vodka | N6: =B6*Assumptions!$B$39*Assumptions!$B$40
A7: Watermelon Sugar High | B7: 50 | C7: =B7/$B$24 | D7: Lemonade | E7: 4 | F7: Watermelon juice | G7: 2 | I7: 0 | J7: 1 | K7: 0 | L7: Muddled fresh mint. WATERMELON JUICE COMES OUT OF A CARTON — 2 oz per cup, bought as its own line (Purchase List row 88). It is NOT the whole melons: those are for Monday’s Hard Reset fresca and nothing else, and they are gone by Tuesday. Nothing to blend and nothing to strain here — pour the lemonade, add the juice, muddle the mint, done. This replaced 1 oz of watermelon Torani: real juice at 2 oz reads as fruit rather than as sweetener, and the lemonade is already carrying the sugar. | M7: Blanco Tequila | N7: =B7*Assumptions!$B$39*Assumptions!$B$40
A8: A Ginger's Pickle (Big Dill Energy) | B8: 30 | C8: =B8/$B$24 | D8: Ginger ale | E8: 4 | F8: Pickle Juice | G8: 1 | I8: 0 | J8: 1 | K8: 0 | L8: Ginger ale + 1 oz pickle juice over ice, TAJIN RIM. Pickle juice is a real ingredient in the Syrup A slot as of 10 Aug 2026 (it was 0.5 oz buried in this note, where nothing could add it up) — it doubles the brine draw on 'Other Consumables' row 50. Spears come free with the jars; hand one over if asked. | M8: Whiskey | N8: =B8*Assumptions!$B$39*Assumptions!$B$40
A9: The Dr's Cream | B9: 40 | C9: =B9/$B$24 | D9: Dr Pepper | E9: 4 | F9: Vanilla | G9: 0.5 | I9: 0 | J9: 1 | K9: 0.5 | L9: DOSED DOWN 21 Aug 2026 (back-propagated from the bar guide) — vanilla cut from 1oz to 0.5oz (2 pumps), same pump-to-oz convention as the rest of the syrup builds. | M9: Bourbon | N9: =B9*Assumptions!$B$39*Assumptions!$B$40 | O9: yes
A10: The Dr's Peach Exam | B10: 40 | C10: =B10/$B$24 | D10: Dr Pepper | E10: 4 | F10: Vanilla | G10: 0.25 | H10: Peach | I10: 0.25 | J10: 1 | K10: 0.5 | L10: Dr Pepper + vanilla syrup + peach syrup + coconut cream, over ice. DOSED DOWN 20 Aug 2026 — vanilla and peach both cut from 2 pumps (0.5 oz) to 1 pump (0.25 oz, Assumptions B8a) each. Two full pumps of both flavors together was heavy-handed; one pump each still reads as a peach-vanilla Dr Pepper, just lighter, and stretches the tighter peach stock further. | M10: Whiskey | N10: =B10*Assumptions!$B$39*Assumptions!$B$40 | O10: yes
A11: SCOBY Mule | B11: 20 | C11: =B11/$B$24 | D11: Kombucha (Superberry) | E11: 4 | F11: Yuzu juice | G11: 0.5 | H11: Ginger beer | I11: 3 | J11: 0 | K11: 0 | L11: SUPERBERRY KOMBUCHA as of 14 Aug 2026. *** ANY FLAVOUR WORKS IF SUPERBERRY IS OUT — this build has always been spec’d "either", and berry is a preference, not a requirement. Substitute Island Mango or Clear Mind without asking anyone. *** Berry against the ginger and yuzu is the best of the three, and it is also the flavour with the most slack in the buy (see Packaged Sizing section 7). Kombucha over ice + 0.5 oz YUZU JUICE + agave + apple cider vinegar, topped with ginger beer. The moscow-mule shape: sharp, gingery, not sweet. Per-serving agave and ACV are on Assumptions B131/B128. YUZU REPLACED THE FRESH LEMON 10 Aug 2026, following Clear Cache — with both builds moved there is no fresh lemon left anywhere on the bar and nothing to juice but limes. Yuzu is bottled and shelf-stable, so it is a pour, not a prep job. Jigger it: at $1.54/oz it is the dearest thing behind the bar. *** ASK IF THEY WANT IT DIRTY (ADD DEW). *** A splash of Mountain Dew is the standing modifier on the kombucha builds as of 11 Aug 2026, replacing SCOBY-Dew as a named drink. It is an offer, not a default: ask, do not assume. | M11: Vodka | N11: =B11*Assumptions!$B$39*Assumptions!$B$40
A12: Thirst Trap | B12: 50 | C12: =B12/$B$24 | D12: Squirt | E12: 4 | F12: Peach | G12: 0.25 | H12: Lime juice (fresh) | I12: 0.5 | J12: 1 | K12: 0 | L12: Squirt + peach syrup + fresh lime over ice. DOSED DOWN 20 Aug 2026 — peach cut from 3 pumps (0.75 oz) to 1 pump (0.25 oz); Squirt already carries plenty of its own fruit character, peach was rounding it more than necessary. MINT CUBE IF AVAILABLE — cubes are not guaranteed, the drink is complete without one, so never hold a build waiting for one. Two-finger pinch of salt or a Tajin rim: the salt is what kills the grapefruit bitterness, and peach only softens it. Replaced Thirst Trap, where Squirt fought muddled cucumber and the soda water thinned what was left — peach rounds the grapefruit instead of competing with it. No muddling, so it is a fast build. | M12: Blanco Tequila | N12: =B12*Assumptions!$B$39*Assumptions!$B$40
A13: Sakura Kisses | B13: 33 | C13: =B13/$B$24 | D13: Green tea | E13: 4 | F13: Orange syrup | G13: 0.5 | H13: Sakura syrup | I13: 0.5 | J13: 0 | K13: 0 | L13: SATURDAY ONLY — Catboy Café finale, built to order off the green tea keg (replaces the retired Saturday aqua fresca jug). Green tea over ice + sakura syrup + orange syrup (0.5 oz each), plus passion fruit purée (Assumptions B118); mint or cucumber garnish. CHANGED 21 Aug 2026 — dropped the 2 oz orange juice pour; orange syrup now carries the orange note at 0.5 oz instead. | N13: 0
A14: Clear Cache | B14: 30 | C14: =B14/$B$24 | D14: Kombucha (Clear Mind) | E14: 4 | F14: Peach | G14: 0.25 | H14: Yuzu juice | I14: 0.5 | J14: 2 | K14: 0 | L14: Built off Dr. Clear Mind kombucha (rosemary, mint, sage, green tea). Kombucha over ice + peach syrup (DOSED DOWN 20 Aug 2026, 2 pumps/0.5 oz to 1 pump/0.25 oz — the kombucha and sage already carry most of the flavor, peach was a background note anyway) + 0.5 oz YUZU JUICE, topped with soda water. Rub a sage leaf around the cup rim and drop it in; optional pinch of salt. YUZU REPLACED THE FRESH LEMON 10 Aug 2026 — floral and more bitter-aromatic than lemon, which suits the rosemary-sage kombucha. It is bottled, so there is nothing to squeeze and nothing to keep cold. | M14: Bourbon | N14: =B14*Assumptions!$B$39*Assumptions!$B$40 | O14: yes
A15: Catboy Snot | B15: 25 | C15: =B15/$B$24 | D15: Squirt | E15: 4 | F15: Melon | G15: 0.5 | H15: Lime juice (fresh) | I15: 0.5 | J15: 0 | K15: 0 | L15: SATURDAY ONLY — Catboy Café finale, do not put it on the board before Saturday. Squirt + melon syrup + fresh lime over ice, then 1.5 oz of aloe vera juice WITH THE PULP spooned in (per-serving oz on Assumptions B147) so the cubes hang in suspension — that is the whole gag. Two-finger pinch of salt, same as Thirst Trap: the salt is what kills the grapefruit bitterness. Tint the ALOE BOTTLE (not the cup) with a pinch of blue spirulina — pale-yellow Squirt + blue reads green, and tinting per-cup comes out uneven. THE SPIRULINA JAR IS NOW BOUGHT FOR THIS ONE JOB (Purchase List row 52): Blue Screen of Death is retired, so nothing else in the workbook uses it. A pinch does it; the jar is ample. Optional basil seeds (Assumptions B150), hydrated in water ahead of service. BUY DRINKING ALOE — inner-fillet/decolorized, NOT whole-leaf or supplement aloe (aloin = laxative). | M15: Blanco Tequila | N15: =B15*Assumptions!$B$39*Assumptions!$B$40
A16: Catboy Piss | B16: 25 | C16: =B16/$B$24 | D16: Red Bull (Yellow Edition) | E16: 4 | F16: Passion fruit purée | G16: 0.5 | H16: Lime juice (fresh) | I16: 0.5 | J16: 0 | K16: 0 | L16: SATURDAY ONLY — do not put it on the board before Saturday. YELLOW EDITION RED BULL, NOT REGULAR (specified 14 Aug 2026): the drink is named for its colour, and the passion fruit purée only reads as an alarming gold off a yellow base — regular Red Bull is amber and goes muddy brown. Yellow Edition is tropical, so the passion fruit adds to it instead of fighting it. Red Bull + blanco tequila over ice, passion fruit purée and fresh lime, Tajin rim. The purée deepens the colour and its tartness cuts the Red Bull sweetness; the salty-spicy rim is what stops it tasting like a dorm drink. Red Bull comes off the Bar Add-Ons tab (12 of the 24 YELLOW cans). SATURDAY COLOUR SET: this is the yellow one — Sakura Kisses is pink and Catboy Snot is green. Keep all three distinct. | M16: Blanco Tequila | N16: =B16*Assumptions!$B$39*Assumptions!$B$40
A17: Shirley Temple of Doom | B17: 25 | C17: =B17/$B$24 | D17: Sprite | E17: 4 | F17: Cherry | G17: 0.5 | H17: Lime juice (fresh) | I17: 0.5 | J17: 2 | K17: 0 | L17: Sprite + cherry syrup (DOSED DOWN 21 Aug 2026, back-propagated from the bar guide — 3 pumps/0.75oz to 2 pumps/0.5oz) + fresh lime over ice, topped with soda water. TAJIN RIM plus a two-finger pinch of salt — cherry + chile-lime is chamoy logic, and the salt and acid are what stop it reading as candy in the heat. Same rim station as the Michelada, A Ginger's Pickle and Catboy Piss, so it adds no new workflow. No coconut cream (it was pulled from the plain Shirley Temple on row 6 as well). | M17: Vodka | N17: =B17*Assumptions!$B$39*Assumptions!$B$40 | O17: yes
A18: Shirley Mule | B18: 25 | C18: =B18/$B$24 | D18: Sprite | E18: 2 | F18: Cherry | G18: 0.75 | H18: Ginger beer | I18: 3 | J18: 0 | K18: 0 | L18: Sprite + ginger beer + cherry syrup over ice, plus a 0.5 oz fresh lime squeeze (Assumptions B154 — the two ingredient slots here are full, same situation as Tang Dynasty). BASE SWAPPED TO SPRITE 10 Aug 2026 and ginger beer raised from 2 to 3 oz: the ginger now comes entirely from the ginger beer instead of being split with ginger ale, and the pour volume is unchanged at 6.25 oz. Ginger is genuinely useful for dust-and-heat stomach and the ginger beer's bite cuts the cherry. Vodka is the default; whiskey works if someone asks. | M18: Vodka | N18: =B18*Assumptions!$B$39*Assumptions!$B$40 | O18: yes
A19: Root Access | B19: 40 | C19: =B19/$B$24 | D19: Root beer | E19: 4 | F19: Vanilla | G19: 0.5 | I19: 0 | J19: 2 | K19: 1 | L19: A dirty root beer float. 4 oz root beer + 0.5 oz vanilla syrup + 1 oz cream of coconut over ice — stir gently, it will foam. Cream of coconut instead of dairy means it will not curdle and needs no refrigeration once opened. Cherry syrup in place of vanilla is the other good build. | M19: Spiced Rum | N19: =B19*Assumptions!$B$39*Assumptions!$B$40 | O19: yes
A20: Paloma | B20: 20 | C20: =B20/$B$24 | D20: Paloma mixer | E20: 3 | J20: 5 | K20: 0 | L20: NEW 18 Aug 2026. SALT RIM. 3 oz paloma mixer + 5 oz soda water over ice, lime wedge. Optional 1.5 oz blanco tequila OR vodka — tequila is the paloma, vodka is the cleaner one and both work. Complete and good without either, sized at the standard 35% uptake like its sibling Guavascript, not the 100% the two tequila-mandatory builds use. The mixer already carries grapefruit, lime and agave, so nothing else is added by default. OPTIONAL ENHANCEMENT: a splash of watermelon juice or extra fresh lime on request — not scaled into the buy, both are already stocked for other drinks, so pouring a little into this one costs nothing extra to plan for. SPICY OPTION: 2-3 drops of Fee Brothers Habanero Bitters on request — ask before adding, it's a real kick, not a suggestion of heat. | M20: Blanco Tequila | N20: =B20*Assumptions!$B$39*Assumptions!$B$40 | O20: No — NEW, untested
A21: Ranch Water | B21: 20 | C21: =B21/$B$24 | E21: 0 | F21: Lime juice (fresh) | G21: 0.5 | I21: 0 | J21: 6 | K21: 0 | L21: SALT RIM, then 1.5 oz blanco tequila + 0.5 oz FRESH lime + 6 oz soda water over ice. Nothing else — no syrup, no sugar, no colour. SODA WATER CUT 8 oz TO 6 ON 11 Aug 2026, which brings the drink to exactly the 8 oz house pour instead of 10 and takes 40 oz off the soda water buy. It is a tighter, less watery ranch water for it. THIS IS THE "HAVE YOU GOT ANYTHING NOT TOO SWEET?" DRINK: the only genuinely dry thing on the board, and after four days of syrup that question gets asked a lot. The non-alcoholic version is on the standing board as salted soda water + lime. | M21: Blanco Tequila | N21: =B21*Assumptions!$B$222*Assumptions!$B$40
A22: Margarita | B22: 20 | C22: =B22/$B$24 | D22: Margarita mixer | E22: 4 | G22: 0 | H22: Fresh lime | I22: 1 | J22: 0 | K22: 0 | L22: SALT RIM. 4 oz margarita mixer + 1.5 oz blanco tequila over ice, then 1 oz FRESH lime and 0.5 oz agave (Assumptions B224) TO TASTE. THE LIME AND THE AGAVE ARE OPTIONAL — the mixer already contains both; start with mixer + tequila, taste, and add only if it needs it. Both stay fully costed and are bought for other drinks anyway, so leaving them out wastes nothing. *** HIBISCUS REMOVED 11 Aug 2026 — THIS IS NOW A STANDARD MARGARITA. *** It was a hibiscus margarita built on cold-steeped flower, which meant the drink could not be poured unless someone had steeped a batch the night before. With hibiscus now also feeding the Daily Tea standing tea, that prep was competing with itself. 4 oz of mixer to 1.5 oz of tequila is the mixer's own ratio. *** THE TEQUILA IS NOT OPTIONAL HERE. *** A margarita without it is not this drink — it is sized at 100% uptake on Assumptions B222, unlike every other built drink, which sizes at 35% on B39. If someone wants it dry, pour them an Iced Tea or a Bitwise instead of a diluted margarita. | M22: Blanco Tequila | N22: =B22*Assumptions!$B$222*Assumptions!$B$40
A23: Guavascript | B23: 25 | C23: =B23/$B$24 | D23: Paloma mixer | E23: 3 | H23: Guava syrup | I23: 0.5 | J23: 4.5 | K23: 0 | L23: SALT OR TAJIN RIM. 3 oz paloma mixer + 0.5 oz guava syrup + 4.5 oz soda water over ice, lime wedge. SWITCHED FROM GUAVA PUREE TO TORANI GUAVA SYRUP 19 Aug 2026 — Reàl guava purée wasn't at Total Wine and Amazon only sells it in a 3-pack; Torani Guava syrup is the same 750ml/25.4oz format as the other Torani flavors already on the truck, easier to source. Same 0.5 oz dose carried over — syrup is thinner and sweeter than purée, so taste it against the original if you get the chance; the guava character may read a little different (less pulp/body, more straight sweetness) even at the same pour. Optional 1.5 oz blanco tequila OR vodka — tequila is the paloma, vodka is the cleaner one and both work. Complete and good without either, which is why it sizes at the standard 35% uptake rather than the 100% the two tequila builds use. OPTIONAL ENHANCEMENT: a splash of watermelon juice or extra fresh lime on request — not scaled into the buy, both are already stocked for other drinks. CONTINGENCY, 19 Aug 2026: if guava (syrup or purée) doesn't turn up at Total Wine this weekend and Amazon stays unreliable, the fallback is pulling Guavascript from the menu entirely rather than serving it without its one twist ingredient. | M23: Blanco Tequila | N23: =B23*Assumptions!$B$39*Assumptions!$B$40 | O23: No — NEW, untested
A24: TOTAL BUILT-TO-ORDER SERVINGS | B24: =SUM(B3:B23) | N24: =SUM(N3:N23) | O24: Renamed from "dirty soda" — row 21 (Rawhide) is a tequila build with no canned base at all, and rows 22 and 23 carry a bottled mixer in the base slot rather than a soda: Localhost takes 4 oz of margarita mixer as of 11 Aug 2026, Guavascript 3 oz of paloma mixer. All three still roll into the "Dirty soda — canned base" bucket on Totals by Type row 10, which is a slight misnomer for three of the twenty-one. NOTE the base slot is read by "Base Soda — Cans" (which matches on soda names only, so the two mixers fall through harmlessly) AND by "Other Consumables" rows 55 and 57, which is what actually buys them — that is why the mixers sit there rather than in a syrup slot.
A26: SECRET PARTY — off-menu, NOT included in TOTAL BUILT-TO-ORDER SERVINGS (B24). Camp-mate request, 21 Aug 2026. Keep off the standing board and the Menu Board — a separate menu is being built just for this event (Service Availability section 6, Start Here hard rule).
A27: Recipe | B27: Servings | C27: (share) | D27: Base soda | E27: Base oz | F27: Syrup A | G27: A oz | H27: Syrup B | I27: B oz | J27: Soda water oz | K27: Coconut cream oz | L27: Special / garnish | M27: Liquor (optional) | N27: Liquor oz needed | O27: Tested?
A28: Vodka Shot | B28: =Assumptions!$B$286 | C28: =B28/$B$34 | D28: — | L28: SECRET PARTY. Neat or on the rocks — no mixer, no build, fastest possible pour. This is the "I just need it in a cup" option when the line gets long. | M28: Vodka | N28: =B28*Assumptions!$B$277*Assumptions!$B$40 | O28: No — NEW, off-menu
A29: Vodka Cranberry | B29: =Assumptions!$B$287 | C29: =B29/$B$34 | D29: Cranberry juice | E29: =Assumptions!$B$293 | L29: SECRET PARTY. Vodka + cranberry juice over ice. One pour, no muddle — built for a fast line. | M29: Vodka | N29: =B29*Assumptions!$B$277*Assumptions!$B$40 | O29: No — NEW, off-menu
A30: Screwdriver | B30: =Assumptions!$B$288 | C30: =B30/$B$34 | D30: Orange juice | E30: =Assumptions!$B$294 | L30: SECRET PARTY. Vodka + orange juice over ice. | M30: Vodka | N30: =B30*Assumptions!$B$277*Assumptions!$B$40 | O30: No — NEW, off-menu
A31: Vodka Red Bull | B31: =Assumptions!$B$289 | C31: =B31/$B$34 | D31: Red Bull | E31: 4 | L31: SECRET PARTY. Vodka + Red Bull over ice — draws off the Red Bull already stocked for the standing board (Bar Add-Ons), not a new purchase. Either flavor works; save the Yellow Edition for Catboy Piss if both land the same night. | M31: Vodka | N31: =B31*Assumptions!$B$277*Assumptions!$B$40 | O31: No — NEW, off-menu
A32: Vodka Lemonade | B32: =Assumptions!$B$290 | C32: =B32/$B$34 | D32: Lemonade | E32: 4 | L32: SECRET PARTY. Vodka + lemonade over ice — draws off the lemonade already stocked for Watermelon Sugar High, not a new purchase. | M32: Vodka | N32: =B32*Assumptions!$B$277*Assumptions!$B$40 | O32: No — NEW, off-menu
A33: Vodka Soda | B33: =Assumptions!$B$291 | C33: =B33/$B$34 | D33: Soda water | E33: 4 | L33: SECRET PARTY. Vodka + soda water + lime squeeze — draws off soda water already stocked, assumed sufficient for this event (no extra purchase added, per your 21 Aug 2026 call). REPLACED VODKA TONIC 21 Aug 2026. | M33: Vodka | N33: =B33*Assumptions!$B$277*Assumptions!$B$40 | O33: No — NEW, off-menu
A34: TOTAL SECRET PARTY SERVINGS | B34: =SUM(B28:B33) | N34: =SUM(N28:N33)

Sheet Jug Recipes
A1: Jug Recipes — the nightly 10 L batch, and what goes in it
A2: One batch per night. SET THE NUMBER OF JUGS IN COLUMN B — servings and every ingredient quantity scale off it automatically, and the buy quantities at the bottom of this tab follow. Wednesday already runs 3 jugs for the next-door party. Ingredients are listed strongest-first with water/ice fills last, so nothing real hides behind a zero. READ THE NOTES COLUMN: Sunday’s Cherry Bomb is built in two halves, and Thursday’s Fee Brothers Cherry Bitters go into the cup rather than the jug. SATURDAY AND THE CLOSING SUNDAY POUR THE SAME PEACH GREEN ICED TEA — two separate overnight steeps, one started Friday night and one Saturday night. Day-by-day prep is on ‘Daily Schedule’.
A3: Day | B3: # Jugs | C3: Offering | D3: Format | E3: Servings | F3: Ingredient 1 | G3: Ing 1 oz | H3: Ingredient 2 | I3: Ing 2 oz | J3: Ingredient 3 | K3: Ing 3 oz | L3: Ingredient 4 | M3: Ing 4 oz | N3: Ingredient 5 | O3: Ing 5 oz | P3: Alcohol (optional) | Q3: Alcohol — 2nd option (SIGNAGE ONLY) | R3: Alcohol oz needed | S3: Notes
A4: Sunday | B4: 1 | C4: Cherry Bomb (Cherry Limeade) | D4: =IF(B4=1,"10 L jug",B4&" x 10 L jugs") | E4: =B4*Assumptions!$B$117 | F4: Sprite | G4: =E4*2.5 | H4: Cherry syrup | I4: =E4*1.5 | J4: Lime juice (bottled) | K4: =E4*1 | L4: Soda water | M4: =E4*1 | N4: Maraschino cherries (garnish) | O4: 0 | P4: Vodka | Q4: Blanco Tequila | R4: =E4*Assumptions!$B$39*Assumptions!$B$40 | S4: Sonic-style cherry limeade, opening night. Cherry syrup doubled to 1.5 oz/serving — at 0.75 against a full ounce of bottled lime it read sour and thin. Lime:syrup now 1:1.5. BUILD IT IN TWO HALVES: this pours in a 1-2 hour arrival window, so make ~17 servings, then build the second half when the first is a third down. The Sprite and soda water stay fizzy in the bottle until they are needed, which is the whole reason this one gets away with carbonation. ~0.75 tsp salt per half.
A5: Monday | B5: 1 | C5: Hard Reset (Watermelon-Mint Aqua Fresca) | D5: =IF(B5=1,"10 L jug",B5&" x 10 L jugs") | E5: =B5*Assumptions!$B$117 | F5: Watermelon (fresh, blended) | G5: =E5*Assumptions!$B$51 | H5: Agave syrup | I5: =E5*Assumptions!$B$54 | J5: Fresh mint (blended) | K5: 5 | L5: Fresh lime (squeeze) | M5: 0 | N5: Water (fill) | O5: 0 | P5: Blanco Tequila | Q5: Vodka | R5: =E5*Assumptions!$B$39*Assumptions!$B$40 | S5: Blend melon chunks with a handful of mint, strain rough, add agave + lime, top with STILL water to fill the jug (traditional fresca — skip tonic; optional soda-water splash per cup for fizz). ~1-2 melons per batch; melons travel fine unrefrigerated. Optional Blanco Tequila per cup makes it a watermelon margarita — melon, mint and lime are already the whole drink.
A6: Tuesday | B6: 1 | C6: Smoke Test (Lapsang Souchong Lemonade) | D6: =IF(B6=1,"10 L jug",B6&" x 10 L jugs") | E6: =B6*Assumptions!$B$117 | F6: Lapsang souchong | G6: =E6*Assumptions!$B$142 | H6: Lemonade | I6: =E6*3 | J6: Lime juice (bottled) | K6: =E6*0.5 | L6: Water/ice (fill) | M6: 0 | O6: 0 | P6: Whiskey | Q6: Spiced Rum | R6: =E6*Assumptions!$B$39*Assumptions!$B$40 | S6: Cold-steep ~2 oz of lapsang leaf overnight (or steep hot and chill) to make ~1.3 gal of STRONG smoky tea, then build the jug: 5 oz strong tea + 3 oz lemonade + 0.5 oz lime per serving, topped with water/ice. ~1.5 tsp salt per jug. Naturally still, so nothing to go flat. WARNING: lapsang runs from 'campfire' to 'ashtray' fast — brew it weaker than you think and taste before committing the jug. Optional Whiskey leans into the smoke.
A7: Wednesday | B7: 2 | C7: Red Flag (Agua de Jamaica) | D7: =IF(B7=1,"10 L jug",B7&" x 10 L jugs") | E7: =B7*Assumptions!$B$117 | F7: Dried hibiscus | G7: =E7*Assumptions!$B$124 | H7: Agave syrup | I7: =E7*0.5 | J7: Lime juice (bottled) | K7: =E7*0.5 | L7: Water (fill) | M7: 0 | O7: 0 | P7: Blanco Tequila | Q7: Spiced Rum | R7: =E7*Assumptions!$B$39*Assumptions!$B$40 | S7: Hibiscus agua fresca — steep the dried flowers, strain, cool, sweeten with agave, fill with cold water/ice. Cold-steeping overnight works too. TWO JUGS PREPPED (66 servings) — double a normal night, which is what the next-door party needs. A THIRD IS BACKUP ONLY and costs nothing to keep in reserve: one 1 lb bag of hibiscus is ~188 servings' worth, so the flowers for a third and fourth jug are already on the truck. If the party outruns two jugs, make the extra as concentrate — see 'Jug Build Steps'. Agave raised to 0.5 oz/serving; hibiscus is far tarter than the watermelon and was getting less sugar, which was backwards. Naturally still. ~1.5 tsp salt per jug. STAINS.
A8: Thursday | B8: 1 | C8: Gradient Descent (Malibu Sunrise) | D8: =IF(B8=1,"10 L jug",B8&" x 10 L jugs") | E8: =B8*Assumptions!$B$117 | F8: Orange juice | G8: =E8*3 | H8: Pineapple juice | I8: =E8*2.5 | J8: Fee Brothers Cherry Bitters (garnish, a few dashes per cup — not batched) | K8: 0 | L8: Lime juice (bottled) | M8: =E8*0.5 | N8: Passion fruit purée | O8: =E8*0.5 | P8: Coconut Rum | Q8: Spiced Rum | R8: =E8*Assumptions!$B$39*Assumptions!$B$40 | S8: Batch OJ + pineapple + passion fruit + lime in the jug, then top with water/ice. JUICE TRIMMED AGAIN — OJ 4 to 3 oz, pineapple 3 to 2.5 oz. At 8.5 oz of juice in a 10 oz cup this was essentially undiluted juice, the sugariest thing on the board and the most likely to make someone feel worse in the heat. Add 2-3 dashes of Fee Brothers Cherry Bitters to each CUP, not the jug, for a cherry note and a light color vein — swapped off grenadine 18 Aug 2026. Dashes are a subtler effect than the old 0.5 oz syrup drizzle: expect a soft tint, not the heavy syrup-sink gradient grenadine gave. ~1.5 tsp salt per jug. Optional Malibu per cup.
A9: Friday | B9: 1 | C9: Whore-chata | D9: =IF(B9=1,"10 L jug",B9&" x 10 L jugs") | E9: =B9*Assumptions!$B$117 | F9: Rice Dream Horchata (ready-to-drink) | G9: =E9*5 | H9: Coconut cream | I9: =E9*0.5 | J9: Vanilla syrup | K9: =E9*0.25 | L9: Water/ice (fill) | M9: 0 | P9: Spiced Rum | Q9: Bourbon | R9: =E9*Assumptions!$B$39*Assumptions!$B$40 | S9: Rice-milk base + cinnamon/vanilla syrup, batched cold; optional Spiced Rum float. SWITCHED TO READY-TO-DRINK 18 Aug 2026 — Rice Dream Horchata, 32 oz bottles, poured straight in rather than mixed from concentrate. Same 5 oz/serving pour as before (RAISED from 3 oz to 5 oz on the original concentrate build, so it stays generous here too); at 3 oz in a 10 oz cup it read as cinnamon water. Horchata should be opaque and rich. See Purchase List row 46 and Assumptions B16-18 (retired) for the sourcing history.
A10: Saturday | B10: 1 | C10: Sleep Mode (Peach Green Iced Tea) | D10: =IF(B10=1,"10 L jug",B10&" x 10 L jugs") | E10: =B10*Assumptions!$B$117 | F10: Green tea (cold-steeped) | G10: =E10*8 | H10: Peach syrup | I10: =E10*1 | J10: Lemon juice (bottled) | K10: =E10*0.5 | L10: Agave syrup | M10: =E10*0.25 | N10: Water/ice (fill) | O10: 0 | P10: Whiskey | Q10: Vodka | R10: =E10*Assumptions!$B$39*Assumptions!$B$40 | S10: THE SAME DRINK AS THE CLOSING SUNDAY’S GRACEFUL SHUTDOWN, ON PURPOSE. Saturday is the Catboy Café night — Sakura Kisses, Catboy Snot and Catboy Piss all land built-to-order on top of the full standing board — so the jug has to be the one thing nobody has to think about. Cold-steeped green tea, peach syrup, fresh lemon, a little agave. STEEP IT FRIDAY NIGHT with the rest of the Saturday prep, in its own sealed, labelled container; Sunday’s jug gets a SECOND steep on Saturday night. Naturally still, so nothing goes flat across a long night, and nothing needs stirring mid-service. ~1.5 tsp salt per jug. Taste BEFORE the ice — peach syrup varies, and this should read as tea with peach behind it, not peach squash. REPLACED BLUE SCREEN OF DEATH: the DIY Baja Blast wanted a per-cup Mountain Dew top-up from a recapped 2 L and a spirulina jug stirred every 20 minutes, which is the last thing the busiest night of the week needs. LEMON IS BOTTLED FOR THIS JUG (Purchase List row 44). 16.5 oz into a 10 L batch is about a dozen hand-squeezed lemons for something nobody can taste against the peach syrup and the tea. The fresh lemons are reserved for the per-drink squeezes on SCOBY Mule and Clear Cache.
A11: Sunday (closing) | B11: 1 | C11: Graceful Shutdown (Peach Green Iced Tea) | D11: =IF(B11=1,"10 L jug",B11&" x 10 L jugs") | E11: =B11*Assumptions!$B$117 | F11: Green tea (cold-steeped) | G11: =E11*8 | H11: Peach syrup | I11: =E11*1 | J11: Lemon juice (bottled) | K11: =E11*0.5 | L11: Agave syrup | M11: =E11*0.25 | N11: Water/ice (fill) | O11: 0 | P11: Whiskey | Q11: Vodka | R11: =E11*Assumptions!$B$39*Assumptions!$B$40 | S11: CLOSING SUNDAY, DAYTIME — the extra service day, not a night jug. Cold-steeped green tea, peach syrup, fresh lemon and a little agave. Cheapest jug of the week by a distance: the green tea comes out of the 100-bag camp box that camp barely touches, and the agave and lemons are already on the list. Serve it long over ice; cut it with soda water for anyone who wants it unsweetened. Steep the tea SATURDAY NIGHT — it is the one prep job that survives the busiest day of the week. LEMON IS BOTTLED FOR THIS JUG (Purchase List row 44). 16.5 oz into a 10 L batch is about a dozen hand-squeezed lemons for something nobody can taste against the peach syrup and the tea. The fresh lemons are reserved for the per-drink squeezes on SCOBY Mule and Clear Cache.
A12: ANY NIGHT | B12: — | C12: Turtle Soup (Mix of leftover alcohol) | S12: This is JUST for signage purposes, it will be made from whatever is left over.
A13: BACKUP | B13: — | C13: Salted Limeade (spare jug — no extra shopping) | D13: 10 L jug | S13: Fallback if a night runs dry or we want a 7th jug: lime juice 1oz + agave 0.5oz + water/ice to fill + ~1.5 tsp salt per jug. Deliberately left at 0 servings so it buys nothing — by the back half of the week we will already have the lime, syrup and salt on hand. Give it a serving count only if we decide to actually run it.
C14: Sakura Kisses (Described in Built Drinks)
A17: INGREDIENT TOTALS (jug-batch buys) | B17: Total oz | C17: +buffer | D17: Units to buy | E17: $/unit | F17: Subtotal | G17: Note
A18: Watermelon (whole melons) | B18: =SUMPRODUCT(('Jug Recipes'!$F$4:$F$15="Watermelon (fresh, blended)")*'Jug Recipes'!$G$4:$G$15)+SUMPRODUCT(('Jug Recipes'!$H$4:$H$15="Watermelon (fresh, blended)")*'Jug Recipes'!$I$4:$I$15)+SUMPRODUCT(('Jug Recipes'!$J$4:$J$15="Watermelon (fresh, blended)")*'Jug Recipes'!$K$4:$K$15)+SUMPRODUCT(('Jug Recipes'!$L$4:$L$15="Watermelon (fresh, blended)")*'Jug Recipes'!$M$4:$M$15)+SUMPRODUCT(('Jug Recipes'!$N$4:$N$15="Watermelon (fresh, blended)")*'Jug Recipes'!$O$4:$O$15) | C18: =B18*(1+Assumptions!$B$5) | D18: =CEILING(C18/Assumptions!$B$76,1) | E18: =Assumptions!$B$77 | F18: =D18*E18 | G18: Mon fresca — blend & strain
A19: Agave syrup (bottles) | B19: =SUMPRODUCT(('Jug Recipes'!$F$4:$F$15="Agave syrup")*'Jug Recipes'!$G$4:$G$15)+SUMPRODUCT(('Jug Recipes'!$H$4:$H$15="Agave syrup")*'Jug Recipes'!$I$4:$I$15)+SUMPRODUCT(('Jug Recipes'!$J$4:$J$15="Agave syrup")*'Jug Recipes'!$K$4:$K$15)+SUMPRODUCT(('Jug Recipes'!$L$4:$L$15="Agave syrup")*'Jug Recipes'!$M$4:$M$15)+SUMPRODUCT(('Jug Recipes'!$N$4:$N$15="Agave syrup")*'Jug Recipes'!$O$4:$O$15) | C19: =B19*(1+Assumptions!$B$5) | D19: =CEILING(C19/Assumptions!$B$132,1) | E19: =Assumptions!$B$133 | F19: =D19*E19 | G19: Mon fresca + Wed Red Flag
A20: TAB TOTAL (rows above + below) | F20: =F18+F19+SUM(F23:F32)
A21: Jug-format servings (for total-servings calc) | B21: =SUM(E4:E15)
A22: New special ingredients (Sun Cherry Bomb / Thu sunrise / Sat + Sun peach tea):
A23: Orange juice (64oz cartons) | B23: =SUMPRODUCT(('Jug Recipes'!$F$4:$F$15="Orange juice")*'Jug Recipes'!$G$4:$G$15)+SUMPRODUCT(('Jug Recipes'!$H$4:$H$15="Orange juice")*'Jug Recipes'!$I$4:$I$15)+SUMPRODUCT(('Jug Recipes'!$J$4:$J$15="Orange juice")*'Jug Recipes'!$K$4:$K$15)+SUMPRODUCT(('Jug Recipes'!$L$4:$L$15="Orange juice")*'Jug Recipes'!$M$4:$M$15)+SUMPRODUCT(('Jug Recipes'!$N$4:$N$15="Orange juice")*'Jug Recipes'!$O$4:$O$15) | C23: =B23*(1+Assumptions!$B$5) | D23: =CEILING(C23/Assumptions!$B$69,1) | E23: =Assumptions!$B$70 | F23: =D23*E23 | G23: Thu sunrise + Sat fresca
A24: Pineapple juice (24 x 8 oz cans) | B24: =SUMPRODUCT(('Jug Recipes'!$F$4:$F$15="Pineapple juice")*'Jug Recipes'!$G$4:$G$15)+SUMPRODUCT(('Jug Recipes'!$H$4:$H$15="Pineapple juice")*'Jug Recipes'!$I$4:$I$15)+SUMPRODUCT(('Jug Recipes'!$J$4:$J$15="Pineapple juice")*'Jug Recipes'!$K$4:$K$15)+SUMPRODUCT(('Jug Recipes'!$L$4:$L$15="Pineapple juice")*'Jug Recipes'!$M$4:$M$15)+SUMPRODUCT(('Jug Recipes'!$N$4:$N$15="Pineapple juice")*'Jug Recipes'!$O$4:$O$15) | C24: =B24*(1+Assumptions!$B$5) | D24: =CEILING(C24/Assumptions!$B$71,1) | E24: =Assumptions!$B$72 | F24: =D24*E24 | G24: Thu sunrise
A25: Grenadine (bottles) — RETIRED 18 Aug 2026, replaced by Fee Brothers Cherry Bitters (Purchase List) | B25: =SUMPRODUCT(('Jug Recipes'!$F$4:$F$15="Grenadine")*'Jug Recipes'!$G$4:$G$15)+SUMPRODUCT(('Jug Recipes'!$H$4:$H$15="Grenadine")*'Jug Recipes'!$I$4:$I$15)+SUMPRODUCT(('Jug Recipes'!$J$4:$J$15="Grenadine")*'Jug Recipes'!$K$4:$K$15)+SUMPRODUCT(('Jug Recipes'!$L$4:$L$15="Grenadine")*'Jug Recipes'!$M$4:$M$15)+SUMPRODUCT(('Jug Recipes'!$N$4:$N$15="Grenadine")*'Jug Recipes'!$O$4:$O$15) | C25: =B25*(1+Assumptions!$B$5) | D25: =CEILING(C25/Assumptions!$B$73,1) | E25: =Assumptions!$B$74 | F25: =D25*E25 | G25: RETIRED. Reads $0 on purpose — no ingredient is named "Grenadine" in the recipe grid any more, so the SUMPRODUCT above naturally zeroes. The Thursday jug's garnish is now Fee Brothers Cherry Bitters, bought as a flat bottle on Purchase List (was row 51, the old Grenadine line).
A26: Blue spirulina (jar) | D26: 1 | E26: =Assumptions!$B$75 | F26: =D26*E26 | G26: Grams not oz. NO LONGER A JUG INGREDIENT — Blue Screen of Death is retired and nothing in the jug block uses it. The jar is kept for exactly one job: tinting the Catboy Snot aloe bottle on Saturday (‘Dirty Soda - Built Drinks’ row 15). A pinch does it, so one 30 g jar is far more than enough, and there is no smaller sensible buy. Set the qty in column D to 0 if you drop the green tint as well.
A27: Lime juice (48oz bottles) | B27: =SUMPRODUCT(('Jug Recipes'!$F$4:$F$15="Lime juice (bottled)")*'Jug Recipes'!$G$4:$G$15)+SUMPRODUCT(('Jug Recipes'!$H$4:$H$15="Lime juice (bottled)")*'Jug Recipes'!$I$4:$I$15)+SUMPRODUCT(('Jug Recipes'!$J$4:$J$15="Lime juice (bottled)")*'Jug Recipes'!$K$4:$K$15)+SUMPRODUCT(('Jug Recipes'!$L$4:$L$15="Lime juice (bottled)")*'Jug Recipes'!$M$4:$M$15)+SUMPRODUCT(('Jug Recipes'!$N$4:$N$15="Lime juice (bottled)")*'Jug Recipes'!$O$4:$O$15)+SUMPRODUCT(('Dirty Soda - Built Drinks'!$H$3:$H$23="Lime juice (bottled)")*'Dirty Soda - Built Drinks'!$I$3:$I$23*'Dirty Soda - Built Drinks'!$B$3:$B$23) | C27: =B27*(1+Assumptions!$B$5) | D27: =CEILING(C27/Assumptions!$B$78,1) | E27: =Assumptions!$B$79 | F27: =D27*E27 | G27: Wed Cherry Limeade
A28: Maraschino cherries (jars) | D28: 2 | E28: =Assumptions!$B$80 | F28: =D28*E28 | G28: One cherry + juice splash per Wed cup (~35-40 cherries)
A29: Dried hibiscus (lb bags) | B29: =SUMPRODUCT(('Jug Recipes'!$F$4:$F$15="Dried hibiscus")*'Jug Recipes'!$G$4:$G$15)+SUMPRODUCT(('Jug Recipes'!$H$4:$H$15="Dried hibiscus")*'Jug Recipes'!$I$4:$I$15)+SUMPRODUCT(('Jug Recipes'!$J$4:$J$15="Dried hibiscus")*'Jug Recipes'!$K$4:$K$15)+SUMPRODUCT(('Jug Recipes'!$L$4:$L$15="Dried hibiscus")*'Jug Recipes'!$M$4:$M$15)+SUMPRODUCT(('Jug Recipes'!$N$4:$N$15="Dried hibiscus")*'Jug Recipes'!$O$4:$O$15)+'Dirty Soda - Built Drinks'!$B$22*Assumptions!$B$223 | C29: =B29*(1+Assumptions!$B$5) | D29: =CEILING(C29/Assumptions!$B$125,1) | E29: =Assumptions!$B$126 | F29: =D29*E29 | G29: Wed Red Flag — packs tiny and shelf-stable. LOCALHOST DROPPED HIBISCUS 11 Aug 2026 and became a standard margarita, so the Red Flag jug is the only committed draw again (~5.6 oz of the 16 oz bag). *** THE ~10.4 oz OF SPARE FLOWER IS SPOKEN FOR BY THE DAILY TEA STANDING TEA (Assumptions B252-B255) — do not reallocate it without checking there. ***
A30: Lapsang souchong (loose leaf) | B30: =SUMPRODUCT(('Jug Recipes'!$F$4:$F$15="Lapsang souchong")*'Jug Recipes'!$G$4:$G$15)+SUMPRODUCT(('Jug Recipes'!$H$4:$H$15="Lapsang souchong")*'Jug Recipes'!$I$4:$I$15)+SUMPRODUCT(('Jug Recipes'!$J$4:$J$15="Lapsang souchong")*'Jug Recipes'!$K$4:$K$15)+SUMPRODUCT(('Jug Recipes'!$L$4:$L$15="Lapsang souchong")*'Jug Recipes'!$M$4:$M$15)+SUMPRODUCT(('Jug Recipes'!$N$4:$N$15="Lapsang souchong")*'Jug Recipes'!$O$4:$O$15) | C30: =B30*(1+Assumptions!$B$5) | D30: =CEILING(C30/Assumptions!$B$143,1) | E30: =Assumptions!$B$144 | F30: =D30*E30 | G30: Tue Smoke Test — packs to nothing *** PART OF THIS IS SPOKEN FOR BY THE DAILY TEA STANDING TEA (Assumptions B252-B255) — do not reallocate the spare without checking there. ***
A31: Green tea teabags (Sun closing jug) | B31: =SUMPRODUCT(('Jug Recipes'!$F$4:$F$15="Green tea (cold-steeped)")*'Jug Recipes'!$G$4:$G$15)+SUMPRODUCT(('Jug Recipes'!$H$4:$H$15="Green tea (cold-steeped)")*'Jug Recipes'!$I$4:$I$15)+SUMPRODUCT(('Jug Recipes'!$J$4:$J$15="Green tea (cold-steeped)")*'Jug Recipes'!$K$4:$K$15)+SUMPRODUCT(('Jug Recipes'!$L$4:$L$15="Green tea (cold-steeped)")*'Jug Recipes'!$M$4:$M$15)+SUMPRODUCT(('Jug Recipes'!$N$4:$N$15="Green tea (cold-steeped)")*'Jug Recipes'!$O$4:$O$15) | C31: =B31*(1+Assumptions!$B$5) | D31: =CEILING(C31/128*Assumptions!$B$178,1) | E31: 0 | F31: 0 | G31: teabags — DRAWN FROM THE CAMP BOX, not a separate buy. TWO jugs now steep green tea, Saturday and the closing Sunday, so this roughly doubled — and it still barely dents the box. The green tea box on Purchase List row 62 holds Assumptions B179 bags; the camp iced tea and both jugs together use about a quarter of them. $0 here ON PURPOSE: costing it again would double-buy a box that goes home mostly full either way. *** PART OF THIS IS SPOKEN FOR BY THE DAILY TEA STANDING TEA (Assumptions B252-B255) — do not reallocate the spare without checking there. ***
A32: Lemon juice (32oz bottles) | B32: =SUMPRODUCT(('Jug Recipes'!$F$4:$F$15="Lemon juice (bottled)")*'Jug Recipes'!$G$4:$G$15)+SUMPRODUCT(('Jug Recipes'!$H$4:$H$15="Lemon juice (bottled)")*'Jug Recipes'!$I$4:$I$15)+SUMPRODUCT(('Jug Recipes'!$J$4:$J$15="Lemon juice (bottled)")*'Jug Recipes'!$K$4:$K$15)+SUMPRODUCT(('Jug Recipes'!$L$4:$L$15="Lemon juice (bottled)")*'Jug Recipes'!$M$4:$M$15)+SUMPRODUCT(('Jug Recipes'!$N$4:$N$15="Lemon juice (bottled)")*'Jug Recipes'!$O$4:$O$15) | C32: =B32*(1+Assumptions!$B$5) | D32: =CEILING(C32/Assumptions!$B$227,1) | E32: =Assumptions!$B$228 | F32: =D32*E32 | G32: Sat Sleep Mode + Sun Graceful Shutdown — 16.5 oz each. Mirrors the bottled lime on row 27: batch jugs take bottled, per-drink squeezes take fresh.

Sheet Jug Build Steps
A1: Jug Build Steps — how to actually make each night
A3: The procedure card. 'Jug Recipes' says WHAT goes in; this says HOW and IN WHAT ORDER. Quantities in column F are live — they follow the # jugs on Jug Recipes, so they stay right if a night gets scaled up. Written for someone who has never made these, reading in the dark. FOR THE DESIGNER: this is one card per night, plus the standing block at the bottom which goes on the permanent card alongside the Main Instructions from 'Daily Schedule'.
A5: Day | B5: Drink | C5: Start by / time needed | D5: NIGHT BEFORE | E5: BUILD — in this order | F5: Batch quantities (live) | G5: AT SERVICE
A6: ='Jug Recipes'!A4 | B6: ='Jug Recipes'!C4 | C6: 45 min before the party. Shortest build of the week. | D6: Nothing. | E6: BUILD IN HALVES — this pours in a 1-2 hour window. 1. Half the cherry syrup + half the lime into the dispenser. 2. Cold water to about half full. 3. Half the Sprite and soda water, poured DOWN THE INSIDE WALL. One gentle stir — do not whisk, you will kill the fizz. 4. Ice to fill. ~0.75 tsp salt. 5. Taste. 6. Build the second half the same way when the first is a third down. Do NOT pre-mix both. | F6: =IF('Jug Recipes'!G4>0,'Jug Recipes'!F4&" "&TEXT('Jug Recipes'!G4,"0.#")&" oz"&CHAR(10),"")&IF('Jug Recipes'!I4>0,'Jug Recipes'!H4&" "&TEXT('Jug Recipes'!I4,"0.#")&" oz"&CHAR(10),"")&IF('Jug Recipes'!K4>0,'Jug Recipes'!J4&" "&TEXT('Jug Recipes'!K4,"0.#")&" oz"&CHAR(10),"")&IF('Jug Recipes'!M4>0,'Jug Recipes'!L4&" "&TEXT('Jug Recipes'!M4,"0.#")&" oz"&CHAR(10),"")&IF('Jug Recipes'!O4>0,'Jug Recipes'!N4&" "&TEXT('Jug Recipes'!O4,"0.#")&" oz"&CHAR(10),"") | G6: Pour and go. Maraschino cherry on top if supplies allow. Flatness is not a problem here — it is gone inside two hours.
A7: ='Jug Recipes'!A5 | B7: ='Jug Recipes'!C5 | C7: 90 minutes. THE LONGEST BUILD OF THE WEEK — start early. | D7: Nothing. Melons travel fine unrefrigerated. | E7: 1. Cut 2 melons into chunks. Reckon ~90 oz of juice per melon. 2. Blend in batches with a handful of mint. The 12 V blender is small — plan on 4-6 rounds. 3. Strain rough through the fine mesh into a gallon container. Some pulp is good; you are not making juice. 4. Strained juice + agave + lime into the dispenser. 5. STILL water to fill. No tonic, no soda. 6. 1.5 tsp salt. Stir. | F7: =IF('Jug Recipes'!G5>0,'Jug Recipes'!F5&" "&TEXT('Jug Recipes'!G5,"0.#")&" oz"&CHAR(10),"")&IF('Jug Recipes'!I5>0,'Jug Recipes'!H5&" "&TEXT('Jug Recipes'!I5,"0.#")&" oz"&CHAR(10),"")&IF('Jug Recipes'!K5>0,'Jug Recipes'!J5&" "&TEXT('Jug Recipes'!K5,"0.#")&" oz"&CHAR(10),"")&IF('Jug Recipes'!M5>0,'Jug Recipes'!L5&" "&TEXT('Jug Recipes'!M5,"0.#")&" oz"&CHAR(10),"")&IF('Jug Recipes'!O5>0,'Jug Recipes'!N5&" "&TEXT('Jug Recipes'!O5,"0.#")&" oz"&CHAR(10),"") | G7: Stir before each pour — pulp settles. Soda-water splash per cup if someone wants fizz. Blanco Tequila makes it a watermelon margarita.
A8: ='Jug Recipes'!A6 | B8: ='Jug Recipes'!C6 | C8: 30 min, plus an overnight steep started Monday. | D8: MONDAY NIGHT: cold-steep ~2 oz of lapsang leaf in ~1.3 gal of cold water. Seal it. | E8: 1. STRAIN THE LEAVES OUT FIRST. Left in, it keeps extracting and goes from campfire to ashtray. 2. TASTE THE TEA ON ITS OWN. This is the decision point — if it is acrid, cut it with water BEFORE it meets anything else. 3. Strong tea + lemonade + lime into the dispenser. 4. Water/ice to fill. 1.5 tsp salt. 5. Taste again. | F8: =IF('Jug Recipes'!G6>0,'Jug Recipes'!F6&" "&TEXT('Jug Recipes'!G6,"0.#")&" oz"&CHAR(10),"")&IF('Jug Recipes'!I6>0,'Jug Recipes'!H6&" "&TEXT('Jug Recipes'!I6,"0.#")&" oz"&CHAR(10),"")&IF('Jug Recipes'!K6>0,'Jug Recipes'!J6&" "&TEXT('Jug Recipes'!K6,"0.#")&" oz"&CHAR(10),"")&IF('Jug Recipes'!M6>0,'Jug Recipes'!L6&" "&TEXT('Jug Recipes'!M6,"0.#")&" oz"&CHAR(10),"")&IF('Jug Recipes'!O6>0,'Jug Recipes'!N6&" "&TEXT('Jug Recipes'!O6,"0.#")&" oz"&CHAR(10),"") | G8: Naturally still, so nothing is going flat. No rush on this one.
A9: ='Jug Recipes'!A7 | B9: ='Jug Recipes'!C7 | C9: 2 hours. Still the biggest build of the week. | D9: TUESDAY NIGHT: cold-steep the dried hibiscus for TWO jugs. Steeping hot on the day works too, but it then has to cool. | E9: 1. Steep, then STRAIN THOROUGHLY. Flowers left in turn it bitter and astringent. 2. Two jugs, two dispensers — it fits, no juggling. 3. Per dispenser: hibiscus tea + agave + lime + cold water to fill. 4. 1.5 tsp salt per jug. Taste — it should read properly sweet, not just tart. 5. IF THE PARTY OUTRUNS TWO JUGS: you have flowers for plenty more. Steep a third batch as CONCENTRATE and hold it in a 1-gallon container — concentrate takes about a third the space of finished drink — then cut it into a dispenser as one empties. | F9: =IF('Jug Recipes'!G7>0,'Jug Recipes'!F7&" "&TEXT('Jug Recipes'!G7,"0.#")&" oz"&CHAR(10),"")&IF('Jug Recipes'!I7>0,'Jug Recipes'!H7&" "&TEXT('Jug Recipes'!I7,"0.#")&" oz"&CHAR(10),"")&IF('Jug Recipes'!K7>0,'Jug Recipes'!J7&" "&TEXT('Jug Recipes'!K7,"0.#")&" oz"&CHAR(10),"")&IF('Jug Recipes'!M7>0,'Jug Recipes'!L7&" "&TEXT('Jug Recipes'!M7,"0.#")&" oz"&CHAR(10),"")&IF('Jug Recipes'!O7>0,'Jug Recipes'!N7&" "&TEXT('Jug Recipes'!O7,"0.#")&" oz"&CHAR(10),"") | G9: WARN PEOPLE IT STAINS — cups, hands, clothing, especially anything white. Naturally still, so there is no hurry once it is built.
A10: ='Jug Recipes'!A8 | B10: ='Jug Recipes'!C8 | C10: 30 min. | D10: Nothing. | E10: 1. OJ + pineapple + passion fruit purée + lime into the dispenser. 2. Water/ice to fill. 1.5 tsp salt. 3. Stir well — the purée sinks. 4. THE BITTERS DO NOT GO IN THE JUG. Keep the Fee Brothers Cherry Bitters bottle at the bar. | F10: =IF('Jug Recipes'!G8>0,'Jug Recipes'!F8&" "&TEXT('Jug Recipes'!G8,"0.#")&" oz"&CHAR(10),"")&IF('Jug Recipes'!I8>0,'Jug Recipes'!H8&" "&TEXT('Jug Recipes'!I8,"0.#")&" oz"&CHAR(10),"")&IF('Jug Recipes'!K8>0,'Jug Recipes'!J8&" "&TEXT('Jug Recipes'!K8,"0.#")&" oz"&CHAR(10),"")&IF('Jug Recipes'!M8>0,'Jug Recipes'!L8&" "&TEXT('Jug Recipes'!M8,"0.#")&" oz"&CHAR(10),"")&IF('Jug Recipes'!O8>0,'Jug Recipes'!N8&" "&TEXT('Jug Recipes'!O8,"0.#")&" oz"&CHAR(10),"") | G10: Pour the cup, THEN add 2-3 dashes of Fee Brothers Cherry Bitters on top. Swapped off grenadine 18 Aug 2026 — expect a cherry note and a light color tint, not the old heavy syrup-sink gradient. Orange slice or cherry if supplies allow.
A11: ='Jug Recipes'!A9 | B11: ='Jug Recipes'!C9 | C11: 30 min for the jug. The rest of tonight belongs to Saturday. | D11: Nothing for this drink — but TONIGHT IS THE BIG SATURDAY PREP. See the Daily Schedule. | E11: 1. Whisk the coconut cream smooth in a little warm water FIRST. Straight from the bottle it clumps and you will never get it out. 2. Rice Dream Horchata (shake well, it settles) + whisked coconut cream + vanilla syrup — no dilution needed, it's ready-to-drink. 3. Water/ice to fill. 1.5 tsp salt. 4. WHISK, do not just stir. | F11: =IF('Jug Recipes'!G9>0,'Jug Recipes'!F9&" "&TEXT('Jug Recipes'!G9,"0.#")&" oz"&CHAR(10),"")&IF('Jug Recipes'!I9>0,'Jug Recipes'!H9&" "&TEXT('Jug Recipes'!I9,"0.#")&" oz"&CHAR(10),"")&IF('Jug Recipes'!K9>0,'Jug Recipes'!J9&" "&TEXT('Jug Recipes'!K9,"0.#")&" oz"&CHAR(10),"")&IF('Jug Recipes'!M9>0,'Jug Recipes'!L9&" "&TEXT('Jug Recipes'!M9,"0.#")&" oz"&CHAR(10),"")&IF('Jug Recipes'!O9>0,'Jug Recipes'!N9&" "&TEXT('Jug Recipes'!O9,"0.#")&" oz"&CHAR(10),"") | G11: STIR BEFORE EVERY POUR — rice milk settles hard and fast. Cinnamon dust on top. Spiced Rum float on request.
A12: ='Jug Recipes'!A10 | B12: ='Jug Recipes'!C10 | C12: 20 min on the day, plus an overnight cold steep started Friday. Deliberately the easiest build of the week — Saturday needs a jug that looks after itself. | D12: FRIDAY NIGHT: cold-steep ~10 green teabags in ~2 gal of cold water and seal it. This is a SECOND, SEPARATE steep from Sunday’s — same recipe, its own container, its own label, or you will pour tomorrow’s jug into today’s. Cold-steeping cannot go bitter the way a hot steep can, so it survives being forgotten in the middle of the Saturday prep. | E12: 1. Pull the teabags. Do not squeeze them. 2. Tea into the dispenser, then peach syrup, then lemon, then agave. 3. Taste BEFORE the ice. Peach syrup varies; this should read as tea with peach behind it, not peach squash. 4. Water/ice to fill. 1.5 tsp salt. 5. *** NO MOUNTAIN DEW AND NO SPIRULINA. *** That was Blue Screen of Death and it is gone. Nothing on this jug gets topped up per cup and nothing needs stirring. | F12: =IF('Jug Recipes'!G10>0,'Jug Recipes'!F10&" "&TEXT('Jug Recipes'!G10,"0.#")&" oz"&CHAR(10),"")&IF('Jug Recipes'!I10>0,'Jug Recipes'!H10&" "&TEXT('Jug Recipes'!I10,"0.#")&" oz"&CHAR(10),"")&IF('Jug Recipes'!K10>0,'Jug Recipes'!J10&" "&TEXT('Jug Recipes'!K10,"0.#")&" oz"&CHAR(10),"")&IF('Jug Recipes'!M10>0,'Jug Recipes'!L10&" "&TEXT('Jug Recipes'!M10,"0.#")&" oz"&CHAR(10),"")&IF('Jug Recipes'!O10>0,'Jug Recipes'!N10&" "&TEXT('Jug Recipes'!O10,"0.#")&" oz"&CHAR(10),"") | G12: Pour and go. Naturally still, so there is nothing to keep fizzy and nothing to stir — which is the entire point on the night the three reveals land. Soda-water splash for anyone who wants it longer or less sweet. Same drink as tomorrow, so anyone who liked it can have it again.
A13: ='Jug Recipes'!A11 | B13: ='Jug Recipes'!C11 | C13: 20 min on the day, plus an overnight cold steep started Saturday. Easiest build of the week — which is the point, on the day everyone is packing. | D13: SATURDAY NIGHT: cold-steep ~10 green teabags in ~2 gal of cold water and seal it. Cold-steeping cannot go bitter the way a hot steep can, so this one survives being forgotten until morning. | E13: 1. Pull the teabags. Do not squeeze them. 2. Tea into the dispenser, then peach syrup, then lemon, then agave. 3. Taste BEFORE the ice. Peach syrup varies; this should read as tea with peach behind it, not peach squash. 4. Water/ice to fill. 1.5 tsp salt. | F13: =IF('Jug Recipes'!G11>0,'Jug Recipes'!F11&" "&TEXT('Jug Recipes'!G11,"0.#")&" oz"&CHAR(10),"")&IF('Jug Recipes'!I11>0,'Jug Recipes'!H11&" "&TEXT('Jug Recipes'!I11,"0.#")&" oz"&CHAR(10),"")&IF('Jug Recipes'!K11>0,'Jug Recipes'!J11&" "&TEXT('Jug Recipes'!K11,"0.#")&" oz"&CHAR(10),"")&IF('Jug Recipes'!M11>0,'Jug Recipes'!L11&" "&TEXT('Jug Recipes'!M11,"0.#")&" oz"&CHAR(10),"")&IF('Jug Recipes'!O11>0,'Jug Recipes'!N11&" "&TEXT('Jug Recipes'!O11,"0.#")&" oz"&CHAR(10),"") | G13: Daytime service, so it goes out warm-adjacent fast — keep the dispenser out of the sun and the ice topped up. Soda-water splash for anyone who wants it unsweetened.
A15: EVERY JUG, EVERY TIME — the standing rules
A16: Wipe the dispenser and the spigot before you start. Dust gets into everything, and the spigot is the bit everyone touches.
A17: ORDER MATTERS: syrups and juices first, then water, then ICE LAST. Ice first means it melts while you are still stirring and you end up with a weak jug.
A18: SALT EVERY JUG — about 1.5 tsp per 10 L. It is not optional and it is not for flavour exactly; it is what makes a batch taste finished instead of watery in the heat.
A19: TASTE IT BEFORE IT GOES OUT. Every recipe here is a starting point, not a law. Fruit varies, steeps vary, and nobody will know it was wrong except the 33 people who drink it.
A20: BATCH BEFORE SERVICE OPENS, never during. A jug built in a rush is a jug built wrong.
A21: Label the dispenser. The special changes every night and the sign from yesterday is a lie.
A22: If a jug runs dry early there is a Salted Limeade fallback on 'Jug Recipes' row 13 that needs no extra shopping.

Sheet Camp Drinks
A1: Camp Drinks — bulk, self-serve, not bar service
A3: Big-batch drinks that live on the camp table, not the bar: caffeine in the morning, electrolytes all day, two unsweetened iced teas plus one sweetened winter melon tea, and a canned block (Celsius, hard seltzer, Spindrift, ginger beer) counted by the can rather than by the gallon, plus the coffee creamer. Everything here runs EIGHT days (Assumptions B81) — Sunday through the closing Sunday. Quantities are live from the Assumptions tab — yellow cells there drive gallons. These feed the Purchase List rows tagged 'Camp bulk'.
A5: Drink | B5: Gallons | C5: Servings (10oz) | D5: What to buy | E5: Qty | F5: Unit | G5: $/unit | H5: Subtotal | I5: Note
A6: Cold brew coffee | B6: =Assumptions!$B$81*Assumptions!$B$82 | C6: =B6*128/10 | D6: Stone Street COARSE cold brew coffee (5 lb bags) | E6: =CEILING(B6*Assumptions!$B$83/Assumptions!$B$84,1) | F6: lbs | G6: =Assumptions!$B$85 | H6: =E6*G6 | I6: Brewed as concentrate then cut ~1:1. Assumptions B82 sets gallons/day. SWITCHED TO GROUND 18 Aug 2026 (was whole bean, which needed a grinder nobody has) — 14 lb ordered, mixed bag sizes since 5 lb ground wasn't available in enough quantity. RATIO CORRECTED same day: 0.5 lb/gal (Assumptions B83), not the original 1 — 24 finished gal x 0.5 = 12 lb needed, so 14 lb carries a ~2 lb buffer, a bit more generous than the original plan's 1 lb spare. Steep it in the strainer bags on Supplies row 28: grounds go IN the bag, bag comes out, no second filtration pass.
A7: Electrolyte mix | B7: =Assumptions!$B$81*Assumptions!$B$86 | C7: =B7*128/10 | D7: Powder canisters | E7: =CEILING(B7/Assumptions!$B$87,1) | F7: canisters | G7: =Assumptions!$B$88 | H7: =E7*G7 | I7: Gatorade-style 51oz canister, ~6 gal each. Assumptions B86 sets gallons/day.
A8: Winter melon tea (dong gua cha) | B8: =Assumptions!$B$135 | C8: =B8*128/10 | D8: Tea/sugar blocks | E8: =CEILING(B8/Assumptions!$B$136,1) | F8: blocks | G8: =Assumptions!$B$137 | H8: =E8*G8 | I8: Winter melon (white gourd) sugar block, dissolved in hot water then chilled — a classic Chinese/Taiwanese sweet iced tea, REPLACING SUAN MEI TANG 18 Aug 2026. Served cold and self-serve from the DEDICATED TEA DISPENSER (Supplies row 23, third unit) — brewed in two batches, Wednesday and Friday. NOTE: unlike the other two camp teas, this one is SWEET, not unsweetened — label it clearly so it doesn't get mistaken for the unsweetened pair. *** RESEARCHED 18 Aug 2026, NOT A CHECKED RECEIPT: *** yield and price are estimated from a handful of Asian-grocery listings (Weee!, Yami) rather than a single confirmed SKU — see Assumptions B136/B137 for the basis. Standard prep is to simmer the block in water until dissolved, then dilute with water/ice to taste; treat the block-per-gallon figure as a starting point and adjust to the real product's own instructions once it arrives.
A9: Mugicha (roasted barley tea) | B9: =Assumptions!$B$138 | C9: =B9*128/10 | D9: Teabags | E9: =CEILING(B9*Assumptions!$B$139/Assumptions!$B$140,1) | F9: boxes | G9: =Assumptions!$B$141 | H9: =E9*G9 | I9: Cold-steep overnight, serve iced and unsweetened. Shares the dedicated tea dispenser with the suan mei tang — brewed in two batches, Thursday and Saturday. Label it: unsweetened surprises people.
A10: Green tea (iced) | B10: =Assumptions!$B$177 | C10: =B10*128/10 | D10: Teabags | E10: =CEILING(B10*Assumptions!$B$178/Assumptions!$B$179,1) | F10: boxes | G10: =Assumptions!$B$180 | H10: =E10*G10 | I10: Cold-steep overnight, serve iced and unsweetened. THIRD tea on the dedicated dispenser (Supplies row 23) — suan mei tang and mugicha already share it, so either stagger a third brew slot or add a fourth dispenser. Label it unsweetened.
A11: Tangerine juice (RATIONED) | B11: =Assumptions!$B$194*Assumptions!$B$195/128 | C11: =B11*128/10 | D11: Quart cartons, chilled | E11: =Assumptions!$B$194 | F11: quarts | G11: =Assumptions!$B$196 | H11: =E11*G11 | I11: *** RATION IT. *** 4 quarts is ~13 servings against an eight-day burn — this is a treat, not a staple, and it will be gone by Monday lunchtime if it goes out with everything else. Put ONE quart out at a time, in the morning alongside the cold brew, and keep the rest out of the cooler people browse. It is the only thing on the camp block that tastes like it came from outside the desert, which is exactly why it disappears.
A12: TOTAL | C12: =SUM(C6:C11) | H12: =SUM(H6:H11)
A13: These eleven are tagged 'Camp bulk' on the Purchase List — camper supply, not bar service. They are not sized against guest servings and do not appear in the per-drink cost figures.
A15: CANNED — self-serve from the cooler, counted by the can. CHANGE THE COUNTS ON Assumptions B183 (Celsius) / B186 (seltzer) / B189 (Spindrift) / B199 (ginger beer) — columns B and C here are both derived and will overwrite anything typed into them. The pack sizes in columns D-F only exist to price the buy; the Purchase List asks for TOTAL CANS, so any pack format on the shelf is fine.
A16: Drink | B16: Cans (from Assumptions) | C16: Servings (= cans) | D16: What to buy | E16: Qty | F16: Unit | G16: $/unit | H16: Subtotal | I16: Note
A17: Celsius (energy drink) | B17: =Assumptions!$B$183 | C17: =B17 | D17: 12-packs | E17: =CEILING(B17/Assumptions!$B$184,1) | F17: packs | G17: =Assumptions!$B$185 | H17: =E17*G17 | I17: Camper stock — caffeine that is not coffee. Not bar service and not counted in the per-drink figures.
A18: White Claw (or equivalent hard seltzer) | B18: =Assumptions!$B$186 | C18: =B18 | D18: 12-packs | E18: =CEILING(B18/Assumptions!$B$187,1) | F18: packs | G18: =Assumptions!$B$188 | H18: =E18*G18 | I18: ALREADY ALCOHOLIC — no liquor add-on. Any equivalent seltzer substitutes 1:1; swap the price on Assumptions B188.
A19: Spindrift | B19: =Assumptions!$B$189 | C19: =B19 | D19: 24-packs | E19: =CEILING(B19/Assumptions!$B$190,1) | F19: packs | G19: =Assumptions!$B$191 | H19: =E19*G19 | I19: Sparkling water with real juice — the low-sugar option for people who are done with syrup.
A20: Ginger beer (camper stock) | B20: =Assumptions!$B$199 | C20: =B20 | D20: 24-packs | E20: =CEILING(B20/Assumptions!$B$200,1) | F20: packs | G20: =Assumptions!$B$201 | H20: =E20*G20 | I20: CAMPER STOCK — separate from the bar. The bar already buys ginger beer twice: the cans the Kombucha Mule build eats ('Other Consumables' row 36) and the 24-can mixer buffer that turns any liquor into a mule ('Bar Add-Ons' row 9). This is the third pool, in the cooler, for campers to take. Change the count on Assumptions B199.
A21: Mountain Dew (camper stock) | B21: =Assumptions!$B$258 | C21: =B21 | D21: 12-packs | E21: =CEILING(B21/Assumptions!$B$259,1) | F21: packs | G21: =Assumptions!$B$260 | H21: =E21*G21
A22: TOTAL — CANNED | B22: =SUM(B17:B21) | C22: =SUM(C17:C21) | H22: =SUM(H17:H21)
A24: COFFEE CREAMER — camper item
A25: Creamer for the cold brew, and the answer for anyone who does not want coconut. The bar dropped dairy entirely — cream of coconut is the only cream in the model (Assumptions B10) — so without this there is nothing to put in a coffee and nothing to offer someone who dislikes coconut. Camper item: it sits on the camp table with the cold brew, it is not bar service, and it is not sized against guest servings. Count and price on Assumptions B204/B205; the dairy/non-dairy split is a shopping note, not a modelled input.
A26: Item | D26: What to buy | E26: Qty | F26: Unit | G26: $/unit | H26: Subtotal | I26: Note
A27: Coffee creamer | D27: Creamer, 32oz — 4 dairy (Starbucks Caramel Macchiato, already ordered) | E27: =Assumptions!$B$204 | F27: bottles | G27: =Assumptions!$B$205 | H27: =E27*G27 | I27: Camper stock. For the coffee and as the non-coconut cream option in the dirty sodas. DAIRY PORTION ONLY as of 18 Aug 2026 — the non-dairy half moved to Rice Dream Horchata (Purchase List row 46), which does double duty as the Friday jug's horchata base too. Sized off last year, where camp got through close to a bottle a day.
A29: DISPENSER SIGNS — 3 x 5, taped to the dispenser
A30: Print and laminate before playa (Supplies row 26). All three teas are cold and unsweetened — without a sign people assume iced tea, take one sip and walk off. Say what it is, say it is unsweetened, say it is cold. Keep it to what fits on a 3 x 5 card.
A31: Sign | B31: Headline | C31: Body copy
A32: Winter melon tea | B32: WINTER MELON TEA — Dong Gua Cha | C32: Chinese/Taiwanese winter melon sugar tea, served ice cold. SWEET — the one sweet option on the camp tea dispenser, unlike the other two. Smooth, mellow, caramel-like, not fruity. Caffeine-free.
A33: Mugicha | B33: MUGICHA — Roasted Barley Tea | C33: Roasted barley, brewed cold. UNSWEETENED and CAFFEINE-FREE. Nutty and toasty, not bitter. Drink it like water — this is the one to hand someone who has had enough sugar for one day.
A34: Green tea | B34: GREEN TEA — Iced, Unsweetened | C34: Cold-steeped green tea. UNSWEETENED, lightly caffeinated. Clean and grassy, not bitter — brewed cold so it never gets stewed. The one to drink when you want tea that tastes like tea.
A35: Tangerine juice | B35: TANGERINE JUICE — Rationed | C35: Real tangerine juice, cold. There is not much of it and there will not be more. One cup, enjoy it, leave some for the person behind you.

Sheet Assumptions
A1: Future Turtles Drinks — Supply Model (Burning Man 2026)
A2: REPRICED — see the 'Ingredient Pricing' tab. Base soda, soda water, syrups, cream of coconut, purées, juices, agave, citrus and cherries now carry real July 2026 Costco / WebstaurantStore / Walmart prices instead of placeholders.
A3: KEY INPUTS — yellow cells are editable
A4: Input | B4: Value | C4: Note
A5: Buffer (waste/over-pour) | B5: 0.15 | C5: Applied to consumables.
A6: Cans per case (base soda) | B6: 35 | C6: 12 oz can case.
A7: Can size (oz) | B7: 12 | C7: Standard can.
A8: Syrup bottle size (oz) | B8: 25.4 | C8: Torani 750ml. PUMP REFERENCE, added 20 Aug 2026: a standard Torani pump is 1/4 oz — 4 pumps = 1 fl oz. Recipe oz doses of 0.25 read as 1 pump, 0.5 as 2 pumps, 0.75 as 3 pumps, and so on.
A9: Cream of coconut (oz/bottle) | B9: 16.9 | C9: 22oz squeeze bottle (Amazon).
A10: Half & half (oz/quart) — LEGACY | B10: 32 | C10: Dairy dropped — replaced by cream of coconut squeeze bottles.
A11: Sizing unit (gal) — legacy keg block | B11: 5 | C11: All 5 kegs assumed 5 gal.
A12: Servings per unit | B12: =FLOOR((B11*128-B121)/B120,1) | C12: Derived: (keg gal x 128 - loss) / pour size. Change B120 to resize every keg count in the model.
A13: Squirt bottle size (oz) — LEGACY | B13: 67.6 | C13: Legacy 2L sizing — Squirt now bought in 12oz cans like the other sodas.
A15: UNIT PRICES
A16: Base soda — $/case (24) | B16: 16
A17: Lemonade — $/96 oz bottle | B17: 4.5 | C17: SWITCHED TO READY-TO-DRINK 14 Aug 2026 — Kirkland Signature Organic Lemonade, 96 fl oz, sold as a 2-count pack. CONFIRMED SHELF-STABLE, not a cold-case item, so it does not claim cooler space until it is opened. This replaces the Country Time powder (82.5 oz canister, Costco item #92860) and with it the whole mix-on-arrival session. *** THE $4.50/BOTTLE HERE IS AN UNCHECKED PLACEHOLDER — $9.00 assumed for the 2-count pack. GET THE REAL SHELF PRICE AND REPLACE IT. *** The old powder line was $1.25 per finished gallon and the whole lemonade requirement cost $3.75, so even a bad price here moves the total by ~$15. Unit is now ONE 96 oz BOTTLE, not a gallon — Purchase List F12 multiplies by bottles.
A18: Horchata mix — $/case-equiv — RETIRED 18 Aug 2026 | B18: 5 | C18: Repriced 2 Aug 2026. RESOLVED — this was the workbook's flagged unknown. One 23.6 oz bottle of Mexquisita horchata concentrate (~$5-6, any Reno Latino grocery) dilutes 1:4-1:5 and lands almost exactly on the 165 oz the model needs. Klass 14.1 oz powder is cheaper (~$3, makes 7 quarts) but tastes thin on its own. Rice Dream cartons are 3.5x the cost — skip. RETIRED — switched to Rice Dream Horchata, ready-to-drink, no concentrate/dilution step. Purchase List row 46 is now a flat manual entry, not driven by this cell. Left in place, harmless.
A19: Syrup — $/bottle | B19: 8
A20: Cream of coconut — $/bottle | B20: 3.98
A21: Half & half — $/quart — LEGACY | B21: 3.5
A22: Soda water — $/case — LEGACY (soda water is 1 L now, see B236) | B22: 13
A23: Squirt — (now in cans; see soda case price) | B23: 2.5
A24: Cider — old keg $ (BASELINE ONLY) | B24: 160
A25: Kombucha — old keg $ (BASELINE ONLY) | B25: 130
A26: Beer — old keg $ (BASELINE ONLY) | B26: 180
A27: Green tea — old keg $ (BASELINE ONLY) | B27: 130
A28: Old keg add-ons/garnish $ (BASELINE ONLY) | B28: 25
A29: Kombucha | B29: 0.35 | C29: Kombucha Mule add-ins (yuzu/agave/ginger beer); Tang Dynasty extras are itemized separately.
A31: RETIRED — KEG EQUIPMENT (kept only as the cost baseline)
A32: Keg deposit — each (REFUNDABLE) | B32: 50 | C32: Cash needed up front, returned with the empties — excluded from program cost.
A33: Double jockey box (2 taps) — $ per 4-day rental | B33: 150 | C33: Ice-cooled coil box; no kegerator needed.
A34: Rental periods (12 days = 3 x 4-day) | B34: 3
A35: CO2 refill — $ each | B35: 59
A36: CO2 refills — count | B36: 2 | C36: 10lb pushes ~5-7 kegs; 2nd fill covers heat/venting losses.
A38: LIQUOR (OPTIONAL ADD-ON)
A39: % of drinks made alcoholic | B39: 0.35 | C39: Applied to servings per recipe to size liquor needs.
A40: Liquor pour per alcoholic drink (oz) | B40: 1.5 | C40: Standard single shot.
A41: Liquor bottle size (oz) | B41: 25.4 | C41: 750ml standard.
A42: Vodka — $/bottle | B42: 15 | C42: Repriced 2 Aug 2026. Tito's 750 ml, Total Wine $14.99-15.49. SEE THE 1.75 L NOTE BELOW — Kirkland is $8.35 per 750 ml equivalent.
A43: Coconut Rum — $/bottle | B43: 15.49 | C43: Repriced 2 Aug 2026. Malibu 750 ml, Total Wine $15.49.
A44: Bourbon — $/bottle | B44: 14 | C44: Repriced 2 Aug 2026. Evan Williams Black 750 ml, Total Wine $13.99 and it mixes fine. The old $28 only holds if you specifically want Buffalo Trace (~$29.99).
A45: Blanco Tequila — $/bottle | B45: 26 | C45: Repriced 2 Aug 2026. Espolòn Blanco 750 ml, ~$25.99 in store. Kirkland Tequila Blanco is 50-60% cheaper per 750 ml if you take the 1.75 L.
A46: Spiced Rum — $/bottle | B46: 15.99 | C46: Repriced 2 Aug 2026. Captain Morgan Original 750 ml, Total Wine $15.99.
A47: Whiskey — $/bottle | B47: 24.99 | C47: Repriced 2 Aug 2026. Jameson 750 ml $24.99. Ole Smoky Pickles moonshine, for the one pickle bottle, is $21.99.
A49: DAILY SPECIALS & SUNDAY PARTY (new inputs)
A50: Taps available at once (Mon–Sat) | B50: 2 | C50: Two continuous tap lines now: a 'beer line' + an 'other tap' line, each evolving through kegs across the week. See Keg Rotation tab.
A51: Aqua fresca fruit base — oz/serving | B51: 3.2 | C51: Juice per fresca serving (watermelon Mon; Sat OJ fresca uses 4 oz).
A52: Aqua fresca fruit base — $/32oz bottle | B52: 6 | C52: Legacy — Mon/Sat frescas now use whole melons / OJ cartons.
A53: Aqua fresca fruit base — oz/bottle | B53: 32
A54: Agave — oz/serving (jug frescas) | B54: 0.35 | C54: Agave per serving for the Monday watermelon fresca. DROPPED from 0.45 — watermelon is already sweet and was getting more sugar than the hibiscus, which is far tarter. Agave is ~1.5x sweeter than simple syrup, so this is roughly 0.5 oz of simple. Taste and nudge.
A55: Simple syrup — $/bottle — LEGACY (agave now, B133) | B55: 9 | C55: Reuse Torani-size bottle for costing.
A56: Simple syrup — oz/bottle — LEGACY (agave now, B132) | B56: 25.4
A57: Snow Paws Milkshake IPA — RETIRED | B57: 210 | C57: Legacy — Snow Paws cut; second Kombucha keg closes the beer line instead.
A58: Sour Ale — old keg $ (BASELINE ONLY) | B58: 190 | C58: Sunday party + first couple days.
A59: Blonde Ale — old keg $ (BASELINE ONLY) | B59: 180 | C59: Sunday party pour + Michelada base Wed–Fri.
A60: Michelada build — servings (from Mexican Lager keg) | B60: 30 | C60: Built to order from the Mexican Lager keg, like the Kombucha Mule. 30 of the keg's 50 pours go out as Micheladas; the other 20 are pulled straight (see 'Beverage Lines'!C11, which takes the remainder).
A61: Michelada extras — $/serving (Tajin, lime, Clamato, hot sauce) | B61: 0.5
A62: Sakura + orange syrup — $/bottle | B62: 9 | C62: Added to the green tea keg for the Sat Catboy Café.
A63: Sakura + orange syrup — bottles needed | B63: 2 | C63: 1 sakura + 1 orange — covers the built Catboy Café Green Tea (Recipes row 14).
A64: Rough daily-volume note | C64: Previous baseline ~80 drinks/day. Sunday party + Cider/White Tea/Michelada + 2 daily specials/day bumped the plan hard; the model now totals 1,323 servings (Totals by Type B11) after the cuts and additions to date — expect actual pace ~110/day. NOTE THE SATURDAY SPIKE: the Catboy Cafe finale stacks Sakura Kisses (33, Recipes row 14), Catboy Snot (25, Recipes row 16) and Catboy Piss (25, Recipes row 17) — 83 servings of reveal-only drinks — on top of the nightly jug (33) and the normal all-week board. That is ~116 servings from Saturday-only items alone, all built to order, all on the busiest day. THE JUG IS DELIBERATELY THE EASY ONE NOW: Saturday pours the same cold-steeped peach green tea as the closing Sunday, steeped the night before, so it needs no top-up and no stirring while the reveals are landing. Prep the aloe tint, the basil seeds and the hydrated garnishes on FRIDAY NIGHT, not Saturday.
A65: Half keg price factor (vs full keg) | B65: 0.65 | C65: Vendor charges more per-oz for the smaller format, so it's not a flat 50%.
A66: Servings per half keg | B66: =FLOOR(B12/2,1) | C66: Half of a full keg's servings, rounded down.
A67: Mexican Lager — old keg $ (BASELINE ONLY) | B67: 150 | C67: Built into Michelada mid-week (Wed-Thu) instead of Blonde Ale.
A68: Daily jug size (L) | B68: 10 | C68: 10 L drink dispenser (~2.6 gal). Derived oz and servings-per-jug are at rows 115-117; the Daily Schedule servings column reads from B117, so changing this resizes every nightly batch and its ingredient buys.
A69: Orange juice — oz/carton | B69: 64
A70: Orange juice — $/carton | B70: 7.49
A71: Pineapple juice — oz/pack (24 x 8 oz) | B71: 192 | C71: FORMAT CHANGED 14 Aug 2026 — bought as Dole 100% Pineapple Juice, 24 x 8 fl oz = 192 oz per pack, not a 46 oz can. The Thursday Gradient Descent jug draws 82.5 oz (94.9 with buffer), so ONE pack covers it with 97 oz to spare — the leftover 8 oz cans are perfectly good handed out cold.
A72: Pineapple juice — $/pack | B72: 13.99 | C72: *** UNCHECKED PLACEHOLDER — $13.99 assumed for the Dole 24 x 8 oz pack. GET THE RECEIPT PRICE AND REPLACE. *** Was $3.33 per 46 oz can. Only one pack is bought, so the whole line moves with this cell.
A73: Grenadine — oz/bottle — RETIRED 18 Aug 2026 | B73: 25
A74: Grenadine — $/bottle — RETIRED 18 Aug 2026 | B74: 7.5 | C74: Repriced 2 Aug 2026. Rose's Grenadine 25 oz, Smart & Final Reno $7.99. RETIRED 18 Aug 2026 — Thursday's jug garnish switched to Fee Brothers Cherry Bitters. Left in place, harmless: Jug Recipes row 25 now always evaluates to 0 regardless of these values.
A75: Blue spirulina — $/jar | B75: 16 | C75: Repriced 2 Aug 2026. RESPECIFIED to a 30 g jar. The 50 g size barely exists — the market is 30 g and 60 g (Target Micro Ingredients 60 g $32.99). At 0.25-0.5 g per drink for colour, 30 g at ~$16 covers the week comfortably.
A76: Watermelon — juice yield oz/melon | B76: 90 | C76: ~15 lb melon → ~3 qt strained juice.
A77: Watermelon — $/melon | B77: 7
A78: Lime juice — oz/bottle | B78: 48 | C78: ReaLime-style bottled.
A79: Lime juice — $/bottle | B79: 4
A80: Maraschino cherries — $/jar | B80: 9.99 | C80: Repriced 2 Aug 2026. Luxardo 2 x 14.1 oz at Costco is $19.97 REGULAR = $9.99/jar; the old $7.49 was a sale price. STOCK RISK: carried by only ~24% of warehouses and single jars run $22-26 elsewhere. Ring Costco Reno; if they are out, substitute bulk cocktail cherries rather than paying retail Luxardo.
A81: Event days (camp bulk drinks) | B81: 8 | C81: Sun through the CLOSING SUNDAY — eight days, not seven. Scales cold brew and electrolytes on Camp Drinks rows 6-7, and every buy that hangs off them. The eighth day is the daytime cafe service that carries the Graceful Shutdown jug ('Jug Recipes' row 11).
A82: Cold brew — gallons/day | B82: 3
A83: Cold brew grounds — lb per gallon | B83: 0.5 | C83: CORRECTED 18 Aug 2026, was 1 lb/gal. The original 1 lb/gal was applied to B6's FINISHED (post-dilution) gallon count, but the brew method is concentrate-then-cut-~1:1 — cutting 1:1 roughly doubles volume, so grounds per FINISHED gallon should be roughly half of what a full-strength brew would need. Standard home cold-brew concentrate ratios (cut 1:1 to serve) land close to 0.5 lb grounds per finished gallon, which the user cross-checked independently and matches. 24 finished gal x 0.5 lb/gal = 12 lb needed, down from the original 24 lb. If your actual steep is stronger than a standard concentrate ratio, dial this back up — but 0.5 is the better default than the original 1.
A84: Cold brew grounds — lb per purchase unit | B84: 1 | C84: CHANGED 18 Aug 2026, was 5 (fixed 5 lb bags). Ground coffee is now being bought as whatever bag sizes are actually in stock, not standardized 5 lb bags — set to 1 so the 'bags' column below just tracks lbs directly.
A85: Cold brew grounds — $/lb | B85: 12 | C85: UPDATED 18 Aug 2026 — real receipt: 7 x 2lb bags at $23.99 each = $167.93 for 14 lb, i.e. $12.00/lb almost exactly ($11.995). Replaces the $14.60/lb placeholder.
A86: Electrolyte mix — gallons/day | B86: 5
A87: Electrolyte mix — gal per canister | B87: 9 | C87: Repriced 2 Aug 2026. Costco sells a 76.5 oz Gatorade canister making ~9 gal, not the 51 oz / 6 gal this assumed. Unit changed to match the real product.
A88: Electrolyte mix — $/canister | B88: 14.99 | C88: Repriced 2 Aug 2026. Gatorade Thirst Quencher powder, 76.5 oz, Costco $14.99 (tracker refreshed 2 Aug 2026). = $1.67/gal. Liquid I.V. sticks were checked and are $5.33/gal — 3.2x worse, and ~1.4x worse even after normalising for their higher sodium. Keep a box as a heat-casualty medical item, not as the bulk line.
A89: Tangerine juice — oz/bottle | B89: 59 | C89: Repriced 2 Aug 2026. Perricone Farms tangerine juice ships as 2 x 59 oz at Costco, so the bottle is 59 oz not 52.
A90: Tangerine juice — $/bottle | B90: 4.8 | C90: Repriced 2 Aug 2026. Perricone Farms 2 x 59 oz, Costco $9.59 = $4.80/bottle ($0.081/oz). STOCK RISK: in stock at only ~63% of warehouses. If unavailable, OJ plus a dose of tangerine/mandarin syrup — straight OJ alone reads noticeably different.
A91: Fruit purée squeeze bottle — oz | B91: 16.9
A92: Passion fruit purée — $/bottle | B92: 6.5 | C92: Repriced 2 Aug 2026. Reàl Passion Fruit Purée Infused Syrup, 16.9 fl oz, WebstaurantStore: $9.59 single, $38.99 per case of 6 = $6.50/bottle. Buy the case — you need several.
A93: Pineapple purée — $/bottle | B93: 7.25 | C93: Repriced 2 Aug 2026. Reàl Pineapple, 16.9 fl oz, WebstaurantStore $43.49 per case of 6 = $7.25. No longer an estimate.
A95: KOMBUCHA MULE BUILD — extras itemized
A96: Ginger beer — oz/can | B96: 12 | C96: 12oz can/bottle.
A97: Ginger beer — $/can | B97: 1.7 | C97: Repriced 2 Aug 2026. RAISED for availability, not price. Costco Bundaberg 12 x 12.7 oz is $1.14/can — but it is OUT OF STOCK at 93% of warehouses (16 of 400). The reliably-available format is Cock'n Bull 12 oz 4-packs at $6.99 = $1.75/can, $1.63 at 6+. Costed at the format you can actually buy. Ring Costco Reno first; if Bundaberg is in, this line drops by about a third across all three ginger beer pools.
A98: Kombucha Mule — simple syrup oz/serving — RETIRED (agave, B131) | B98: 0 | C98: Zeroed when agave replaced the sugar in the SCOBY Mule build. Set back above 0 to revive it.
A99: Lemon — juice yield oz/lemon | B99: 1.5 | C99: ~1.5oz juice from an average lemon.
A100: Lemon — $/each | B100: 0.29 | C100: Repriced 2 Aug 2026. Costco lemons 5 lb $4.49 current / $6.52 avg, ~20-23 per bag.
A102: MICHELADA & TANG DYNASTY BUILDS — extras itemized
A103: Clamato — oz/bottle | B103: 64 | C103: Large bottle.
A104: Clamato — $/bottle | B104: 3.25 | C104: Repriced 2 Aug 2026. Clamato 2 x 64 oz, Costco warehouse $5.99-6.49. Buy in warehouse — Costco.com lists $10.99 for the same pack.
A105: Michelada — hot sauce oz/serving — RETIRED 18 Aug 2026 | B105: 0 | C105: RETIRED — Michelada dropped separate hot sauce when it moved to Tres Agaves Bloody Mary Mix (already spiced). This was hot sauce's only use in the model, so Other Consumables row 41 and Purchase List row 33 now correctly read $0.
A106: Hot sauce — oz/bottle | B106: 12
...

Sheet Ingredient Pricing
A1: Ingredient Pricing — real Costco / Nevada prices, July 2026
A3: Every price below has been written INTO the Assumptions tab, so the Purchase List and Totals by Type are already running on these numbers. The 'Now' column reads live from Assumptions — edit there, not here. Sourced from Costco warehouse pricing (July 2026), WebstaurantStore and Walmart. Costco prices vary by warehouse; the Reno warehouse is the one that matters and these are national ranges, so treat them as good-to-±15%.
A5: PRICES CHANGED
A6: Ingredient | B6: Assumptions cell | C6: Was | D6: Now | E6: Change | F6: Unit | G6: Source / basis
A7: Cans per case (base soda) | B7: B6 | C7: 24 | D7: =Assumptions!B6 | E7: =D7-C7 | F7: cans/case | G7: Costco does not sell soda in 24s — the warehouse pack is 35 x 12 oz. Changing this alone cuts the case count, and it feeds the soda-water line too.
A8: Base soda — $/case (35) | B8: B16 | C8: 25 | D8: =Assumptions!B16 | E8: =D8-C8 | F8: $/case of 35 | G8: Costco 35 x 12 oz, July 2026: Coca-Cola $14.49-18.19, Sprite $15.49-16.49, Dr Pepper $14.49-16.49. Using $16. Was $25 for a 24-pack ($1.04/can) — real is ~$0.46/can.
A9: Soda water — $/case (35) | B9: B22 | C9: 18 | D9: =Assumptions!B22 | E9: =D9-C9 | F9: $/case of 35 | G9: Kirkland Signature Sparkling Water 35 x 12 oz, $11.99-17.09. Variety pack is lime/lemon/grapefruit, which is fine-to-good in the Italian sodas and the Shirley variants. (It used to earn its place in Thirst Trap too; Fuzz Test dropped the soda water entirely.)
A10: Syrup — $/bottle (Torani 750 ml) | B10: B19 | C10: 9 | D10: =Assumptions!B19 | E10: =D10-C10 | F10: $/750 ml bottle | G10: WebstaurantStore July 2026: $9.89 single, $7.99 in lots of 3, $6.58 by the case of 12. You need ~19 bottles across many flavors, so you cannot case-buy one SKU — lots of 3 per flavor is the realistic basis. Using $8.
A11: Cream of coconut — oz/bottle | B11: B9 | C11: 22 | D11: =Assumptions!B9 | E11: =D11-C11 | F11: oz/bottle | G11: Coco Real squeeze bottle is 16.9 oz, not 22 oz.
A12: Cream of coconut — $/bottle | B12: B20 | C12: 7 | D12: =Assumptions!B20 | E12: =D12-C12 | F12: $/bottle | G12: Coco Real 16.9 oz plastic squeeze, Walmart $3.98 ($0.236/oz vs the old $0.318/oz). Coco Lopez 15 oz can is $4.24 but it is a can, not a squeeze — worse on a dusty bar.
A13: Fruit purée squeeze bottle — oz | B13: B91 | C13: 22 | D13: =Assumptions!B91 | E13: =D13-C13 | F13: oz/bottle | G13: Reàl ships in a 16.9 oz squeeze bottle. (The model started at 22 oz; a brief detour through 30 oz culinary purée is now abandoned.)
A14: Passion fruit purée — $/bottle | B14: B92 | C14: 12 | D14: =Assumptions!B92 | E14: =D14-C14 | F14: $/30 oz bottle | G14: Reàl Passion Fruit Puree Infused Syrup, 16.9 fl oz squeezable, Amazon $12.84 ($0.76/fl oz). The $12-per-22oz original was a placeholder for a product that does not exist; pure culinary purée turned out to be $36-54 per 30 oz. This lands in between and is the right format for a bar.
A15: Pineapple purée — $/bottle | B15: B93 | C15: 10 | D15: =Assumptions!B93 | E15: =D15-C15 | F15: $/30 oz bottle | G15: ESTIMATE — Reàl pineapple in the same 16.9 oz squeeze, usually slightly cheaper. Qty 0 today.
A16: Orange juice — $/carton (64 oz) | B16: B70 | C16: 5 | D16: =Assumptions!B70 | E16: =D16-C16 | F16: $/64 oz carton | G16: Barsotti 64 oz at Costco, $7.49-7.99.
A17: Pineapple juice — $/can (46 oz) | B17: B72 | C17: 4 | D17: =Assumptions!B72 | E17: =D17-C17 | F17: $/46 oz can | G17: Dole 100% pineapple juice 3 x 46 oz, $8.69-9.99 → $3.33 per can.
A18: Clamato — $/bottle (64 oz) | B18: B104 | C18: 5 | D18: =Assumptions!B104 | E18: =D18-C18 | F18: $/64 oz bottle | G18: Costco Clamato 2 x 64 oz, $4.97-6.49 → $2.87 per bottle.
A19: Maraschino cherries — $/jar | B19: B80 | C19: 8 | D19: =Assumptions!B80 | E19: =D19-C19 | F19: $/jar | G19: Luxardo 2 x 14.1 oz at Costco $14.97 → $7.49/jar. That is the GOOD cherry, not the neon supermarket kind, and it is cheaper than the placeholder was.
A20: Lemon — $/each | B20: B100 | C20: 0.6 | D20: =Assumptions!B100 | E20: =D20-C20 | F20: $/each | G20: Costco 5 lb bag $4.49-5.39, roughly 20-25 lemons per bag → ~$0.22 each. Using $0.25.
A21: Lime — $/each | B21: B112 | C21: 0.35 | D21: =Assumptions!B112 | E21: =D21-C21 | F21: $/each | G21: Costco 3 lb bag, ~12 limes. The 40 lb full case is $19.19 (~$0.10 each) — at 113 limes you are one third of a case, so the bag price is the honest basis. Using $0.30.
A22: Agave syrup — oz/bottle | B22: B132 | C22: 23.5 | D22: =Assumptions!B132 | E22: =D22-C22 | F22: oz/bottle | G22: Kirkland Organic Blue Agave ships as 2 x 36 oz.
A23: Agave syrup — $/bottle (36 oz) | B23: B133 | C23: 9 | D23: =Assumptions!B133 | E23: =D23-C23 | F23: $/36 oz bottle | G23: Kirkland Organic Blue Agave 2 x 36 oz, $8.89-9.99 → $4.75 per 36 oz bottle. Cheaper per bottle AND 53% more syrup in it.
A25: THE PASSION FRUIT DECISION — settled (and cheaper again on the Aug 2026 recheck)
A26: Option | B26: $ / oz | C26: oz needed | D26: Cost | E26: vs the old assumption | G26: Note
A27: Placeholder the model started with | B27: 0.5455 | C27: ='Other Consumables'!D17*Assumptions!$B$91 | D27: =B27*C27 | E27: =D27-$D$27 | G27: $12 per 22 oz. Not a real product at that price.
A28: Reàl infused syrup, 16.9 oz squeeze — CHOSEN | B28: 0.385 | C28: ='Other Consumables'!D17*Assumptions!$B$91 | D28: =B28*C28 | E28: =D28-$D$27 | G28: WebstaurantStore case of 6, $38.99 = $6.50/bottle = $0.385/fl oz (checked 2 Aug 2026). The single-bottle Amazon price this block was originally argued from was $12.84 = $0.76/oz. Halving the price does not change the conclusion — it strengthens it: Reàl was already the right call against pure culinary purée at $1.21/oz, and at case pricing it is not close.
A29: Alternatives rejected | G29: Pure culinary purée (Perfect Puree 30 oz) at $1.21/oz best case — real and tart, but $36-54 a bottle and it wants refrigeration once opened. Plain flavouring syrup (Torani 750 ml) at $0.315/oz — cheapest, but sweet with no fruit body, and the passion fruit is doing real work in Tang Dynasty and Catboy Piss.
A31: NOT REPRICED IN JULY — ALL CHECKED 2 AUG 2026, see the second-pass table below
A32: Ingredient | B32: Assumptions cell | C32: Still assumes | G32: Why it was left alone
A33: Horchata mix / rice-milk base | B33: B18 | C33: 12 | G33: RESOLVED. Mexquisita concentrate or Klass powder, ~$5. Was a pure guess at $12.
A34: Lemonade, ready-to-drink (96 oz bottle) | B34: B17 | C34: 4.5 | G34: REPLACED 14 Aug 2026 — was Country Time powder at $1.25/finished gallon. Now Kirkland Signature Organic Lemonade, 96 oz x 2-count, shelf-stable. *** PRICE IS AN UNCHECKED PLACEHOLDER ($4.50/bottle, $9.00/pack). *** Buying 2 packs / 4 bottles. Confirm at the warehouse.
A35: Lime juice, bottled (48 oz) | B35: B79 | C35: 4 | G35: Held at $4. ReaLime 48 oz may not be a US Costco SKU at all — see the open questions below.
A36: Blue spirulina | B36: B75 | C36: 20 | G36: Respecified to a 30 g jar at $16. The 50 g size barely exists.
A37: Hot sauce, Tajin, pickles, cinnamon | B37: B107 / B110 | G37: Now itemized properly. Hot sauce fell to $1.75, Tajin rose to $4.68, pickles restructured to gallon jars.
A38: Ginger beer (12 oz cans) | B38: B97 | C38: 1.25 | G38: Raised to $1.70/can — an AVAILABILITY correction, not a price one. Costco Bundaberg is out at 93% of warehouses.
A39: Watermelon, cucumbers, mint, basil, sage | B39: B77 / B123 | G39: Checked. Watermelon exact at $7; cucumbers, grapefruit and limes nudged up; mint is the problem — Costco carries no fresh soft herbs.
A41: SECOND PASS — AUGUST 2026 REPRICE (six parallel checks, 2 Aug 2026)
A42: Every line below was checked against a live listing. Costco figures come from a warehouse price tracker whose "current" column is the LOWEST price seen across all warehouses and often reflects a promo — the average is the honest planning number, and Reno may sit anywhere in the range. One true Reno datapoint was obtained: Costco #25, Harvard Way, Coke 35-count at $14.49 on 2 Aug 2026, at the bottom of the national range. Walmart, Total Wine and Binny's all block automated fetching, so those figures come from search snippets or Instacart storefronts (Instacart runs 5-15% above Total Wine shelf prices), and should be treated as +/-10%.
A44: Item | B44: Cell | C44: Was | D44: Now | E44: Direction | F44: Confidence | G44: Source / basis
A45: Creamer, 32 oz | B45: B205 | C45: 7 | D45: 4.15 | E45: -41% | F45: VERIFIED | G45: Coffee-mate $3.79 Costco, Califia Oat $4.32 Walmart, blended over the 4 dairy / 8 non-dairy split
A46: Electrolyte canister | B46: B87/B88 | C46: $13 / 6 gal | D46: $14.99 / 9 gal | E46: unit fixed | F46: VERIFIED | G46: Costco Gatorade 76.5 oz = $1.67/gal. Liquid I.V. checked and rejected at $5.33/gal
A47: Coffee grounds, 5 lb (Stone Street coarse) | B47: B85 | C47: 72.99 | D47: 72.99 | E47: +17% | F47: VERIFIED | G47: RESOLVED 14 Aug 2026 — Stone Street COARSE cold brew, 5 lb bag $72.99 ($14.60/lb), Amazon. Replaces Kirkland Colombian 3 lb drip grind at $20.99. Buy size checked: 5 bags beats 24 single pounds by $49.05 and an exact-24 lb mix by only $3.99. See Purchase List row 55.
A48: Passion fruit purée | B48: B92 | C48: 12.84 | D48: 6.5 | E48: -49% | F48: VERIFIED | G48: Reàl 16.9 oz, WebstaurantStore case of 6 at $38.99
A49: Pineapple purée | B49: B93 | C49: 12 | D49: 7.25 | E49: -40% | F49: VERIFIED | G49: Reàl 16.9 oz, WebstaurantStore case of 6 at $43.49
A50: Hot sauce, 12 oz | B50: B107 | C50: 3 | D50: 1.75 | E50: -42% | F50: VERIFIED | G50: Valentina 12.5 oz, Walmart $1.68
A51: Horchata base | B51: B18 | C51: 12 | D51: 5 | E51: -58% | F51: VERIFIED | G51: Mexquisita 23.6 oz concentrate makes ~165 oz. Was the workbook's own flagged unknown
A52: Pickle brine | B52: B211/B212 | C52: 14 oz @ $5 | D52: 115 oz @ $7.50 | E52: restructured | F52: VERIFIED | G52: Mt. Olive 128 oz gallon spear jar = $0.13/oz brine vs $0.357 for six 32 oz jars
A53: Blue spirulina | B53: B75 | C53: 50 g @ $20 | D53: 30 g @ $16 | E53: respecified | F53: VERIFIED | G53: 50 g is not a real SKU; market is 30 g and 60 g. 0.25-0.5 g per drink
A54: Basil seeds, 100 g | B54: B152 | C54: 7 | D54: 4 | E54: -43% | F54: VERIFIED | G54: NY Spice Shop 8 oz bag at $6.49 = $2.86/100 g
A55: Mugicha, 54 bags | B55: B141 | C55: 10 | D55: 7 | E55: -30% | F55: VERIFIED | G55: Ito En, H Mart $5.99
A56: Suan mei tang YIELD | B56: B136 | C56: 0.66 gal | D56: 0.53 gal | E56: YIELD FIX | F56: VERIFIED | G56: *** Packets brew at 2.0 L, not 2.5 L. Every supplier agrees. 8 packets bought 4.2 gal against a 5 gal target ***
A57: Suan mei tang | B57: B137 | C57: 5 | D57: 6 | E57: +20% | F57: VERIFIED | G57: Tak Shing Hong $4.99 direct, $5.66 via Weee!
A58: Green tea, 100 bags | B58: B180 | C58: 8 | D58: 12 | E58: +50% | F58: VERIFIED | G58: Kirkland Japanese 100-ct, Costco $11.99-13.49
A59: Dried hibiscus, 1 lb | B59: B126 | C59: 11 | D59: 14 | E59: +27% | F59: VERIFIED | G59: Sabor Orgánico 1 lb, Amazon $14.95
A60: Lapsang, 4 oz | B60: B144 | C60: 12 | D60: 11 | E60: -8% | F60: VERIFIED | G60: Upton Tea / English Tea Store
A61: Aloe, 1.5 L | B61: B149 | C61: 4 | D61: 4.5 | E61: +13% | F61: VERIFIED | G61: OKF Aloe Vera King. Buy the PULPED line, not pulp-free
A62: Celsius | B62: B184/B185 | C62: 12-pk @ $20 | D62: 18-pk @ $24 | E62: pack fixed | F62: VERIFIED | G62: Costco has no 12-pack; the SKU is an 18-count at $1.33/can
A63: Spindrift | B63: B190/B191 | C63: 24-pk @ $20 | D63: 30-pk @ $21.49 | E63: pack fixed | F63: VERIFIED | G63: Costco SKU is a 30-count variety = $0.64/can vs $0.833 assumed
A64: White Claw | B64: B187/B188 | C64: 12-pk @ $18 | D64: 24-pk @ $30.49 | E64: pack fixed | F64: VERIFIED | G64: 24-pack is $1.27/can vs $1.42; the 12-pack SKU is nearly gone
A65: Ginger beer | B65: B97 | C65: 1.25 | D65: 1.7 | E65: +36% | F65: VERIFIED | G65: AVAILABILITY, not price. Costco Bundaberg is $1.14/can but out at 93% of warehouses. Cock'n Bull 4-packs are the buyable format
A66: Tonic, 12 oz can | B66: Bar Add-Ons D7 | C66: 0.85 | D66: 0.6 | E66: -29% | F66: VERIFIED | G66: Seagram's 24-pack $12.57 Walmart. The old price was Fever-Tree, whose cans are 5.07 oz not 12
A67: Soda water buffer | B67: Bar Add-Ons D8 | C67: 0.75 | D67: 0.4 | E67: -47% | F67: VERIFIED | G67: Kirkland 35-pack at $13 = $0.371/can
A68: Angostura, 4 oz | B68: Bar Add-Ons D10 | C68: 9 | D68: 12 | E68: +33% | F68: VERIFIED | G68: Total Wine $14.99, Walmart $9.87
A69: Red Bull | B69: Bar Add-Ons D14 | C69: 1.4 | D69: 1.55 | E69: +11% | F69: VERIFIED | G69: Costco 24-pack. Widest warehouse spread of anything checked ($21-45) *** CHECK YELLOW EDITION SEPARATELY (14 Aug 2026): specialty editions often shelf above regular, and this line budgets $1.55/can. Half the buy is now Yellow Edition — see Bar Add-Ons row 14. ***
A70: Coconut water | B70: Bar Add-Ons D16 | C70: 1.1 | D70: 1.25 | E70: +14% | F70: VERIFIED | G70: Vita Coco 18 x 11.1 oz, Costco
A71: Mexican lager, 24-pk | B71: Packaged Prices C11 | C71: 20 | D71: 26.5 | E71: +33% | F71: VERIFIED | G71: *** BIGGEST UNDERSTATEMENT FOUND. $20 was the promo floor; Costco average is $26.80 ***
A72: Kombucha, 48 oz | B72: Packaged Prices C7 | C72: 12 | D72: 9.99 | E72: -17% | F72: VERIFIED | G72: GT's Synergy, Sprouts Reno. See the Clear Mind format problem in the open questions
A73: Sour ale, 6-pk | B73: Packaged Prices C9 | C73: 13 | D73: 12.99 | E73: settled | F73: VERIFIED | G73: Sierra Nevada Wild Little Thing. The placeholder price was right; only the "TBD" needed resolving
A74: Blonde ale, 6-pk | B74: Packaged Prices C10 | C74: 11 | D74: 10.49 | E74: -5% | F74: VERIFIED | G74: Kona Big Wave, Total Wine
A75: Green tea, 12-pk | B75: Packaged Prices C12 | C75: 16 | D75: 18.59 | E75: +16% | F75: VERIFIED | G75: Ito En Oi Ocha, Costco regular. In stock at only ~36% of warehouses
A76: Vodka, 750 ml | B76: B42 | C76: 24 | D76: 15 | E76: -38% | F76: VERIFIED | G76: Tito's, Total Wine
... A81: Whiskey, 750 ml | B81: B47 | C81: 22 | D81: 24.99 | E81: +14% | F81: VERIFIED | G81: Jameson. Ole Smoky Pickles is $21.99 for the novelty bottle
A82: Tangerine, per bottle | B82: B89/B90 | C82: 52 oz @ $5 | D82: 59 oz @ $4.80 | E82: unit fixed | F82: VERIFIED | G82: Perricone Farms 2 x 59 oz, Costco $9.59. In stock at ~63% of warehouses
A83: Tangerine, per quart | B83: B196 | C83: 3.5 | D83: 6.5 | E83: +86% | F83: VERIFIED | G83: Natalie's 32 oz. $3.50 is not achievable for tangerine
A84: Maraschino cherries | B84: B80 | C84: 7.49 | D84: 9.99 | E84: +33% | F84: VERIFIED | G84: Luxardo Costco REGULAR price; $7.49 was a sale. Stocked at only ~24% of warehouses
A85: Grenadine, 25 oz | B85: B74 | C85: 6 | D85: 7.5 | E85: +25% | F85: VERIFIED | G85: Rose's, Smart & Final Reno
A86: ACV, 32 oz | B86: B130 | C86: 5 | D86: 6.17 | E86: +23% | F86: VERIFIED | G86: Bragg organic, Walmart
A87: Tajin, 5 oz | B87: B110 | C87: 4 | D87: 4.68 | E87: +17% | F87: VERIFIED | G87: Walmart
A88: Clamato, 64 oz | B88: B104 | C88: 2.87 | D88: 3.25 | E88: +13% | F88: VERIFIED | G88: Costco warehouse $5.99-6.49 per 2-pack. Costco.com is $10.99 — buy in store
A89: 2 L bottles | B89: B166 | C89: 2.48 | D89: 2.78 | E89: +12% | F89: VERIFIED | G89: Walmart
A90: Cucumbers | B90: B123 | C90: 1 | D90: 1.2 | E90: +20% | F90: VERIFIED | G90: Costco English hothouse 3-ct
A91: Lemons | B91: B100 | C91: 0.25 | D91: 0.29 | E91: +16% | F91: VERIFIED | G91: Costco 5 lb bag
A92: Limes | B92: B112 | C92: 0.3 | D92: 0.32 | E92: +7% | F92: VERIFIED | G92: Costco 3 lb bag. A 40 lb case at Chef'Store Reno is $0.21 each — worth ~$15
A93: Dispensers | B93: Purchase List F69 | C93: 28 ea | D93: 17.50 ea | E93: -38% | F93: VERIFIED | G93: Choice 3-gal, WebstaurantStore. $28 was stainless-tier
A94: 1 gal containers | B94: Purchase List F70 | C94: 9 ea | D94: 4.35 ea | E94: -52% | F94: VERIFIED | G94: Cambro 4 qt 3-pack at $12.99
A95: Ice tubs | B95: Purchase List F72 | C95: 20 ea | D95: 15 ea | E95: -25% | F95: VERIFIED | G95: Sterilite 20 gal, Walmart. A 27 gal HDX is ~$8-10 and holds more
A96: Fresh mint | B96: Purchase List F42 | C96: 12 | D96: 20 | E96: +67% | F96: ESTIMATE | G96: COSTCO CARRIES NO FRESH SOFT HERBS. Grocery bunches $2-3; Walmart clamshells would put this at ~$21
A97: Apples & pears | B97: Purchase List F48 | C97: 10 | D97: 13 | E97: +30% | F97: VERIFIED | G97: ~$0.70 a fruit, but bag minimums mean ~$13 regardless
A98: CONFIRMED UNCHANGED | F98: VERIFIED | G98: Base soda $16/35-pk (Reno #25 at $14.49), soda water $13, Torani $8, cream of coconut $3.98, agave $4.75, OJ $7.49, pineapple juice $3.33, watermelon $7, cider $19.99, lemonade REPRICED — now RTD bottles, see row 34, Radler $9.99
A101: STILL OPEN — decisions, not prices
A102: SAKURA SYRUP is not buyable at $9. Monin cherry blossom is an Asia/Europe SKU, WebstaurantStore returns zero results, and the US options are 200 ml novelty bottles at $18-25 — a third the volume for twice the money. Either budget $18 for a small bottle or substitute Torani Rose (750 ml, $8) with a splash of grenadine for the colour. This changes a named Saturday reveal drink, so it is left unpriced pending a call.
A103: ORANGE FANTA cannot be bought as the model assumes. Costco has no single-flavour Fanta multipack — only a 36-count variety (12 orange / 12 pineapple / 12 strawberry). The build needs 33 orange cans. Either buy the Walmart 24-pack at $0.62/can (+35% on that line) or take the variety pack and find uses for the other two flavours. Base soda pricing is left at the blended case rate pending that choice.
A104: LIQUOR FORMAT. Prices above are 750 ml at Total Wine. Kirkland 1.75 L is dramatically cheaper per 750 ml equivalent — vodka $8.35 against $15, coconut rum $8.46 against $15.49, tequila $9.77-13.67 against $26. Switching means changing Assumptions B41 (bottle size) from 25.4 oz to 59.2 oz and rebuying every line in the 1.75 L format. Worth doing if nobody minds the brand; not applied because it is a taste call.
A105: BREW DR. CLEAR MIND HAS NO 48 OZ BOTTLE. It sells in 14 oz bottles and 4 x 12 oz cans; the "48 oz" listings are 4-packs. Costco carry a Brew Dr. variety 6 x 14 oz including Clear Mind at $11.99 regular / $7.99 on instant savings, which is $0.14/oz against $0.21/oz for GT's 48 oz. Moving the Clear Mind side to that pack saves roughly $40 but needs the Packaged Sizing block reworked.
A106: COFFEE GRIND — DECIDED 14 Aug 2026, was open since 2 Aug. Buying Stone Street EXPLICITLY COARSE, 5 lb bags at $72.99, rather than taking the Kirkland drip grind and adding a filtration pass, or grinding 24 lb of SF Bay whole bean on site. Costco carries no coarse grind at any size. The coarse premium is real and accepted: $14.60/lb vs $7.00/lb, +$197.03 on the line. Buy size was priced three ways — 5 x 5 lb $364.95 (chosen), mixed 4 x 5 lb + 4 x 1 lb $360.96, all singles $414.00. Strainer bags on Supplies row 28 / Purchase List row 92 make the coarse grind a lift-and-drain job; they also do every tea steep.
A107: RING COSTCO RENO BEFORE THE DRIVE. Four lines carry real stock risk: Bundaberg ginger beer (out at 93% of warehouses), Luxardo cherries (~24% stocked), Ito En green tea (~36%, and its promo ends within days), and Perricone tangerine juice (~63%). Also verify ReaLime 48 oz exists as a US Costco SKU — only ReaLemon could be confirmed.
A108: ONE PROMO EXPIRES AROUND THE TRIP: the Ito En green tea instant saving takes it from $18.59 to $9.97 — worth buying early. (The Country Time lemonade powder promo is no longer relevant: the lemonade went ready-to-drink 14 Aug 2026, see row 34.)
A109: WATERMELON JUICE IS AN ESTIMATE, NOT A CHECKED PRICE. Assumptions B218/B219 assume a 1 L (33.8 oz) carton at $4.99. It is no longer the only estimate in the model — the two 1 L mixer prices added on 8 Aug 2026 (B236 soda water, B237 tonic) are also unchecked. See the BevMo section below.
A110: BLANCO TEQUILA IS NOW THE BIGGEST SINGLE LIQUOR LINE, and that changes the 1.75 L argument above. Rawhide and Localhost add 40 servings at a full 1.5 oz each, taking blanco from 6 bottles to 9 — about +$78 at the Espolòn price on Assumptions B45. Kirkland Tequila Blanco is $9.77-13.67 per 750 ml equivalent against $26, so switching just this one line to the 1.75 L format saves more than the two new drinks cost. If you only change one liquor format, change this one.
A112: BEVMO SCOUTING TRIP — 8 Aug 2026
A113: BOUGHT: BOTTLED LEMON JUICE, $4.29 / 32 oz ($0.134/oz). Written into Assumptions B227/B228. Cheaper per oz than fresh lemons ($0.193) and it takes ~25 lemons of squeezing out of the two batch jugs. Fresh lemon stays on the per-drink squeezes only. Net effect: lemons 45 to 20, plus 2 bottles. Costs about $1.30 more in total and saves the labour, which is the trade that was wanted.
...

Sheet Totals by Type
A1: Drink Totals & Cost by Section
A3: Live-linked to every other tab. Drinks come from Kegs / Daily Schedule / Recipes; costs roll up from the Purchase List Category column, then Section C splits each shared pool across the four drink types by a stated basis, so no type is over- or under-charged.
A4: PACKAGED (POST-KEG) VERSION — the 'Kegs' cost category on row 24 is now packaged beer, cider, kombucha and green tea, and 'Rental/gas' on row 26 has fallen to $0. Drink counts and every allocation basis are unchanged, because the swap fills exactly the same servings.
A5: A. DRINKS BY TYPE
A6: Drink type | B6: Drinks | C6: Share | D6: Cost | E6: $ / drink
A7: Straight pour — cold can or bottle handed over | B7: ='Beverage Lines'!$C$13 | C7: =B7/$B$12 | D7: =D49 | E7: =D7/B7
A8: Jug — nightly 10 L daily special | B8: =SUM('Jug Recipes'!$E$4:$E$15) | C8: =B8/$B$12 | D8: =E49 | E8: =D8/B8
A9: Built off a beverage line (Michelada, Tang, both SCOBYs, Clear Cache, Sakura) | B9: =('Dirty Soda - Built Drinks'!$B$3+'Dirty Soda - Built Drinks'!$B$4+'Dirty Soda - Built Drinks'!$B$11+'Dirty Soda - Built Drinks'!$B$13+'Dirty Soda - Built Drinks'!$B$14+'Dirty Soda - Built Drinks'!$B$20) | C9: =B9/$B$12 | D9: =F49 | E9: =D9/B9
A10: Dirty soda — canned base | B10: ='Dirty Soda - Built Drinks'!$B$24-('Dirty Soda - Built Drinks'!$B$3+'Dirty Soda - Built Drinks'!$B$4+'Dirty Soda - Built Drinks'!$B$11+'Dirty Soda - Built Drinks'!$B$13+'Dirty Soda - Built Drinks'!$B$14+'Dirty Soda - Built Drinks'!$B$20) | C10: =B10/$B$12 | D10: =G49 | E10: =D10/B10
A11: Standalone — a can or bottle taken from the cooler | B11: =('Bar Add-Ons'!B14-CEILING('Dirty Soda - Built Drinks'!$B$16*'Dirty Soda - Built Drinks'!$E$16/Assumptions!$B$174,1))+'Bar Add-Ons'!B16+Assumptions!$B$169 | C11: =B11/$B$12 | D11: ='Bar Add-Ons'!E14+'Bar Add-Ons'!E15+'Bar Add-Ons'!E16 | E11: =D11/B11
A12: TOTAL DRINKS / DIRECTLY ATTRIBUTED COST | B12: =SUM(B7:B11) | C12: =SUM(C7:C11) | D12: =SUM(D7:D11) | E12: =D12/B12
A13: Shared cost — not tied to one drink type | D13: =D29+D30+D31+D32+D33-D11
A14: TOTAL PROGRAM COST (excl. refundable deposits) | D14: =D12+D13 | E14: =D14/B12
A15: The built drinks pour off a beverage line but are counted separately because that is where their build cost sits. STANDALONE (row 11) is Red Bull, coconut water and the Grapefruit Radler — cans a camper takes from the cooler with no bartender involved. They were previously left out of the drink count entirely; they are real drinks, so they are now counted and carry their own cost, which is deducted from the shared pool on row 13 so nothing is double-charged. The 12 Red Bulls consumed building Catboy Piss are netted out.
A17: B. COST BY SECTION — straight from the Purchase List categories
A18: Section | B18: Purchase List category | C18: Share | D18: Cost | E18: $ / drink | F18: Rolls up to
A19: Base soda, lemonade, horchata & soda water | B19: Soda | C19: =D19/$D$34 | D19: =SUMIF('Purchase List'!$C$5:$C$109,"Soda",'Purchase List'!$F$5:$F$109) | E19: =D19/$B$12 | F19: Jug + canned dirty soda
A20: Syrups & fruit purees | B20: Syrup | C20: =D20/$D$34 | D20: =SUMIF('Purchase List'!$C$5:$C$109,"Syrup",'Purchase List'!$F$5:$F$109) | E20: =D20/$B$12 | F20: Jug + built + canned
A21: Cream of coconut | B21: Dairy/cream | C21: =D21/$D$34 | D21: =SUMIF('Purchase List'!$C$5:$C$109,"Dairy/cream",'Purchase List'!$F$5:$F$109) | E21: =D21/$B$12 | F21: Jug + canned dirty soda
A22: Built-drink extras + rim salt | B22: Built drink | C22: =D22/$D$34 | D22: =SUMIF('Purchase List'!$C$5:$C$109,"Built drink",'Purchase List'!$F$5:$F$109) | E22: =D22/$B$12 | F22: Built drinks
A23: Fresh produce (limes and the watermelon juice for the canned-base builds; cucumber only if cubes happen) | B23: Fresh produce | C23: =D23/$D$34 | D23: =SUMIF('Purchase List'!$C$5:$C$109,"Fresh produce",'Purchase List'!$F$5:$F$109) | E23: =D23/$B$12 | F23: Canned dirty soda
A24: Packaged beverage — cider, beer, kombucha, green tea | B24: Beverage | C24: =D24/$D$34 | D24: =SUMIF('Purchase List'!$C$5:$C$109,"Beverage",'Purchase List'!$F$5:$F$109) | E24: =D24/$B$12 | F24: Keg + built drinks
A25: Beverage add-ons (aloe, lychee) | B25: Beverage add-on | C25: =D25/$D$34 | D25: =SUMIF('Purchase List'!$C$5:$C$109,"Beverage add-on",'Purchase List'!$F$5:$F$109) | E25: =D25/$B$12 | F25: Keg
A26: Jockey box rental, CO2, lines — $0 with no kegs | B26: Rental/gas | C26: =D26/$D$34 | D26: =SUMIF('Purchase List'!$C$5:$C$109,"Rental/gas",'Purchase List'!$F$5:$F$109) | E26: =D26/$B$12 | F26: Keg + built drinks
A27: Ice tubs for the cold stock | B27: Hardware | C27: =D27/$D$34 | D27: =SUMIF('Purchase List'!$C$5:$C$109,"Hardware",'Purchase List'!$F$5:$F$109) | E27: =D27/$B$12 | F27: Keg + built drinks
A28: Daily special (jug) ingredients | B28: Daily Special | C28: =D28/$D$34 | D28: =SUMIF('Purchase List'!$C$5:$C$109,"Daily Special",'Purchase List'!$F$5:$F$109) | E28: =D28/$B$12 | F28: Jug
A29: Liquor (optional add-on) | B29: Liquor | C29: =D29/$D$34 | D29: =SUMIF('Purchase List'!$C$5:$C$109,"Liquor",'Purchase List'!$F$5:$F$109) | E29: =D29/$B$12 | F29: Shared
A30: Fresh garnish & produce | B30: Garnish | C30: =D30/$D$34 | D30: =SUMIF('Purchase List'!$C$5:$C$109,"Garnish",'Purchase List'!$F$5:$F$109) | E30: =D30/$B$12 | F30: Shared
A31: Misc — catch-all (nothing tagged Misc right now) | B31: Misc | C31: =D31/$D$34 | D31: =SUMIF('Purchase List'!$C$5:$C$109,"Misc",'Purchase List'!$F$5:$F$109) | E31: =D31/$B$12 | F31: Shared
A32: Camp bulk (cold brew, creamer, electrolytes, suan mei tang, mugicha, green tea, Celsius, seltzer, Spindrift, ginger beer) | B32: Camp bulk | C32: =D32/$D$34 | D32: =SUMIF('Purchase List'!$C$5:$C$109,"Camp bulk",'Purchase List'!$F$5:$F$109) | E32: =D32/$B$12 | F32: Shared — see Camp Drinks tab
A33: Bar add-ons (tonic, soda water, Red Bull, bitters) | B33: Add-on | C33: =D33/$D$34 | D33: =SUMIF('Purchase List'!$C$5:$C$109,"Add-on",'Purchase List'!$F$5:$F$109) | E33: =D33/$B$12 | F33: Shared — see Bar Add-Ons tab
A34: PROGRAM TOTAL (excl. refundable deposits) | C34: =SUM(C19:C33) | D34: =SUM(D19:D33) | E34: =D34/$B$12
A36: Memo — keg deposits (REFUNDABLE, cash up front) | B36: Deposit | D36: =SUMIF('Purchase List'!$C$5:$C$109,"Deposit",'Purchase List'!$F$5:$F$109)
A37: Check: sections + deposits vs Purchase List total (should be $0) | D37: =D34+D36-'Purchase List'!$F$110
A39: C. SHARED-INPUT ALLOCATION — how each pool splits across the four types
A40: Shared input pool | B40: Allocation basis | C40: Pool $ | D40: → Keg straight | E40: → Jug | F40: → Built drinks | G40: → Canned dirty soda
A41: Keg liquid + tap infrastructure | B41: servings drawn off the kegs | C41: =D24+D26+D27 | D41: =C41*$B$59/($B$59+$B$60) | E41: 0 | F41: =C41*$B$60/($B$59+$B$60) | G41: =C41-D41-E41-F41
A42: Keg add-ons (aloe, lychee) | B42: 100% straight pours | C42: =D25 | D42: =C42 | E42: 0 | F42: 0 | G42: 0
A43: Base soda, lemonade, horchata & soda water | B43: oz consumed | C43: =D19 | D43: 0 | E43: =C43*$B$53/$B$52 | F43: 0 | G43: =C43-D43-E43-F43
A44: Syrups & fruit purees | B44: oz consumed | C44: =D20 | D44: 0 | E44: =C44*$B$55/$B$54 | F44: =C44*$B$56/$B$54 | G44: =C44-D44-E44-F44
A45: Cream of coconut | B45: oz consumed | C45: =D21 | D45: 0 | E45: =C45*$B$58/$B$57 | F45: 0 | G45: =C45-D45-E45-F45
A46: Built-drink extras + rim salt | B46: 100% built drinks | C46: =D22 | D46: 0 | E46: 0 | F46: =C46 | G46: 0
A47: Fresh produce (limes and watermelon juice; cucumber only if cubes happen) | B47: 100% canned dirty soda | C47: =D23 | D47: 0 | E47: 0 | F47: 0 | G47: =C47
A48: Daily special ingredients | B48: 100% jug | C48: =D28 | D48: 0 | E48: =C48 | F48: 0 | G48: 0
A49: TOTAL ALLOCATED | C49: =SUM(C41:C48) | D49: =SUM(D41:D48) | E49: =SUM(E41:E48) | F49: =SUM(F41:F48) | G49: =SUM(G41:G48)
A51: Supporting figures — the quantities that drive the splits above
A52: Base soda pool — total oz | B52: ='Base Soda — Cans'!$B$14+'Other Consumables'!$B$20
A53: Base soda pool — jug oz | B53: =SUMPRODUCT(('Jug Recipes'!$F$4:$F$15="Sprite")*'Jug Recipes'!$G$4:$G$15)+SUMPRODUCT(('Jug Recipes'!$H$4:$H$15="Sprite")*'Jug Recipes'!$I$4:$I$15)+SUMPRODUCT(('Jug Recipes'!$J$4:$J$15="Sprite")*'Jug Recipes'!$K$4:$K$15)+SUMPRODUCT(('Jug Recipes'!$L$4:$L$15="Sprite")*'Jug Recipes'!$M$4:$M$15)+SUMPRODUCT(('Jug Recipes'!$N$4:$N$15="Sprite")*'Jug Recipes'!$O$4:$O$15)+SUMPRODUCT(('Jug Recipes'!$F$4:$F$15="Mountain Dew")*'Jug Recipes'!$G$4:$G$15)+SUMPRODUCT(('Jug Recipes'!$H$4:$H$15="Mountain Dew")*'Jug Recipes'!$I$4:$I$15)+SUMPRODUCT(('Jug Recipes'!$J$4:$J$15="Mountain Dew")*'Jug Recipes'!$K$4:$K$15)+SUMPRODUCT(('Jug Recipes'!$L$4:$L$15="Mountain Dew")*'Jug Recipes'!$M$4:$M$15)+SUMPRODUCT(('Jug Recipes'!$N$4:$N$15="Mountain Dew")*'Jug Recipes'!$O$4:$O$15)+SUMPRODUCT(('Jug Recipes'!$F$4:$F$15="Lemonade")*'Jug Recipes'!$G$4:$G$15)+SUMPRODUCT(('Jug Recipes'!$H$4:$H$15="Lemonade")*'Jug Recipes'!$I$4:$I$15)+SUMPRODUCT(('Jug Recipes'!$J$4:$J$15="Lemonade")*'Jug Recipes'!$K$4:$K$15)+SUMPRODUCT(('Jug Recipes'!$L$4:$L$15="Lemonade")*'Jug Recipes'!$M$4:$M$15)+SUMPRODUCT(('Jug Recipes'!$N$4:$N$15="Lemonade")*'Jug Recipes'!$O$4:$O$15)+SUMPRODUCT(('Jug Recipes'!$F$4:$F$15="Horchata mix")*'Jug Recipes'!$G$4:$G$15)+SUMPRODUCT(('Jug Recipes'!$H$4:$H$15="Horchata mix")*'Jug Recipes'!$I$4:$I$15)+SUMPRODUCT(('Jug Recipes'!$J$4:$J$15="Horchata mix")*'Jug Recipes'!$K$4:$K$15)+SUMPRODUCT(('Jug Recipes'!$L$4:$L$15="Horchata mix")*'Jug Recipes'!$M$4:$M$15)+SUMPRODUCT(('Jug Recipes'!$N$4:$N$15="Horchata mix")*'Jug Recipes'!$O$4:$O$15)
A54: Syrups & purees — total oz | B54: ='Other Consumables'!$B$12+'Other Consumables'!$B$17+'Other Consumables'!$B$18
A55: Syrups & purees — jug oz | B55: =SUMPRODUCT(('Jug Recipes'!$F$4:$F$15="Peach syrup")*'Jug Recipes'!$G$4:$G$15)+SUMPRODUCT(('Jug Recipes'!$H$4:$H$15="Peach syrup")*'Jug Recipes'!$I$4:$I$15)+SUMPRODUCT(('Jug Recipes'!$J$4:$J$15="Peach syrup")*'Jug Recipes'!$K$4:$K$15)+SUMPRODUCT(('Jug Recipes'!$L$4:$L$15="Peach syrup")*'Jug Recipes'!$M$4:$M$15)+SUMPRODUCT(('Jug Recipes'!$N$4:$N$15="Peach syrup")*'Jug Recipes'!$O$4:$O$15)+SUMPRODUCT(('Jug Recipes'!$F$4:$F$15="Cherry syrup")*'Jug Recipes'!$G$4:$G$15)+SUMPRODUCT(('Jug Recipes'!$H$4:$H$15="Cherry syrup")*'Jug Recipes'!$I$4:$I$15)+SUMPRODUCT(('Jug Recipes'!$J$4:$J$15="Cherry syrup")*'Jug Recipes'!$K$4:$K$15)+SUMPRODUCT(('Jug Recipes'!$L$4:$L$15="Cherry syrup")*'Jug Recipes'!$M$4:$M$15)+SUMPRODUCT(('Jug Recipes'!$N$4:$N$15="Cherry syrup")*'Jug Recipes'!$O$4:$O$15)+SUMPRODUCT(('Jug Recipes'!$F$4:$F$15="Vanilla syrup")*'Jug Recipes'!$G$4:$G$15)+SUMPRODUCT(('Jug Recipes'!$H$4:$H$15="Vanilla syrup")*'Jug Recipes'!$I$4:$I$15)+SUMPRODUCT(('Jug Recipes'!$J$4:$J$15="Vanilla syrup")*'Jug Recipes'!$K$4:$K$15)+SUMPRODUCT(('Jug Recipes'!$L$4:$L$15="Vanilla syrup")*'Jug Recipes'!$M$4:$M$15)+SUMPRODUCT(('Jug Recipes'!$N$4:$N$15="Vanilla syrup")*'Jug Recipes'!$O$4:$O$15)+SUMPRODUCT(('Jug Recipes'!$F$4:$F$15="Pineapple purée")*'Jug Recipes'!$G$4:$G$15)+SUMPRODUCT(('Jug Recipes'!$H$4:$H$15="Pineapple purée")*'Jug Recipes'!$I$4:$I$15)+SUMPRODUCT(('Jug Recipes'!$J$4:$J$15="Pineapple purée")*'Jug Recipes'!$K$4:$K$15)+SUMPRODUCT(('Jug Recipes'!$L$4:$L$15="Pineapple purée")*'Jug Recipes'!$M$4:$M$15)+SUMPRODUCT(('Jug Recipes'!$N$4:$N$15="Pineapple purée")*'Jug Recipes'!$O$4:$O$15)+SUMPRODUCT(('Jug Recipes'!$F$4:$F$15="Passion fruit purée")*'Jug Recipes'!$G$4:$G$15)+SUMPRODUCT(('Jug Recipes'!$H$4:$H$15="Passion fruit purée")*'Jug Recipes'!$I$4:$I$15)+SUMPRODUCT(('Jug Recipes'!$J$4:$J$15="Passion fruit purée")*'Jug Recipes'!$K$4:$K$15)+SUMPRODUCT(('Jug Recipes'!$L$4:$L$15="Passion fruit purée")*'Jug Recipes'!$M$4:$M$15)+SUMPRODUCT(('Jug Recipes'!$N$4:$N$15="Passion fruit purée")*'Jug Recipes'!$O$4:$O$15)
A56: Syrups & purees — built-drink oz (Tang + Sakura passion fruit, Clear Cache peach) | B56: ='Dirty Soda - Built Drinks'!$B$3*'Dirty Soda - Built Drinks'!$I$3+'Dirty Soda - Built Drinks'!$B$13*Assumptions!$B$118+'Dirty Soda - Built Drinks'!$B$14*'Dirty Soda - Built Drinks'!$G$14
A57: Cream of coconut — total oz | B57: ='Other Consumables'!$B$16
A58: Cream of coconut — jug oz | B58: =SUMPRODUCT(('Jug Recipes'!$F$4:$F$15="Coconut cream")*'Jug Recipes'!$G$4:$G$15)+SUMPRODUCT(('Jug Recipes'!$H$4:$H$15="Coconut cream")*'Jug Recipes'!$I$4:$I$15)+SUMPRODUCT(('Jug Recipes'!$J$4:$J$15="Coconut cream")*'Jug Recipes'!$K$4:$K$15)+SUMPRODUCT(('Jug Recipes'!$L$4:$L$15="Coconut cream")*'Jug Recipes'!$M$4:$M$15)+SUMPRODUCT(('Jug Recipes'!$N$4:$N$15="Coconut cream")*'Jug Recipes'!$O$4:$O$15)
A59: Keg servings — poured straight | B59: ='Beverage Lines'!$C$13
A60: Keg servings — leaving as built drinks | B60: =('Dirty Soda - Built Drinks'!$B$3+'Dirty Soda - Built Drinks'!$B$4+'Dirty Soda - Built Drinks'!$B$11+'Dirty Soda - Built Drinks'!$B$13+'Dirty Soda - Built Drinks'!$B$14+'Dirty Soda - Built Drinks'!$B$20)
A61: Keg cost per serving (liquid + tap infrastructure) | B61: =C41/($B$59+$B$60)
A64: Why a straight keg pour and a built drink cost about the same: both draw one serving off a keg, so both carry the same per-serving keg cost (last row above). Liquor, garnish and camp bulk stay unallocated on row 12.

Sheet Beverage Lines
A1: Beverage Lines — packaged drinks poured straight or used as a build base
A2: POST-KEG. Nothing here is a keg any more. This tab sizes how many servings each beverage has to cover; the actual buy is on 'Packaged Sizing'. A 'unit' is the legacy 5-gallon sizing block = 75 servings at 8 oz. The 'Old keg $' columns are kept ONLY as the baseline the packaged swap is measured against — you are not buying them.
A3: POST-KEG. Each line is a finished drink handed over or poured straight (plus optional add-ons). Servings per unit and the baseline price come from Assumptions. Some lines also feed built drinks — the two kombuchas feed Tang Dynasty, the SCOBY Mule and Clear Cache; Mexican Lager feeds the built Michelada; green tea feeds Sakura Kisses — and those servings are subtracted here so nothing is double-counted. THERE ARE NO TAP LINES AND NO ROTATION. Every line is available all week; the day-by-day keg lineup is gone and so is the tab that held it. The "Old keg $" columns are a costing baseline only — you are not buying them.
A5: Beverage | B5: # units (80 servings ea — Assumptions B12) | C5: Servings | D5: Old keg $/ea (baseline only) | E5: Add-ons / garnish ideas | F5: Old keg subtotal (baseline only)
A6: Cider | B6: 1 | C6: =B6*Assumptions!$B$12 | D6: =Assumptions!$B$24 | E6: AVAILABLE ALL WEEK — the old Sun-Mon "other tap line" restriction is gone with the kegs. 80 straight pours, handed over as sealed cans. Cinnamon-sugar rim, apple/pear slice, orange squeeze, rosemary/thyme sprig, candied ginger, pomegranate float. | F6: =B6*(D6+Assumptions!$B$28)
A7: Kombucha — Island Mango | B7: 1 | C7: 0 | D7: =Assumptions!$B$25 | E7: STRAIGHT POURS ARE BACK ON as of 14 Aug 2026 (see Service Availability row 41) — but they are NOT SIZED HERE. This cell stays 0 so the variety-pack count matches the 5 packs ordered; straight pours come out of the spare, which is mostly Superberry. See Packaged Sizing section 7. This line feeds Tang Dynasty (recipe row 3) only — the SCOBY Mule moved to Superberry the same day. Flavour is ISLAND MANGO, not passionfruit: the Brew Dr. variety pack has no passionfruit and Clear Mind has no 48 oz bottle, which is what forced the format change. | F7: =B7*(D7+Assumptions!$B$28)
A8: Sour Ale | B8: 1 | C8: =B8*Assumptions!$B$12 | D8: =Assumptions!$B$58 | E8: 100% straight pours. SPECIFIC BEER TBD — Ancho Paloma was the placeholder; serve style and garnish to be revisited once the beer is chosen. NOT used as a shandy base: a sour is already light and acidic, so lemonade puts acid on acid. The shandy slot is filled by pre-made Stiegl Radler on the Bar Add-Ons tab. | F8: =B8*(D8+Assumptions!$B$28)
A9: Green tea | B9: 1 | C9: =B9*Assumptions!$B$12-'Dirty Soda - Built Drinks'!$B$13 | D9: =Assumptions!$B$27 | E9: AVAILABLE ALL WEEK — the old "Saturday only, other tap line" restriction is gone (Service Availability row 70). 80 servings total: 33 go to the built SAKURA KISSES (Dirty Soda - Built Drinks ROW 13, which IS still Saturday-only), leaving 47 poured straight as the GREEN TEA REFRESHER: aloe vera drink + tea, optional lychee + syrup, mint, cucumber, yuzu, honey, agar boba. The built servings are netted out here so they are not double-counted. SOURCE SPLIT AS OF 14 Aug 2026: the bottled buy is 2 x 12-packs and covers 380 oz; the last 128 oz — about 16 Refreshers — is COLD-STEEPED from teabags (Assumptions B263). Availability is unchanged, only where the liquid comes from. NOTE: the 47 is derived (80 per unit minus 33 built), not a demand estimate — the old note here claimed "the keg’s 50 pours" and pointed at the wrong recipe row; both were wrong and are corrected. | F9: =B9*(D9+Assumptions!$B$28)+Assumptions!$B$63*Assumptions!$B$62
A10: Blonde Ale | B10: 1 | C10: =B10*Assumptions!$B$66 | D10: =Assumptions!$B$59*Assumptions!$B$65 | E10: AVAILABLE ALL WEEK — the old Fri-Sat slot is gone with the kegs. 40 straight pours (this line was sized as a half keg, which is why it is 40 and not 80); handed over as sealed cans. | F10: =B10*(D10+Assumptions!$B$28)
A11: Mexican Lager | B11: 1 | C11: =B11*Assumptions!$B$12-'Dirty Soda - Built Drinks'!$B$4 | D11: =Assumptions!$B$67 | E11: AVAILABLE ALL WEEK — the old Wed-Thu "beer line" slot is gone with the kegs. 80 servings total: 30 go to the built MICHELADA (chelada mix, Tajin rim, lime, Clamato) and 50 are straight pours handed over as sealed cans. The Michelada servings are netted out of this row so they are not double-counted against the built-drinks tab. (The old note said "30 built + 20 straight"; the straight figure was wrong.) | F11: =B11*(D11+Assumptions!$B$28)
A12: Kombucha — Clear Mind | B12: 1 | C12: 0 | D12: =Assumptions!$B$145 | E12: STRAIGHT POURS ARE BACK ON as of 14 Aug 2026, but not sized here — see row 7 and Packaged Sizing section 7. Clear Mind has only ~14 oz of slack, so steer plain-kombucha requests to Superberry. This line feeds the built Clear Cache (peach + yuzu + sage, Recipes B14). Herbaceous and savoury — it was never the crowd pour anyway. | F12: =B12*(D12+Assumptions!$B$28)
A13: TOTAL | B13: =SUM(B6:B12) | C13: =SUM(C6:C12) | F13: =SUM(F6:F12)

Sheet Packaged Prices
A1: Packaged Sizing — packaged unit prices (yellow cells editable)
A3: Prices for buying every keg beverage in bottles/cans instead. Kombucha is the price you gave ($12 per 48 oz). Beer, cider and green tea are July 2026 retail sampled from Costco / grocery listings — treat them as ballpark and swap in real Reno quotes. Everything on the 'Packaged Sizing' tab recalculates from these six rows.
A5: PACKAGED FORMATS
A6: Beverage | B6: oz per unit | C6: $ per unit | D6: $ / oz | E6: Format | F6: Source / basis
A7: Kombucha — Brew Dr. variety pack (2 Clear Mind / 2 Island Mango / 2 Superberry) | B7: 84 | C7: 11.99 | D7: =C7/B7 | E7: 6 x 14 oz variety pack | F7: SWITCHED 14 Aug 2026 — resolves this row’s own flagged spec bug. Brew Dr. Clear Mind HAS NO 48 OZ BOTTLE; the old GT’s Synergy 48 oz @ $9.99 line was buying a product that does not exist. Now the Brew Dr. 6 x 14 oz variety pack, Costco Reno: $11.99 regular, $7.99 on instant savings. $0.143/oz against $0.208/oz before. ONE PACK YIELDS 28 OZ OF EACH OF THREE FLAVOURS (2 bottles each), which is why pack count is NOT derived by dividing total kombucha oz by 84 — see ‘Packaged Sizing’ SECTION 7, which sizes each flavour against its own 28 oz/pack and takes the MAX. B7 is kept at the true 84 oz so the $/oz in column D stays honest.
A8: Hard cider | B8: 144 | C8: 20 | D8: =C8/B8 | E8: 12-pack, 12 oz cans | F8: Angry Orchard Crisp Apple 12x12oz: $19.99 Jewel-Osco, $20.19 Walmart, $21.99 Acme, $22.99 Vons; Costco Fireside mix pack $17.99-$19.89. Using $20.
A9: Sour ale / Shandy | B9: 72 | C9: 12.99 | D9: =C9/B9 | E9: 6-pack, 12 oz cans | F9: RESOLVED 2 Aug 2026 — the placeholder price was accurate, only the "TBD" needed settling. Sierra Nevada Wild Little Thing, $12.99/6-pack, is the pick: Chico CA brewery with saturation distribution in northern Nevada, 5.5%, guava/hibiscus/strawberry. Second choice Dogfish Head SeaQuench (~$12-13), a 4.9% lime-and-sea-salt session sour that is functionally an electrolyte beer — arguably the better playa drink. Anderson Valley Gose is a fine third but showed OUT OF STOCK at Total Wine, so do not make it primary.
A10: Blonde ale | B10: 72 | C10: 10.49 | D10: =C10/B10 | E10: 6-pack, 12 oz cans | F10: REPRICED: Kona Big Wave 6-pack $10.49 at Total Wine. (Firestone 805 24-pack works out to ~$8/6-pack.)
A11: Mexican lager | B11: 288 | C11: 26.5 | D11: =C11/B11 | E11: 24-pack, 12 oz cans | F11: REPRICED 2 Aug 2026 — THE BIGGEST UNDERSTATEMENT FOUND. $20 was the promo floor, not the shelf price: Modelo Especial 24 x 12 oz at Costco ranges $19.76-34.69 with a $26.80 average (tracker, 3 Aug 2026). Budgeting $26.50.
A12: Green tea, unsweetened | B12: 202.8 | C12: 18.59 | D12: =C12/B12 | E12: 12 x 16.9 oz bottles | F12: REPRICED: Ito En Oi Ocha 12 x 16.9 oz, Costco $18.59 regular — currently $9.97 on instant savings, so it could land at half this. STOCK RISK: in stock at only ~36% of warehouses and the promo ends within days. Have a backup.
A14: OPERATING INPUTS
A15: Open-container waste buffer | B15: 0.05 | F15: Bottles/cans opened and not finished. Deliberately lower than the 15% keg buffer (Assumptions B5) because packaged drinks have no foam, no line loss and no 40 oz first-pull allowance.
A16: Serve beer & cider as WHOLE cans? | B16: 1 | F16: 1 = Scenario B (recommended): a straight beer/cider/lager pour is one sealed 12 oz can handed over. 0 = Scenario A: crack cans and pour 8 oz measures like the keg model does. This cell picks which scenario feeds the Purchase List.
A17: Can size served whole (oz) | B17: 12 | F17: Size of the can you actually hand someone. Change to 16 if you buy tallboys/4-packs.

Sheet Packaged Sizing
A1: Packaged Sizing — bottles & cans instead of 8 kegs, same servings
A3: Every keg on the Beverage Lines tab is replaced by packaged product sized to fill the SAME number of servings. Servings pull live from the Beverage Lines tab (straight pours) and the Recipes tab (built drinks), so this stays correct if the menu changes. STRAIGHT KOMBUCHA IS CUT: the two kombucha lines are sized purely to feed Tang Dynasty, the SCOBY Mule and Clear Cache (SCOBY-Dew was retired 11 Aug 2026, which is why the passionfruit bottle count fell from 7 to 5). Total to replace: 427 servings — 274 straight pours plus 153 built.
A5: 1. SERVINGS TO REPLACE — live from the Beverage Lines tab
A6: Was (keg) | B6: Servings — straight | C6: Servings — built | D6: Servings — TOTAL | E6: Pour size (oz) | F6: Liquid oz needed | G6: Built draw (oz ea)
A7: Cider | B7: ='Beverage Lines'!C6 | C7: 0 | D7: =B7+C7 | E7: =Assumptions!$B$120 | F7: =B7*E7+C7*G7 | G7: 0
A8: Kombucha — Island Mango + Superberry (Tang Dynasty + SCOBY Mule) | B8: ='Beverage Lines'!C7 | C8: ='Dirty Soda - Built Drinks'!$B$3+'Dirty Soda - Built Drinks'!$B$11 | D8: =B8+C8 | E8: =Assumptions!$B$120 | F8: =B8*E8+C8*G8 | G8: ='Dirty Soda - Built Drinks'!$E$3
A9: Sour Ale | B9: ='Beverage Lines'!C8 | C9: 0 | D9: =B9+C9 | E9: =Assumptions!$B$120 | F9: =B9*E9+C9*G9 | G9: 0
A10: Green tea | B10: ='Beverage Lines'!C9 | C10: ='Dirty Soda - Built Drinks'!$B$13 | D10: =B10+C10 | E10: =Assumptions!$B$120 | F10: =B10*E10+C10*G10-Assumptions!$B$263 | G10: ='Dirty Soda - Built Drinks'!$E$13
A11: Blonde Ale | B11: ='Beverage Lines'!C10 | C11: 0 | D11: =B11+C11 | E11: =Assumptions!$B$120 | F11: =B11*E11+C11*G11 | G11: 0
A12: Mexican Lager | B12: ='Beverage Lines'!C11 | C12: ='Dirty Soda - Built Drinks'!$B$4 | D12: =B12+C12 | E12: =Assumptions!$B$120 | F12: =B12*E12+C12*G12 | G12: ='Dirty Soda - Built Drinks'!$E$4
A13: Kombucha — Clear Mind (Clear Cache) | B13: ='Beverage Lines'!C12 | C13: ='Dirty Soda - Built Drinks'!$B$14 | D13: =B13+C13 | E13: =Assumptions!$B$120 | F13: =B13*E13+C13*G13 | G13: ='Dirty Soda - Built Drinks'!$E$14
A14: TOTAL SERVINGS OFF KEGS | B14: =SUM(B7:B13) | C14: =SUM(C7:C13) | D14: =SUM(D7:D13) | F14: =SUM(F7:F13)
A15: BUILT DRINKS DO NOT DRAW A FULL POUR. A Tang Dynasty is 4 oz of kombucha in a 10 oz cup, not 8; a Michelada is 6 oz of lager; a Shandy is 6 oz of beer. Column G reads the real draw straight off the Recipes tab, so 'liquid oz needed' is now servings x actual draw rather than servings x 8. Before this, every built drink was sized as if it emptied a full pour — which over-bought the kombucha, green tea and lager lines by roughly a third.
A16: 2. SCENARIO A — crack cans and pour 8 oz measures (cheapest liquid)
A17: Buy instead | B17: oz needed | C17: + waste buffer | D17: Format | E17: oz / unit | F17: $ / unit | G17: UNITS TO BUY | H17: Cost | I17: Keg baseline $ | J17: Δ vs keg
A18: Cider | B18: =F7 | C18: =B18*(1+'Packaged Prices'!$B$15) | D18: ='Packaged Prices'!$E$8 | E18: ='Packaged Prices'!$B$8 | F18: ='Packaged Prices'!$C$8 | G18: =CEILING(C18/E18,1) | H18: =G18*F18 | I18: ='Beverage Lines'!B6*'Beverage Lines'!D6 | J18: =H18-I18
A19: Kombucha — VARIETY PACKS, ALL THREE FLAVOURS (see section 7) | B19: =F8 | C19: =B19*(1+'Packaged Prices'!$B$15) | D19: ='Packaged Prices'!$E$7 | E19: ='Packaged Prices'!$B$7 | F19: ='Packaged Prices'!$C$7 | G19: =$H$81 | H19: =G19*F19 | I19: ='Beverage Lines'!B7*'Beverage Lines'!D7 | J19: =H19-I19
A20: Sour Ale | B20: =F9 | C20: =B20*(1+'Packaged Prices'!$B$15) | D20: ='Packaged Prices'!$E$9 | E20: ='Packaged Prices'!$B$9 | F20: ='Packaged Prices'!$C$9 | G20: =CEILING(C20/E20,1) | H20: =G20*F20 | I20: ='Beverage Lines'!B8*'Beverage Lines'!D8 | J20: =H20-I20
A21: Green tea | B21: =F10 | C21: =B21*(1+'Packaged Prices'!$B$15) | D21: ='Packaged Prices'!$E$12 | E21: ='Packaged Prices'!$B$12 | F21: ='Packaged Prices'!$C$12 | G21: =CEILING(C21/E21,1) | H21: =G21*F21 | I21: ='Beverage Lines'!B9*'Beverage Lines'!D9 | J21: =H21-I21
A22: Blonde Ale | B22: =F11 | C22: =B22*(1+'Packaged Prices'!$B$15) | D22: ='Packaged Prices'!$E$10 | E22: ='Packaged Prices'!$B$10 | F22: ='Packaged Prices'!$C$10 | G22: =CEILING(C22/E22,1) | H22: =G22*F22 | I22: ='Beverage Lines'!B10*'Beverage Lines'!D10 | J22: =H22-I22
A23: Mexican Lager | B23: =F12 | C23: =B23*(1+'Packaged Prices'!$B$15) | D23: ='Packaged Prices'!$E$11 | E23: ='Packaged Prices'!$B$11 | F23: ='Packaged Prices'!$C$11 | G23: =CEILING(C23/E23,1) | H23: =G23*F23 | I23: ='Beverage Lines'!B11*'Beverage Lines'!D11 | J23: =H23-I23
A24: Kombucha (Clear Mind) — INCLUDED IN THE PACKS ON ROW 19, zeroed so it does not double-count | B24: =F13 | C24: =B24*(1+'Packaged Prices'!$B$15) | D24: ='Packaged Prices'!$E$7 | E24: ='Packaged Prices'!$B$7 | F24: ='Packaged Prices'!$C$7 | G24: 0 | H24: =G24*F24 | I24: ='Beverage Lines'!B12*'Beverage Lines'!D12 | J24: =H24-I24
A25: SCENARIO A TOTAL | C25: =SUM(C18:C24) | H25: =SUM(H18:H24) | I25: =SUM(I18:I24) | J25: =SUM(J18:J24) | K25: Liquid only — the jockey box, CO2 and deposits savings are in section 5.
A27: 3. SCENARIO B — beer, cider & lager handed over as whole 12 oz cans (RECOMMENDED)
A28: Buy instead | B28: Straight servings | C28: oz each (whole can) | D28: Built servings | E28: oz each (measured) | F28: oz needed | G28: + waste buffer | H28: oz / unit | I28: $ / unit | J28: UNITS TO BUY | K28: Cost | L28: Keg baseline $ | M28: Δ vs keg
A29: Cider | B29: =B7 | C29: ='Packaged Prices'!$B$17 | D29: =C7 | E29: =G7 | F29: =B29*C29+D29*E29 | G29: =F29*(1+'Packaged Prices'!$B$15) | H29: ='Packaged Prices'!$B$8 | I29: ='Packaged Prices'!$C$8 | J29: =CEILING(G29/H29,1) | K29: =J29*I29 | L29: ='Beverage Lines'!B6*'Beverage Lines'!D6 | M29: =K29-L29
A30: Kombucha — VARIETY PACKS, ALL THREE FLAVOURS (see section 7) | B30: =B8 | C30: =Assumptions!$B$120 | D30: =C8 | E30: =G8 | F30: =B30*C30+D30*E30 | G30: =F30*(1+'Packaged Prices'!$B$15) | H30: ='Packaged Prices'!$B$7 | I30: ='Packaged Prices'!$C$7 | J30: =$H$81 | K30: =J30*I30 | L30: ='Beverage Lines'!B7*'Beverage Lines'!D7 | M30: =K30-L30
A31: Sour Ale | B31: =B9 | C31: ='Packaged Prices'!$B$17 | D31: =C9 | E31: =G9 | F31: =B31*C31+D31*E31 | G31: =F31*(1+'Packaged Prices'!$B$15) | H31: ='Packaged Prices'!$B$9 | I31: ='Packaged Prices'!$C$9 | J31: =CEILING(G31/H31,1) | K31: =J31*I31 | L31: ='Beverage Lines'!B8*'Beverage Lines'!D8 | M31: =K31-L31
A32: Green tea | B32: =B10 | C32: =Assumptions!$B$120 | D32: =C10 | E32: =G10 | F32: =B32*C32+D32*E32-Assumptions!$B$263 | G32: =F32*(1+'Packaged Prices'!$B$15) | H32: ='Packaged Prices'!$B$12 | I32: ='Packaged Prices'!$C$12 | J32: =CEILING(G32/H32,1) | K32: =J32*I32 | L32: ='Beverage Lines'!B9*'Beverage Lines'!D9 | M32: =K32-L32
A33: Blonde Ale | B33: =B11 | C33: ='Packaged Prices'!$B$17 | D33: =C11 | E33: =G11 | F33: =B33*C33+D33*E33 | G33: =F33*(1+'Packaged Prices'!$B$15) | H33: ='Packaged Prices'!$B$10 | I33: ='Packaged Prices'!$C$10 | J33: =CEILING(G33/H33,1) | K33: =J33*I33 | L33: ='Beverage Lines'!B10*'Beverage Lines'!D10 | M33: =K33-L33
A34: Mexican Lager | B34: =B12 | C34: ='Packaged Prices'!$B$17 | D34: =C12 | E34: =G12 | F34: =B34*C34+D34*E34 | G34: =F34*(1+'Packaged Prices'!$B$15) | H34: ='Packaged Prices'!$B$11 | I34: ='Packaged Prices'!$C$11 | J34: =CEILING(G34/H34,1) | K34: =J34*I34 | L34: ='Beverage Lines'!B11*'Beverage Lines'!D11 | M34: =K34-L34
A35: Kombucha (Clear Mind) — INCLUDED IN THE PACKS ON ROW 30, zeroed so it does not double-count | B35: =B13 | C35: =Assumptions!$B$120 | D35: =C13 | E35: =G13 | F35: =B35*C35+D35*E35 | G35: =F35*(1+'Packaged Prices'!$B$15) | H35: ='Packaged Prices'!$B$7 | I35: ='Packaged Prices'!$C$7 | J35: 0 | K35: =J35*I35 | L35: ='Beverage Lines'!B12*'Beverage Lines'!D12 | M35: =K35-L35
A36: SCENARIO B TOTAL | G36: =SUM(G29:G35) | K36: =SUM(K29:K35) | L36: =SUM(L29:L35) | M36: =SUM(M29:M35)
A37: Kombucha and green tea are identical in both scenarios — they are mixers and built-drink bases, so they get poured either way. Only beer, cider and the lager change: their straight pours go from an 8 oz cup to a whole 12 oz can, which is 50% more liquid per serving. That is the real cost of losing pour control, and it is why Scenario B is the honest number to budget against.
A38: 4. SHOPPING LIST — whichever scenario is selected on 'Packaged Prices' B16
A39: Buy | B39: UNITS TO BUY | C39: Unit | D39: Cost
A40: Cider | B40: =IF('Packaged Prices'!$B$16=1,J29,G18) | C40: 12-packs (12 oz cans) | D40: =IF('Packaged Prices'!$B$16=1,K29,H18)
A41: Kombucha — Brew Dr. variety packs (ALL FLAVOURS) | B41: =IF('Packaged Prices'!$B$16=1,J30,G19) | C41: 6 x 14 oz variety packs | D41: =IF('Packaged Prices'!$B$16=1,K30,H19)
A42: Sour Ale | B42: =IF('Packaged Prices'!$B$16=1,J31,G20) | C42: 6-packs (12 oz cans) | D42: =IF('Packaged Prices'!$B$16=1,K31,H20)
A43: Green tea | B43: =IF('Packaged Prices'!$B$16=1,J32,G21) | C43: 12-packs (16.9 oz bottles) | D43: =IF('Packaged Prices'!$B$16=1,K32,H21)
A44: Blonde Ale | B44: =IF('Packaged Prices'!$B$16=1,J33,G22) | C44: 6-packs (12 oz cans) | D44: =IF('Packaged Prices'!$B$16=1,K33,H22)
A45: Mexican Lager | B45: =IF('Packaged Prices'!$B$16=1,J34,G23) | C45: 24-packs (12 oz cans) | D45: =IF('Packaged Prices'!$B$16=1,K34,H23)
A46: Kombucha (Clear Mind) — MERGED INTO ROW 41, reads 0 on purpose | B46: =IF('Packaged Prices'!$B$16=1,J35,G24) | C46: — (included in row 41) | D46: =IF('Packaged Prices'!$B$16=1,K35,H24)
A47: TOTAL PACKAGED BEVERAGE | D47: =SUM(D40:D46) | F47: Purchase List rows 19, 20, 21, 38, 39, 40 and 74 now read their Qty and $ straight off this block.
A50: 5. HEADLINE — cash out the door
A51: Line | B51: Keg program | C51: No kegs — A (poured) | D51: No kegs — B (whole cans) | F51: Note
A52: Beverage liquid | B52: =I25 | C52: =H25 | D52: =K36 | F52: Keg column is 8 kegs of liquid; no-keg columns are sections 2 and 3.
A53: Jockey box rental (3 x 4-day) | B53: =Assumptions!$B$34*Assumptions!$B$33 | C53: 0 | D53: 0 | F53: Purchase List row 27. Gone entirely — nothing to chill through a coil.
A54: CO2 refills | B54: =Assumptions!$B$36*Assumptions!$B$35 | C54: 0 | D54: 0 | F54: Purchase List row 25. Gone — no gas to push anything.
A55: Jumper lines, washers, faucet wrench | B55: =20 | C55: 0 | D55: 0 | F55: Purchase List row 30. Gone.
A56: TOTAL | B56: =SUM(B52:B55) | C56: =SUM(C52:C55) | D56: =SUM(D52:D55)
A57: SAVING vs the keg program | C57: =B56-C56 | D57: =B56-D56
A58: Saving as % of the keg program | C58: =C57/$B$56 | D58: =D57/$B$56
A59: Saving per serving replaced | C59: =C57/$D$14 | D59: =D57/$D$14
A61: Memo — refundable keg deposits no longer fronted | B61: ='Beverage Lines'!B13*Assumptions!$B$32 | F61: Not a saving — it always came back. But it is cash you no longer have to carry to Reno and no empties you have to haul back to Mike's before the deposit window closes.
A63: New program total (Totals by Type D13, recalculated) | B63: ='Totals by Type'!$D$14 | F63: The Purchase List and Totals by Type tabs in THIS file have been rewired to the no-keg plan, so that figure is already the new bottom line. Keg program was $3,872.
A65: 6. WHAT THE MONEY DOESN'T SHOW
A66: PORTION CONTROL IS THE REAL COST. The keg model pours 8 oz on purpose (Assumptions B120: 'less waste when someone wanders off'). A can is 12 oz and cannot be poured half. Scenario B budgets for that honestly; Scenario A pretends you will pour measured cups out of open cans, which on a dusty playa bar means flat, warm, half-finished cans everywhere.
A67: KOMBUCHA WAS THE ONE PLACE KEGS WON — AND IT IS NOW THE SMALLEST LINE ON THE BOARD. At $12 / 48 oz you pay $0.250 per oz against $0.217 for keg liquid, so bottling it was the one swap that cost more. Cutting the straight pours settles it: kombucha demand drops from 225 servings to the 90 the built drinks actually need, and the spend goes from $492 to $204. Buying that in bottles is now unambiguously right — a keg would leave you with ~500 oz of flat kombucha nobody ordered.
A68: MEXICAN LAGER IS THE BIGGEST WIN. $20 for a 24-pack is $0.069/oz against $150 for the keg ($0.250/oz usable). Same for the craft styles once you drop from keg pricing to retail 6-packs.
A69: MOOP AND HAULING. 8 kegs is 8 objects in and 8 objects out. The no-keg plan is roughly 55-70 packages, and every can becomes MOOP you pack out. Budget bin space and a can crusher. Against that: no keg deposits, no 160 lb of full kegs, no coil box, no CO2 tank, no ice bath for kegs.
A70: COLD CHAIN CHANGES SHAPE, NOT SIZE. You still need the two 19-gallon tubs (Purchase List row 90) — they now hold cans on ice instead of kegs. Cans chill far faster than a keg, so the jockey box's whole job disappears; ice demand goes down, not up. Ice is not costed anywhere in this workbook — camp lead covers it.
A71: SERVICE SPEED. Handing someone a can is faster than pulling a pour, and there is no foaming when ambient is over 100F (the Jockey Box tab warns 50' coils foam badly in playa heat). But the built drinks — Michelada, Tang Dynasty, the SCOBY Mule, Clear Cache, Sakura Kisses — get slower, because every one of them now starts with opening a package instead of pulling a tap.
A72: THE JOCKEY BOX TAB IS NOW MOOT. 'Jockey Box — Buy vs Rent' still sits in this file for reference, but with no kegs there is nothing to buy or rent. If the camp goes no-keg permanently, that buy-vs-rent decision goes away with it.
A73: PRICES ARE ESTIMATES. Kombucha is your number. Beer, cider and green tea are July 2026 retail sampled from Costco / grocery listings, not Reno quotes. The sour ale is unpriced until the specific beer is chosen. Every one of these lives on 'Packaged Prices' and everything downstream recalculates when you swap in a real number.
A75: 7. KOMBUCHA — VARIETY-PACK FLAVOUR ALLOCATION (added 14 Aug 2026)
A76: ONE SKU FEEDS THREE LINES, so packs cannot be summed across flavours. Each pack gives 28 oz (2 x 14 oz) of EACH flavour. Every flavour is sized against its own 28 oz/pack, and the number you actually buy is the MAX of the three — one pack serves all three at once. Sections 2, 3 and 4 above now read the MAX off H81, and the second kombucha line in each is forced to zero so nothing double-counts.
A77: Flavour | B77: Drink it feeds | C77: Servings | D77: oz / serving | E77: oz needed | F77: + waste buffer | G77: oz of this flavour per pack | H77: PACKS THIS FLAVOUR NEEDS
A78: Island Mango | B78: Tang Dynasty | C78: ='Dirty Soda - Built Drinks'!$B$3 | D78: ='Dirty Soda - Built Drinks'!$E$3 | E78: =C78*D78 | F78: =E78*(1+'Packaged Prices'!$B$15) | G78: 28 | H78: =CEILING(F78/G78,1)
A79: Clear Mind | B79: Clear Cache | C79: ='Dirty Soda - Built Drinks'!$B$14 | D79: ='Dirty Soda - Built Drinks'!$E$14 | E79: =C79*D79 | F79: =E79*(1+'Packaged Prices'!$B$15) | G79: 28 | H79: =CEILING(F79/G79,1)
A80: Superberry | B80: SCOBY Mule | C80: ='Dirty Soda - Built Drinks'!$B$11 | D80: ='Dirty Soda - Built Drinks'!$E$11 | E80: =C80*D80 | F80: =E80*(1+'Packaged Prices'!$B$15) | G80: 28 | H80: =CEILING(F80/G80,1)
A81: PACKS TO BUY — MAX, not sum (one pack serves all three) | H81: =MAX(H78:H80)
A82: Cost | H82: =H81*'Packaged Prices'!$C$7
A83: Spare, by flavour (oz) | C83: =$H$81*G78-F78 | D83: =$H$81*G79-F79 | E83: =$H$81*G80-F80 | G83: Island Mango / Clear Mind / Superberry — spare in C83, D83, E83
A84: THE SPARE IS WHAT STRAIGHT KOMBUCHA POURS COME OUT OF. There is no separate straight-pour allowance in the buy: ‘Beverage Lines’ C7/C12 stay at 0 so the pack count matches what was actually ordered (5). At an 8 oz pour (Assumptions B120) the spare is roughly 10 straight servings across the whole week, and MOST OF IT IS SUPERBERRY. Steer anyone asking for a plain kombucha to Superberry; Clear Mind and Island Mango have ~14 oz of slack each and are needed for their builds.

Sheet Base Soda — Cans
A1: Base Soda Requirement → Cans & Cases
A3: Base soda | B3: Total oz | C3: +buffer | D3: Cans | E3: Cases | F3: Note | G3: 2 L bottles | H3: oz from 2 L | I3: Jug draw (oz) | J3: 2 L — extra (manual)
A4: Sprite | B4: =SUMPRODUCT(('Dirty Soda - Built Drinks'!$D$3:$D$23=A4)*'Dirty Soda - Built Drinks'!$E$3:$E$23*'Dirty Soda - Built Drinks'!$B$3:$B$23)+SUMPRODUCT(('Dirty Soda - Built Drinks'!$D$3:$D$23="Squirt")*2*'Dirty Soda - Built Drinks'!$B$3:$B$23)+SUMPRODUCT(('Jug Recipes'!$F$4:$F$15="Sprite")*'Jug Recipes'!$G$4:$G$15)+SUMPRODUCT(('Jug Recipes'!$H$4:$H$15="Sprite")*'Jug Recipes'!$I$4:$I$15)+SUMPRODUCT(('Jug Recipes'!$J$4:$J$15="Sprite")*'Jug Recipes'!$K$4:$K$15)+SUMPRODUCT(('Jug Recipes'!$L$4:$L$15="Sprite")*'Jug Recipes'!$M$4:$M$15)+SUMPRODUCT(('Jug Recipes'!$N$4:$N$15="Sprite")*'Jug Recipes'!$O$4:$O$15) | C4: =B4*(1+Assumptions!$B$5) | D4: =CEILING(MAX(C4-H4,0)/(Assumptions!$B$7*Assumptions!$B$157),1) | E4: =CEILING(D4/Assumptions!$B$6,1) | F4: Cherry Bomb jug (82.5 oz) comes out of the 2 L — now DERIVED in column G, not typed. The rest — Shirley Temple of Doom + the Squirt top-up — stays in cans. | G4: =CEILING(I4*(1+Assumptions!$B$5)/Assumptions!$B$165,1)+J4 | H4: =G4*Assumptions!$B$165 | I4: =SUMPRODUCT(('Jug Recipes'!$F$4:$F$15=$A$4)*'Jug Recipes'!$G$4:$G$15)+SUMPRODUCT(('Jug Recipes'!$H$4:$H$15=$A$4)*'Jug Recipes'!$I$4:$I$15)+SUMPRODUCT(('Jug Recipes'!$J$4:$J$15=$A$4)*'Jug Recipes'!$K$4:$K$15)+SUMPRODUCT(('Jug Recipes'!$L$4:$L$15=$A$4)*'Jug Recipes'!$M$4:$M$15)+SUMPRODUCT(('Jug Recipes'!$N$4:$N$15=$A$4)*'Jug Recipes'!$O$4:$O$15) | J4: 0
A5: Coke | B5: =SUMPRODUCT(('Dirty Soda - Built Drinks'!$D$3:$D$23=A5)*'Dirty Soda - Built Drinks'!$E$3:$E$23*'Dirty Soda - Built Drinks'!$B$3:$B$23) | C5: =B5*(1+Assumptions!$B$5) | D5: =CEILING(MAX(C5-H5,0)/(Assumptions!$B$7*Assumptions!$B$157),1) | E5: =CEILING(D5/Assumptions!$B$6,1) | G5: =CEILING(I5*(1+Assumptions!$B$5)/Assumptions!$B$165,1)+J5 | H5: =G5*Assumptions!$B$165 | I5: =SUMPRODUCT(('Jug Recipes'!$F$4:$F$15=$A$5)*'Jug Recipes'!$G$4:$G$15)+SUMPRODUCT(('Jug Recipes'!$H$4:$H$15=$A$5)*'Jug Recipes'!$I$4:$I$15)+SUMPRODUCT(('Jug Recipes'!$J$4:$J$15=$A$5)*'Jug Recipes'!$K$4:$K$15)+SUMPRODUCT(('Jug Recipes'!$L$4:$L$15=$A$5)*'Jug Recipes'!$M$4:$M$15)+SUMPRODUCT(('Jug Recipes'!$N$4:$N$15=$A$5)*'Jug Recipes'!$O$4:$O$15) | J5: 0
A6: Orange Fanta | B6: =SUMPRODUCT(('Dirty Soda - Built Drinks'!$D$3:$D$23=A6)*'Dirty Soda - Built Drinks'!$E$3:$E$23*'Dirty Soda - Built Drinks'!$B$3:$B$23) | C6: =B6*(1+Assumptions!$B$5) | D6: =CEILING(MAX(C6-H6,0)/(Assumptions!$B$7*Assumptions!$B$157),1) | E6: =CEILING(D6/Assumptions!$B$6,1) | G6: =CEILING(I6*(1+Assumptions!$B$5)/Assumptions!$B$165,1)+J6 | H6: =G6*Assumptions!$B$165 | I6: =SUMPRODUCT(('Jug Recipes'!$F$4:$F$15=$A$6)*'Jug Recipes'!$G$4:$G$15)+SUMPRODUCT(('Jug Recipes'!$H$4:$H$15=$A$6)*'Jug Recipes'!$I$4:$I$15)+SUMPRODUCT(('Jug Recipes'!$J$4:$J$15=$A$6)*'Jug Recipes'!$K$4:$K$15)+SUMPRODUCT(('Jug Recipes'!$L$4:$L$15=$A$6)*'Jug Recipes'!$M$4:$M$15)+SUMPRODUCT(('Jug Recipes'!$N$4:$N$15=$A$6)*'Jug Recipes'!$O$4:$O$15) | J6: 0
A7: Lemonade | B7: =SUMPRODUCT(('Dirty Soda - Built Drinks'!$D$3:$D$23=A7)*'Dirty Soda - Built Drinks'!$E$3:$E$23*'Dirty Soda - Built Drinks'!$B$3:$B$23) | C7: =B7*(1+Assumptions!$B$5) | D7: =CEILING(MAX(C7-H7,0)/(Assumptions!$B$7*Assumptions!$B$157),1) | E7: =CEILING(D7/Assumptions!$B$6,1) | F7: Mixed/priced separately — READY-TO-DRINK BOTTLES as of 14 Aug 2026 (was powder), sized in 96 oz bottles on Other Consumables row 19. NO CAN FORMAT: the 99 oz the Tuesday Smoke Test draws is already paid for there, so column G is forced to 0 rather than derived, or the jug would buy the lemonade twice. THE 28 CANS / 1 CASE THIS ROW COMPUTES IN COLUMNS D-E ARE A PHANTOM — there is no canned lemonade and no Purchase List row reads them, but they DO inflate the TOTAL on row 14. Do not hand row 14 to a buyer as the soda order. | G7: 0 | H7: =G7*Assumptions!$B$165 | I7: =SUMPRODUCT(('Jug Recipes'!$F$4:$F$15=$A$7)*'Jug Recipes'!$G$4:$G$15)+SUMPRODUCT(('Jug Recipes'!$H$4:$H$15=$A$7)*'Jug Recipes'!$I$4:$I$15)+SUMPRODUCT(('Jug Recipes'!$J$4:$J$15=$A$7)*'Jug Recipes'!$K$4:$K$15)+SUMPRODUCT(('Jug Recipes'!$L$4:$L$15=$A$7)*'Jug Recipes'!$M$4:$M$15)+SUMPRODUCT(('Jug Recipes'!$N$4:$N$15=$A$7)*'Jug Recipes'!$O$4:$O$15) | J7: 0
A8: Dr Pepper | B8: =SUMPRODUCT(('Dirty Soda - Built Drinks'!$D$3:$D$23=A8)*'Dirty Soda - Built Drinks'!$E$3:$E$23*'Dirty Soda - Built Drinks'!$B$3:$B$23) | C8: =B8*(1+Assumptions!$B$5) | D8: =CEILING(MAX(C8-H8,0)/(Assumptions!$B$7*Assumptions!$B$157),1) | E8: =CEILING(D8/Assumptions!$B$6,1) | G8: =CEILING(I8*(1+Assumptions!$B$5)/Assumptions!$B$165,1)+J8 | H8: =G8*Assumptions!$B$165 | I8: =SUMPRODUCT(('Jug Recipes'!$F$4:$F$15=$A$8)*'Jug Recipes'!$G$4:$G$15)+SUMPRODUCT(('Jug Recipes'!$H$4:$H$15=$A$8)*'Jug Recipes'!$I$4:$I$15)+SUMPRODUCT(('Jug Recipes'!$J$4:$J$15=$A$8)*'Jug Recipes'!$K$4:$K$15)+SUMPRODUCT(('Jug Recipes'!$L$4:$L$15=$A$8)*'Jug Recipes'!$M$4:$M$15)+SUMPRODUCT(('Jug Recipes'!$N$4:$N$15=$A$8)*'Jug Recipes'!$O$4:$O$15) | J8: 0
A9: Ginger ale | B9: =SUMPRODUCT(('Dirty Soda - Built Drinks'!$D$3:$D$23=A9)*'Dirty Soda - Built Drinks'!$E$3:$E$23*'Dirty Soda - Built Drinks'!$B$3:$B$23) | C9: =B9*(1+Assumptions!$B$5) | D9: =CEILING(MAX(C9-H9,0)/(Assumptions!$B$7*Assumptions!$B$157),1) | E9: =CEILING(D9/Assumptions!$B$6,1) | G9: =CEILING(I9*(1+Assumptions!$B$5)/Assumptions!$B$165,1)+J9 | H9: =G9*Assumptions!$B$165 | I9: =SUMPRODUCT(('Jug Recipes'!$F$4:$F$15=$A$9)*'Jug Recipes'!$G$4:$G$15)+SUMPRODUCT(('Jug Recipes'!$H$4:$H$15=$A$9)*'Jug Recipes'!$I$4:$I$15)+SUMPRODUCT(('Jug Recipes'!$J$4:$J$15=$A$9)*'Jug Recipes'!$K$4:$K$15)+SUMPRODUCT(('Jug Recipes'!$L$4:$L$15=$A$9)*'Jug Recipes'!$M$4:$M$15)+SUMPRODUCT(('Jug Recipes'!$N$4:$N$15=$A$9)*'Jug Recipes'!$O$4:$O$15) | J9: 0
A10: Squirt | B10: =SUMPRODUCT(('Dirty Soda - Built Drinks'!$D$3:$D$23=A10)*'Dirty Soda - Built Drinks'!$E$3:$E$23*'Dirty Soda - Built Drinks'!$B$3:$B$23) | C10: =B10*(1+Assumptions!$B$5) | D10: =CEILING(MAX(C10-H10,0)/(Assumptions!$B$7*Assumptions!$B$157),1) | E10: =CEILING(D10/Assumptions!$B$6,1) | G10: =CEILING(I10*(1+Assumptions!$B$5)/Assumptions!$B$165,1)+J10 | H10: =G10*Assumptions!$B$165 | I10: =SUMPRODUCT(('Jug Recipes'!$F$4:$F$15=$A$10)*'Jug Recipes'!$G$4:$G$15)+SUMPRODUCT(('Jug Recipes'!$H$4:$H$15=$A$10)*'Jug Recipes'!$I$4:$I$15)+SUMPRODUCT(('Jug Recipes'!$J$4:$J$15=$A$10)*'Jug Recipes'!$K$4:$K$15)+SUMPRODUCT(('Jug Recipes'!$L$4:$L$15=$A$10)*'Jug Recipes'!$M$4:$M$15)+SUMPRODUCT(('Jug Recipes'!$N$4:$N$15=$A$10)*'Jug Recipes'!$O$4:$O$15) | J10: 0
A11: Horchata mix | B11: =SUMPRODUCT(('Dirty Soda - Built Drinks'!$D$3:$D$23=A11)*'Dirty Soda - Built Drinks'!$E$3:$E$23*'Dirty Soda - Built Drinks'!$B$3:$B$23)+SUMPRODUCT(('Jug Recipes'!$F$4:$F$15="Horchata mix")*'Jug Recipes'!$G$4:$G$15)+SUMPRODUCT(('Jug Recipes'!$H$4:$H$15="Horchata mix")*'Jug Recipes'!$I$4:$I$15)+SUMPRODUCT(('Jug Recipes'!$J$4:$J$15="Horchata mix")*'Jug Recipes'!$K$4:$K$15)+SUMPRODUCT(('Jug Recipes'!$L$4:$L$15="Horchata mix")*'Jug Recipes'!$M$4:$M$15)+SUMPRODUCT(('Jug Recipes'!$N$4:$N$15="Horchata mix")*'Jug Recipes'!$O$4:$O$15) | C11: =B11*(1+Assumptions!$B$5) | D11: =CEILING(MAX(C11-H11,0)/(Assumptions!$B$7*Assumptions!$B$157),1) | E11: =CEILING(D11/Assumptions!$B$6,1) | F11: Mixed/priced separately — concentrate, sized as case-equiv on Purchase List row 46. NO BOTTLE FORMAT, same reason as lemonade on row 7: the 165 oz the Friday Whore-chata draws is already paid for, so column G is forced to 0 rather than derived. | G11: 0 | H11: =G11*Assumptions!$B$165 | I11: =SUMPRODUCT(('Jug Recipes'!$F$4:$F$15=$A$11)*'Jug Recipes'!$G$4:$G$15)+SUMPRODUCT(('Jug Recipes'!$H$4:$H$15=$A$11)*'Jug Recipes'!$I$4:$I$15)+SUMPRODUCT(('Jug Recipes'!$J$4:$J$15=$A$11)*'Jug Recipes'!$K$4:$K$15)+SUMPRODUCT(('Jug Recipes'!$L$4:$L$15=$A$11)*'Jug Recipes'!$M$4:$M$15)+SUMPRODUCT(('Jug Recipes'!$N$4:$N$15=$A$11)*'Jug Recipes'!$O$4:$O$15) | J11: 0
A12: Mountain Dew | B12: =SUMPRODUCT(('Dirty Soda - Built Drinks'!$D$3:$D$23=A12)*'Dirty Soda - Built Drinks'!$E$3:$E$23*'Dirty Soda - Built Drinks'!$B$3:$B$23)+SUMPRODUCT(('Jug Recipes'!$F$4:$F$15="Mountain Dew")*'Jug Recipes'!$G$4:$G$15)+SUMPRODUCT(('Jug Recipes'!$H$4:$H$15="Mountain Dew")*'Jug Recipes'!$I$4:$I$15)+SUMPRODUCT(('Jug Recipes'!$J$4:$J$15="Mountain Dew")*'Jug Recipes'!$K$4:$K$15)+SUMPRODUCT(('Jug Recipes'!$L$4:$L$15="Mountain Dew")*'Jug Recipes'!$M$4:$M$15)+SUMPRODUCT(('Jug Recipes'!$N$4:$N$15="Mountain Dew")*'Jug Recipes'!$O$4:$O$15)+SUMPRODUCT(('Dirty Soda - Built Drinks'!$F$3:$F$23="Mountain Dew")*'Dirty Soda - Built Drinks'!$G$3:$G$23*'Dirty Soda - Built Drinks'!$B$3:$B$23)+SUMPRODUCT(('Dirty Soda - Built Drinks'!$H$3:$H$23="Mountain Dew")*'Dirty Soda - Built Drinks'!$I$3:$I$23*'Dirty Soda - Built Drinks'!$B$3:$B$23) | C12: =B12*(1+Assumptions!$B$5) | D12: =CEILING(MAX(C12-H12,0)/(Assumptions!$B$7*Assumptions!$B$157),1) | E12: =CEILING(D12/Assumptions!$B$6,1) | F12: READS ZERO — SCOBY-Dew was retired 11 Aug 2026 and was the only draw on this line. Kept live because it is derived from the recipe. The camper Mountain Dew (Assumptions B258, Purchase List row 45) is a separate pool and is deliberately NOT counted here: it is camp stock, not a build ingredient. | G12: =CEILING(I12*(1+Assumptions!$B$5)/Assumptions!$B$165,1)+J12 | H12: =G12*Assumptions!$B$165 | I12: =SUMPRODUCT(('Jug Recipes'!$F$4:$F$15=$A$12)*'Jug Recipes'!$G$4:$G$15)+SUMPRODUCT(('Jug Recipes'!$H$4:$H$15=$A$12)*'Jug Recipes'!$I$4:$I$15)+SUMPRODUCT(('Jug Recipes'!$J$4:$J$15=$A$12)*'Jug Recipes'!$K$4:$K$15)+SUMPRODUCT(('Jug Recipes'!$L$4:$L$15=$A$12)*'Jug Recipes'!$M$4:$M$15)+SUMPRODUCT(('Jug Recipes'!$N$4:$N$15=$A$12)*'Jug Recipes'!$O$4:$O$15) | J12: 0
A13: Root beer | B13: =SUMPRODUCT(('Dirty Soda - Built Drinks'!$D$3:$D$23=A13)*'Dirty Soda - Built Drinks'!$E$3:$E$23*'Dirty Soda - Built Drinks'!$B$3:$B$23) | C13: =B13*(1+Assumptions!$B$5) | D13: =CEILING(MAX(C13-H13,0)/(Assumptions!$B$7*Assumptions!$B$157),1) | E13: =CEILING(D13/Assumptions!$B$6,1) | F13: A&W 36-pack is $15.99 at Costco — $0.44/can, the cheapest base on the board and effectively identical to the 35-pack price already assumed. | G13: =CEILING(I13*(1+Assumptions!$B$5)/Assumptions!$B$165,1)+J13 | H13: =G13*Assumptions!$B$165 | I13: =SUMPRODUCT(('Jug Recipes'!$F$4:$F$15=$A$13)*'Jug Recipes'!$G$4:$G$15)+SUMPRODUCT(('Jug Recipes'!$H$4:$H$15=$A$13)*'Jug Recipes'!$I$4:$I$15)+SUMPRODUCT(('Jug Recipes'!$J$4:$J$15=$A$13)*'Jug Recipes'!$K$4:$K$15)+SUMPRODUCT(('Jug Recipes'!$L$4:$L$15=$A$13)*'Jug Recipes'!$M$4:$M$15)+SUMPRODUCT(('Jug Recipes'!$N$4:$N$15=$A$13)*'Jug Recipes'!$O$4:$O$15) | J13: 0
A14: TOTAL | B14: =SUM(B4:B13) | C14: =SUM(C4:C13) | D14: =SUM(D4:D13) | E14: =SUM(E4:E13) | F14: THREE FORMATS, ON PURPOSE. CANS for the built-to-order dirty sodas — a 3-4 oz pour off a 12 oz can carries the waste factor on Assumptions B157. 2 L for anything a JUG batch drinks, because a jug is poured out in one go and wastes nothing; column G derives that straight from the jug recipes (column I is the jug draw it reads), and column J is the manual override for 2 L that no jug asks for. 1 L for the bar-service mixers — soda water and tonic — which are on the Other Consumables and Bar Add-Ons tabs, not here. Bottles are subtracted from the can requirement automatically. CASES = cans / 35. | G14: =SUM(G4:G13) | H14: =SUM(H4:H13) | I14: =SUM(I4:I13) | J14: =SUM(J4:J13)

Sheet Other Consumables
A1: Other Consumables — syrups, cream, dairy, garnish
A3: SYRUPS
A4: Syrup | B4: Total oz | C4: +buffer | D4: Bottles | E4: Note
A5: Peach | B5: =SUMPRODUCT(('Dirty Soda - Built Drinks'!$F$3:$F$23=A5)*'Dirty Soda - Built Drinks'!$G$3:$G$23*'Dirty Soda - Built Drinks'!$B$3:$B$23)+SUMPRODUCT(('Dirty Soda - Built Drinks'!$H$3:$H$23=A5)*'Dirty Soda - Built Drinks'!$I$3:$I$23*'Dirty Soda - Built Drinks'!$B$3:$B$23)+SUMPRODUCT(('Jug Recipes'!$F$4:$F$15="Peach syrup")*'Jug Recipes'!$G$4:$G$15)+SUMPRODUCT(('Jug Recipes'!$H$4:$H$15="Peach syrup")*'Jug Recipes'!$I$4:$I$15)+SUMPRODUCT(('Jug Recipes'!$J$4:$J$15="Peach syrup")*'Jug Recipes'!$K$4:$K$15)+SUMPRODUCT(('Jug Recipes'!$L$4:$L$15="Peach syrup")*'Jug Recipes'!$M$4:$M$15)+SUMPRODUCT(('Jug Recipes'!$N$4:$N$15="Peach syrup")*'Jug Recipes'!$O$4:$O$15) | C5: =B5*(1+Assumptions!$B$5) | D5: =CEILING(C5/Assumptions!$B$8,1) | E5: Torani 750ml
A6: Pineapple | B6: =SUMPRODUCT(('Dirty Soda - Built Drinks'!$F$3:$F$23=A6)*'Dirty Soda - Built Drinks'!$G$3:$G$23*'Dirty Soda - Built Drinks'!$B$3:$B$23)+SUMPRODUCT(('Dirty Soda - Built Drinks'!$H$3:$H$23=A6)*'Dirty Soda - Built Drinks'!$I$3:$I$23*'Dirty Soda - Built Drinks'!$B$3:$B$23)+SUMPRODUCT(('Jug Recipes'!$F$4:$F$15="Pineapple syrup")*'Jug Recipes'!$G$4:$G$15)+SUMPRODUCT(('Jug Recipes'!$H$4:$H$15="Pineapple syrup")*'Jug Recipes'!$I$4:$I$15)+SUMPRODUCT(('Jug Recipes'!$J$4:$J$15="Pineapple syrup")*'Jug Recipes'!$K$4:$K$15)+SUMPRODUCT(('Jug Recipes'!$L$4:$L$15="Pineapple syrup")*'Jug Recipes'!$M$4:$M$15)+SUMPRODUCT(('Jug Recipes'!$N$4:$N$15="Pineapple syrup")*'Jug Recipes'!$O$4:$O$15) | C6: =B6*(1+Assumptions!$B$5) | D6: =CEILING(C6/Assumptions!$B$8,1) | E6: Torani 750ml
A7: Vanilla | B7: =SUMPRODUCT(('Dirty Soda - Built Drinks'!$F$3:$F$23=A7)*'Dirty Soda - Built Drinks'!$G$3:$G$23*'Dirty Soda - Built Drinks'!$B$3:$B$23)+SUMPRODUCT(('Dirty Soda - Built Drinks'!$H$3:$H$23=A7)*'Dirty Soda - Built Drinks'!$I$3:$I$23*'Dirty Soda - Built Drinks'!$B$3:$B$23)+SUMPRODUCT(('Jug Recipes'!$F$4:$F$15="Vanilla syrup")*'Jug Recipes'!$G$4:$G$15)+SUMPRODUCT(('Jug Recipes'!$H$4:$H$15="Vanilla syrup")*'Jug Recipes'!$I$4:$I$15)+SUMPRODUCT(('Jug Recipes'!$J$4:$J$15="Vanilla syrup")*'Jug Recipes'!$K$4:$K$15)+SUMPRODUCT(('Jug Recipes'!$L$4:$L$15="Vanilla syrup")*'Jug Recipes'!$M$4:$M$15)+SUMPRODUCT(('Jug Recipes'!$N$4:$N$15="Vanilla syrup")*'Jug Recipes'!$O$4:$O$15) | C7: =B7*(1+Assumptions!$B$5) | D7: =CEILING(C7/Assumptions!$B$8,1) | E7: Torani 750ml
A8: Cherry | B8: =SUMPRODUCT(('Dirty Soda - Built Drinks'!$F$3:$F$23=A8)*'Dirty Soda - Built Drinks'!$G$3:$G$23*'Dirty Soda - Built Drinks'!$B$3:$B$23)+SUMPRODUCT(('Dirty Soda - Built Drinks'!$H$3:$H$23=A8)*'Dirty Soda - Built Drinks'!$I$3:$I$23*'Dirty Soda - Built Drinks'!$B$3:$B$23)+SUMPRODUCT(('Jug Recipes'!$F$4:$F$15="Cherry syrup")*'Jug Recipes'!$G$4:$G$15)+SUMPRODUCT(('Jug Recipes'!$H$4:$H$15="Cherry syrup")*'Jug Recipes'!$I$4:$I$15)+SUMPRODUCT(('Jug Recipes'!$J$4:$J$15="Cherry syrup")*'Jug Recipes'!$K$4:$K$15)+SUMPRODUCT(('Jug Recipes'!$L$4:$L$15="Cherry syrup")*'Jug Recipes'!$M$4:$M$15)+SUMPRODUCT(('Jug Recipes'!$N$4:$N$15="Cherry syrup")*'Jug Recipes'!$O$4:$O$15) | C8: =B8*(1+Assumptions!$B$5) | D8: =CEILING(C8/Assumptions!$B$8,1) | E8: Torani 750ml
A9: Watermelon | B9: =SUMPRODUCT(('Dirty Soda - Built Drinks'!$F$3:$F$23=A9)*'Dirty Soda - Built Drinks'!$G$3:$G$23*'Dirty Soda - Built Drinks'!$B$3:$B$23)+SUMPRODUCT(('Dirty Soda - Built Drinks'!$H$3:$H$23=A9)*'Dirty Soda - Built Drinks'!$I$3:$I$23*'Dirty Soda - Built Drinks'!$B$3:$B$23)+SUMPRODUCT(('Jug Recipes'!$F$4:$F$15="Watermelon syrup")*'Jug Recipes'!$G$4:$G$15)+SUMPRODUCT(('Jug Recipes'!$H$4:$H$15="Watermelon syrup")*'Jug Recipes'!$I$4:$I$15)+SUMPRODUCT(('Jug Recipes'!$J$4:$J$15="Watermelon syrup")*'Jug Recipes'!$K$4:$K$15)+SUMPRODUCT(('Jug Recipes'!$L$4:$L$15="Watermelon syrup")*'Jug Recipes'!$M$4:$M$15)+SUMPRODUCT(('Jug Recipes'!$N$4:$N$15="Watermelon syrup")*'Jug Recipes'!$O$4:$O$15) | C9: =B9*(1+Assumptions!$B$5) | D9: =CEILING(C9/Assumptions!$B$8,1) | E9: Torani 750ml — READS ZERO NOW, and that is correct. The Watermelon Sugar High moved to real watermelon juice (row 51) and was the only thing drawing on this syrup. The row is kept live because watermelon is one of the seven Torani flavours already in stock for Italian sodas — putting it back into a build costs nothing but a number in a recipe.
A10: Melon | B10: =SUMPRODUCT(('Dirty Soda - Built Drinks'!$F$3:$F$23=A10)*'Dirty Soda - Built Drinks'!$G$3:$G$23*'Dirty Soda - Built Drinks'!$B$3:$B$23)+SUMPRODUCT(('Dirty Soda - Built Drinks'!$H$3:$H$23=A10)*'Dirty Soda - Built Drinks'!$I$3:$I$23*'Dirty Soda - Built Drinks'!$B$3:$B$23) | C10: =B10*(1+Assumptions!$B$5) | D10: =CEILING(C10/Assumptions!$B$8,1) | E10: SWAPPED OFF TORANI 18 Aug 2026 — bought separately as Marjan Boudan Melon Syrup, 21.3 oz (confirmed on Amazon), not pooled into the Torani 750 ml bottle count any more. See Purchase List row 97 and Assumptions B265/B266. Catboy Snot's only syrup.
A11: Lemon | B11: =SUMPRODUCT(('Dirty Soda - Built Drinks'!$F$3:$F$23=A11)*'Dirty Soda - Built Drinks'!$G$3:$G$23*'Dirty Soda - Built Drinks'!$B$3:$B$23)+SUMPRODUCT(('Dirty Soda - Built Drinks'!$H$3:$H$23=A11)*'Dirty Soda - Built Drinks'!$I$3:$I$23*'Dirty Soda - Built Drinks'!$B$3:$B$23)+SUMPRODUCT(('Jug Recipes'!$F$4:$F$15="Lemon syrup")*'Jug Recipes'!$G$4:$G$15)+SUMPRODUCT(('Jug Recipes'!$H$4:$H$15="Lemon syrup")*'Jug Recipes'!$I$4:$I$15)+SUMPRODUCT(('Jug Recipes'!$J$4:$J$15="Lemon syrup")*'Jug Recipes'!$K$4:$K$15)+SUMPRODUCT(('Jug Recipes'!$L$4:$L$15="Lemon syrup")*'Jug Recipes'!$M$4:$M$15)+SUMPRODUCT(('Jug Recipes'!$N$4:$N$15="Lemon syrup")*'Jug Recipes'!$O$4:$O$15) | C11: =B11*(1+Assumptions!$B$5) | D11: =CEILING(C11/Assumptions!$B$8,1) | E11: Torani 750ml
A12: TOTAL | B12: =SUM(B5:B9,B11)+Assumptions!$B$160*Assumptions!$B$162 | C12: =SUM(C5:C9,C11)+Assumptions!$B$160*Assumptions!$B$162*(1+Assumptions!$B$5) | D12: =SUM(D5:D9,D11)+CEILING(Assumptions!$B$160*Assumptions!$B$162*(1+Assumptions!$B$5)/Assumptions!$B$8,1) | E12: TOTAL incl. Italian soda syrup draw (Assumptions B160 x B162). MELON EXCLUDED 18 Aug 2026 — bought separately as Boudan Melon Syrup (Purchase List row 97), not pooled Torani.
A14: CREAM, DAIRY & NON-CANNED BASES
A15: Item | B15: Total oz | C15: +buffer | D15: Units | E15: Unit/note
A16: Cream of coconut | B16: =SUMPRODUCT('Dirty Soda - Built Drinks'!$K$3:$K$23*'Dirty Soda - Built Drinks'!$B$3:$B$23)+SUMPRODUCT(('Jug Recipes'!$F$4:$F$15="Coconut cream")*'Jug Recipes'!$G$4:$G$15)+SUMPRODUCT(('Jug Recipes'!$H$4:$H$15="Coconut cream")*'Jug Recipes'!$I$4:$I$15)+SUMPRODUCT(('Jug Recipes'!$J$4:$J$15="Coconut cream")*'Jug Recipes'!$K$4:$K$15)+SUMPRODUCT(('Jug Recipes'!$L$4:$L$15="Coconut cream")*'Jug Recipes'!$M$4:$M$15)+SUMPRODUCT(('Jug Recipes'!$N$4:$N$15="Coconut cream")*'Jug Recipes'!$O$4:$O$15) | C16: =B16*(1+Assumptions!$B$5) | D16: =CEILING(C16/Assumptions!$B$9,1) | E16: 22oz squeeze bottles (Amazon)
A17: Passion fruit purée | B17: =SUMPRODUCT(('Dirty Soda - Built Drinks'!$F$3:$F$23=A17)*'Dirty Soda - Built Drinks'!$G$3:$G$23*'Dirty Soda - Built Drinks'!$B$3:$B$23)+SUMPRODUCT(('Dirty Soda - Built Drinks'!$H$3:$H$23=A17)*'Dirty Soda - Built Drinks'!$I$3:$I$23*'Dirty Soda - Built Drinks'!$B$3:$B$23)+SUMPRODUCT(('Jug Recipes'!$F$4:$F$15="Passion fruit purée")*'Jug Recipes'!$G$4:$G$15)+SUMPRODUCT(('Jug Recipes'!$H$4:$H$15="Passion fruit purée")*'Jug Recipes'!$I$4:$I$15)+SUMPRODUCT(('Jug Recipes'!$J$4:$J$15="Passion fruit purée")*'Jug Recipes'!$K$4:$K$15)+SUMPRODUCT(('Jug Recipes'!$L$4:$L$15="Passion fruit purée")*'Jug Recipes'!$M$4:$M$15)+SUMPRODUCT(('Jug Recipes'!$N$4:$N$15="Passion fruit purée")*'Jug Recipes'!$O$4:$O$15)+'Dirty Soda - Built Drinks'!$B$13*Assumptions!$B$118 | C17: =B17*(1+Assumptions!$B$5) | D17: =CEILING(C17/Assumptions!$B$91,1) | E17: 22oz squeeze bottles (Amazon)
A18: Pineapple purée | B18: =SUMPRODUCT(('Dirty Soda - Built Drinks'!$F$3:$F$23=A18)*'Dirty Soda - Built Drinks'!$G$3:$G$23*'Dirty Soda - Built Drinks'!$B$3:$B$23)+SUMPRODUCT(('Dirty Soda - Built Drinks'!$H$3:$H$23=A18)*'Dirty Soda - Built Drinks'!$I$3:$I$23*'Dirty Soda - Built Drinks'!$B$3:$B$23)+SUMPRODUCT(('Jug Recipes'!$F$4:$F$15="Pineapple purée")*'Jug Recipes'!$G$4:$G$15)+SUMPRODUCT(('Jug Recipes'!$H$4:$H$15="Pineapple purée")*'Jug Recipes'!$I$4:$I$15)+SUMPRODUCT(('Jug Recipes'!$J$4:$J$15="Pineapple purée")*'Jug Recipes'!$K$4:$K$15)+SUMPRODUCT(('Jug Recipes'!$L$4:$L$15="Pineapple purée")*'Jug Recipes'!$M$4:$M$15)+SUMPRODUCT(('Jug Recipes'!$N$4:$N$15="Pineapple purée")*'Jug Recipes'!$O$4:$O$15) | C18: =B18*(1+Assumptions!$B$5) | D18: =CEILING(C18/Assumptions!$B$91,1) | E18: 22oz squeeze bottles (Amazon)
A19: Lemonade (base) | B19: =SUMPRODUCT(('Dirty Soda - Built Drinks'!$D$3:$D$23="Lemonade")*'Dirty Soda - Built Drinks'!$E$3:$E$23*'Dirty Soda - Built Drinks'!$B$3:$B$23)+SUMPRODUCT(('Jug Recipes'!$F$4:$F$15="Lemonade")*'Jug Recipes'!$G$4:$G$15)+SUMPRODUCT(('Jug Recipes'!$H$4:$H$15="Lemonade")*'Jug Recipes'!$I$4:$I$15)+SUMPRODUCT(('Jug Recipes'!$J$4:$J$15="Lemonade")*'Jug Recipes'!$K$4:$K$15)+SUMPRODUCT(('Jug Recipes'!$L$4:$L$15="Lemonade")*'Jug Recipes'!$M$4:$M$15)+SUMPRODUCT(('Jug Recipes'!$N$4:$N$15="Lemonade")*'Jug Recipes'!$O$4:$O$15)+SUMPRODUCT(('Dirty Soda - Built Drinks'!$F$3:$F$23="Lemonade")*'Dirty Soda - Built Drinks'!$G$3:$G$23*'Dirty Soda - Built Drinks'!$B$3:$B$23)+SUMPRODUCT(('Dirty Soda - Built Drinks'!$H$3:$H$23="Lemonade")*'Dirty Soda - Built Drinks'!$I$3:$I$23*'Dirty Soda - Built Drinks'!$B$3:$B$23)+Assumptions!$B$300 | C19: =B19*(1+Assumptions!$B$5) | D19: =CEILING(C19/96,1) | E19: 96 oz bottles — Kirkland Organic, bought as 2-count packs (4 bottles = 2 packs)
A20: Soda water | B20: =SUMPRODUCT('Dirty Soda - Built Drinks'!$J$3:$J$23*'Dirty Soda - Built Drinks'!$B$3:$B$23)+SUMPRODUCT(('Jug Recipes'!$F$4:$F$15="Soda water")*'Jug Recipes'!$G$4:$G$15)+SUMPRODUCT(('Jug Recipes'!$H$4:$H$15="Soda water")*'Jug Recipes'!$I$4:$I$15)+SUMPRODUCT(('Jug Recipes'!$J$4:$J$15="Soda water")*'Jug Recipes'!$K$4:$K$15)+SUMPRODUCT(('Jug Recipes'!$L$4:$L$15="Soda water")*'Jug Recipes'!$M$4:$M$15)+SUMPRODUCT(('Jug Recipes'!$N$4:$N$15="Soda water")*'Jug Recipes'!$O$4:$O$15)+Assumptions!$B$160*Assumptions!$B$161 | C20: =B20*(1+Assumptions!$B$5) | D20: =CEILING(C20/(Assumptions!$B$235*Assumptions!$B$238),1) | E20: 1 L bottles — incl. Italian sodas. MOVED OFF CANS 8 Aug 2026. Soda water is the one line where cans were worst: the draw is 120 Italian sodas at 8 oz plus a lot of 0.5-2 oz splashes, so a 12 oz can was either two-thirds wasted or poured flat, which is why it carried the same 0.7 waste factor as the base sodas. A recapped 1 L bottle holds pressure (Assumptions B238, 0.9) and pours four Italian sodas. Fewer units, less volume to haul and cheaper. The 33 oz the Sunday Cherry Bomb jug takes is one bottle almost exactly.
A21: Tangerine juice | B21: =SUMPRODUCT(('Dirty Soda - Built Drinks'!$F$3:$F$23="Tangerine juice")*'Dirty Soda - Built Drinks'!$G$3:$G$23*'Dirty Soda - Built Drinks'!$B$3:$B$23)+SUMPRODUCT(('Dirty Soda - Built Drinks'!$H$3:$H$23="Tangerine juice")*'Dirty Soda - Built Drinks'!$I$3:$I$23*'Dirty Soda - Built Drinks'!$B$3:$B$23) | C21: =B21*(1+Assumptions!$B$5) | D21: =CEILING(C21/Assumptions!$B$89,1) | E21: 52oz bottles
A22: Garnish/misc: fresh mint & basil, limes, cinnamon (horchata), ice, cups, straws. Pickle brine is no longer in this catch-all — it is itemized on row 50. Keg add-ons priced on Beverage Lines tab.
A24: LIQUOR (OPTIONAL ADD-ON)
A25: Liquor | B25: Total oz | C25: +buffer | D25: Bottles | E25: $/bottle | F25: Subtotal | G25: Note
A26: Vodka | B26: =SUMPRODUCT(('Dirty Soda - Built Drinks'!$M$3:$M$23=A26)*'Dirty Soda - Built Drinks'!$N$3:$N$23)+SUMPRODUCT(('Jug Recipes'!$P$4:$P$15=A26)*'Jug Recipes'!$R$4:$R$15) | C26: =B26*(1+Assumptions!$B$5) | D26: =CEILING(C26/Assumptions!$B$41,1) | E26: =Assumptions!$B$42 | F26: =D26*E26 | G26: Consider peach/vanilla flavored vodka for Peaches & Creamed / Orange Cream-sicle.
A27: Coconut Rum | B27: =SUMPRODUCT(('Dirty Soda - Built Drinks'!$M$3:$M$23=A27)*'Dirty Soda - Built Drinks'!$N$3:$N$23)+SUMPRODUCT(('Jug Recipes'!$P$4:$P$15=A27)*'Jug Recipes'!$R$4:$R$15) | C27: =B27*(1+Assumptions!$B$5) | D27: =CEILING(C27/Assumptions!$B$41,1) | E27: =Assumptions!$B$43 | F27: =D27*E27
A28: Bourbon | B28: =SUMPRODUCT(('Dirty Soda - Built Drinks'!$M$3:$M$23=A28)*'Dirty Soda - Built Drinks'!$N$3:$N$23)+SUMPRODUCT(('Jug Recipes'!$P$4:$P$15=A28)*'Jug Recipes'!$R$4:$R$15) | C28: =B28*(1+Assumptions!$B$5) | D28: =CEILING(C28/Assumptions!$B$41,1) | E28: =Assumptions!$B$44 | F28: =D28*E28
A29: Blanco Tequila | B29: =SUMPRODUCT(('Dirty Soda - Built Drinks'!$M$3:$M$23=A29)*'Dirty Soda - Built Drinks'!$N$3:$N$23)+SUMPRODUCT(('Jug Recipes'!$P$4:$P$15=A29)*'Jug Recipes'!$R$4:$R$15) | C29: =B29*(1+Assumptions!$B$5) | D29: =CEILING(C29/Assumptions!$B$41,1) | E29: =Assumptions!$B$45 | F29: =D29*E29
A30: Spiced Rum | B30: =SUMPRODUCT(('Dirty Soda - Built Drinks'!$M$3:$M$23=A30)*'Dirty Soda - Built Drinks'!$N$3:$N$23)+SUMPRODUCT(('Jug Recipes'!$P$4:$P$15=A30)*'Jug Recipes'!$R$4:$R$15) | C30: =B30*(1+Assumptions!$B$5) | D30: =CEILING(C30/Assumptions!$B$41,1) | E30: =Assumptions!$B$46 | F30: =D30*E30
A31: Whiskey | B31: =SUMPRODUCT(('Dirty Soda - Built Drinks'!$M$3:$M$23=A31)*'Dirty Soda - Built Drinks'!$N$3:$N$23)+SUMPRODUCT(('Jug Recipes'!$P$4:$P$15=A31)*'Jug Recipes'!$R$4:$R$15) | C31: =B31*(1+Assumptions!$B$5) | D31: =CEILING(C31/Assumptions!$B$41,1) | E31: =Assumptions!$B$47 | F31: =D31*E31 | G31: Consider 1 pickle whiskey (e.g. Ole Smoky) for A Ginger's Pickle as a novelty side option.
A32: TOTAL | B32: =SUM(B26:B31) | C32: =SUM(C26:C31) | D32: =SUM(D26:D31) | F32: =SUM(F26:F31)
A34: BUILT-DRINK & FRESH-PRODUCE EXTRAS (itemized)
A35: Item | B35: Total oz | C35: +buffer | D35: Units | E35: Unit/note
A36: Ginger beer | B36: =(SUMPRODUCT(('Dirty Soda - Built Drinks'!$F$3:$F$23="Ginger beer")*'Dirty Soda - Built Drinks'!$G$3:$G$23*'Dirty Soda - Built Drinks'!$B$3:$B$23)+SUMPRODUCT(('Dirty Soda - Built Drinks'!$H$3:$H$23="Ginger beer")*'Dirty Soda - Built Drinks'!$I$3:$I$23*'Dirty Soda - Built Drinks'!$B$3:$B$23)) | C36: =B36*(1+Assumptions!$B$5) | D36: =CEILING(C36/Assumptions!$B$96,1) | E36: 12oz cans
A37: Lemon juice (fresh) — RETIRED, no build uses it | B37: =(SUMPRODUCT(('Dirty Soda - Built Drinks'!$F$3:$F$23="Lemon juice (fresh)")*'Dirty Soda - Built Drinks'!$G$3:$G$23*'Dirty Soda - Built Drinks'!$B$3:$B$23)+SUMPRODUCT(('Dirty Soda - Built Drinks'!$H$3:$H$23="Lemon juice (fresh)")*'Dirty Soda - Built Drinks'!$I$3:$I$23*'Dirty Soda - Built Drinks'!$B$3:$B$23)+SUMPRODUCT(('Jug Recipes'!$F$4:$F$15="Lemon juice (fresh)")*'Jug Recipes'!$G$4:$G$15)+SUMPRODUCT(('Jug Recipes'!$H$4:$H$15="Lemon juice (fresh)")*'Jug Recipes'!$I$4:$I$15)+SUMPRODUCT(('Jug Recipes'!$J$4:$J$15="Lemon juice (fresh)")*'Jug Recipes'!$K$4:$K$15)+SUMPRODUCT(('Jug Recipes'!$L$4:$L$15="Lemon juice (fresh)")*'Jug Recipes'!$M$4:$M$15)+SUMPRODUCT(('Jug Recipes'!$N$4:$N$15="Lemon juice (fresh)")*'Jug Recipes'!$O$4:$O$15)) | C37: =B37*(1+Assumptions!$B$5) | D37: =CEILING(C37/Assumptions!$B$99,1) | E37: whole lemons — READS ZERO NOW, AND THAT IS CORRECT. Both consumers left: Clear Cache and then the SCOBY Mule moved onto bottled yuzu (row 56) on 10 Aug 2026, and the two peach-tea jugs went to bottled lemon juice on 8 Aug (Jug Recipes row 32). THERE IS NO FRESH LEMON ON THE BAR AT ALL — no build, no garnish, no wedge. The row is kept live rather than deleted because it is derived: put 'Lemon juice (fresh)' back into a Syrup A/B slot on the recipe tab and the count and the shopping line come back on their own.
A38: Simple syrup (sugar) — RETIRED, agave now (row 46) | B38: ='Dirty Soda - Built Drinks'!$B$11*Assumptions!$B$98 | C38: =B38*(1+Assumptions!$B$5) | D38: =CEILING(C38/Assumptions!$B$56,1) | E38: Computes 0 while Assumptions B98 is zeroed
A39: Clamato — RETIRED 18 Aug 2026, replaced by Tres Agaves Bloody Mary Mix (row 58) | B39: =(SUMPRODUCT(('Dirty Soda - Built Drinks'!$F$3:$F$23="Clamato")*'Dirty Soda - Built Drinks'!$G$3:$G$23*'Dirty Soda - Built Drinks'!$B$3:$B$23)+SUMPRODUCT(('Dirty Soda - Built Drinks'!$H$3:$H$23="Clamato")*'Dirty Soda - Built Drinks'!$I$3:$I$23*'Dirty Soda - Built Drinks'!$B$3:$B$23)) | C39: =B39*(1+Assumptions!$B$5) | D39: =CEILING(C39/Assumptions!$B$103,1) | E39: 64oz bottles
A40: Lime juice (fresh) | B40: ='Dirty Soda - Built Drinks'!$B$4*'Dirty Soda - Built Drinks'!$I$4+'Dirty Soda - Built Drinks'!$B$3*Assumptions!$B$113+'Dirty Soda - Built Drinks'!$B$20*'Dirty Soda - Built Drinks'!$I$20 | C40: =B40*(1+Assumptions!$B$5) | D40: =CEILING(C40/Assumptions!$B$111,1) | E40: whole limes (~1oz juice each) — Michelada + Tang Dynasty
A41: Hot sauce — RETIRED 18 Aug 2026, was Michelada-only | B41: ='Dirty Soda - Built Drinks'!$B$4*Assumptions!$B$105 | C41: =B41*(1+Assumptions!$B$5) | D41: =CEILING(C41/Assumptions!$B$106,1) | E41: 12oz bottles
A42: Tajin (rim salt) | B42: =('Dirty Soda - Built Drinks'!$B$4+'Dirty Soda - Built Drinks'!$B$8+'Dirty Soda - Built Drinks'!$B$16+'Dirty Soda - Built Drinks'!$B$17)*Assumptions!$B$108 | C42: =B42*(1+Assumptions!$B$5) | D42: =CEILING(C42/Assumptions!$B$109,1) | E42: 5oz shakers — Michelada, A Ginger's Pickle and Catboy Piss rims
A43: Orange juice (Catboy Café build) — RETIRED 21 Aug 2026, Sakura Kisses swapped to orange syrup | B43: =(SUMPRODUCT(('Dirty Soda - Built Drinks'!$F$3:$F$23="Orange juice")*'Dirty Soda - Built Drinks'!$G$3:$G$23*'Dirty Soda - Built Drinks'!$B$3:$B$23)+SUMPRODUCT(('Dirty Soda - Built Drinks'!$H$3:$H$23="Orange juice")*'Dirty Soda - Built Drinks'!$I$3:$I$23*'Dirty Soda - Built Drinks'!$B$3:$B$23)) | C43: =B43*(1+Assumptions!$B$5) | D43: =CEILING(C43/Assumptions!$B$69,1) | E43: 64oz cartons — separate from the Thursday jug's OJ so the cost lands on the right line
A44: Cucumber — garnish / cubes only (NOT in any build) | B44: 0 | C44: 0 | D44: =Assumptions!$B$215 | E44: whole cucumbers — MANUAL, from Assumptions B215. Cucumber left the recipe when Thirst Trap became Fuzz Test. This row used to multiply servings by the Syrup A column, which is now peach syrup, so it would have quietly kept buying cucumbers off the wrong measure.
A45: Lime juice (fresh) — Fuzz Test + Catboy Snot + Catboy Piss + Shirley variants | B45: ='Dirty Soda - Built Drinks'!$B$12*'Dirty Soda - Built Drinks'!$I$12+'Dirty Soda - Built Drinks'!$B$15*'Dirty Soda - Built Drinks'!$I$15+'Dirty Soda - Built Drinks'!$B$16*'Dirty Soda - Built Drinks'!$I$16+'Dirty Soda - Built Drinks'!$B$17*'Dirty Soda - Built Drinks'!$I$17+'Dirty Soda - Built Drinks'!$B$18*Assumptions!$B$154+'Dirty Soda - Built Drinks'!$B$21*'Dirty Soda - Built Drinks'!$G$21+'Dirty Soda - Built Drinks'!$B$22*'Dirty Soda - Built Drinks'!$I$22 | C45: =B45*(1+Assumptions!$B$5) | D45: =CEILING(C45/Assumptions!$B$111,1) | E45: whole limes (~1oz juice each) — canned-base drinks, plus Rawhide (0.5 oz) and Localhost (1 oz). Fresh, not bottled: these two are lime-forward and ReaLime tastes like it. LOCALHOST'S LIME IS OPTIONAL as of 11 Aug 2026 — the margarita mixer already carries lime, so it is added to taste. It is still sized here at the full 1 oz deliberately: limes go into eight other drinks, so anything Localhost does not use gets squeezed elsewhere.
A46: Apple cider vinegar (SCOBY Mule) | B46: ='Dirty Soda - Built Drinks'!$B$11*Assumptions!$B$128 | C46: =B46*(1+Assumptions!$B$5) | D46: =CEILING(C46/Assumptions!$B$129,1) | E46: 32oz bottles
A47: Agave syrup (SCOBY Mule + Localhost) | B47: ='Dirty Soda - Built Drinks'!$B$11*Assumptions!$B$131+'Dirty Soda - Built Drinks'!$B$22*Assumptions!$B$224 | C47: =B47*(1+Assumptions!$B$5) | D47: =CEILING(C47/Assumptions!$B$132,1) | E47: 23.5oz bottles — SCOBY Mule at 0.25 oz (Assumptions B131) and Localhost at 0.5 oz (B224). LOCALHOST'S AGAVE IS OPTIONAL as of 11 Aug 2026 — the margarita mixer is already sweetened with agave, so it is added to taste. Still sized at the full rate here; the surplus is small and agave keeps indefinitely.
A48: Aloe vera juice (Catboy Snot) | B48: ='Dirty Soda - Built Drinks'!$B$15*Assumptions!$B$147 | C48: =B48*(1+Assumptions!$B$5) | D48: =CEILING(C48/Assumptions!$B$148,1) | E48: 1.5 L (50.7oz) bottles — DRINKING aloe with pulp, not supplement/whole-leaf
A49: Basil seeds (Catboy Snot) — OPTIONAL | B49: ='Dirty Soda - Built Drinks'!$B$15*Assumptions!$B$150 | C49: =B49*(1+Assumptions!$B$5) | D49: =CEILING(C49/Assumptions!$B$151,1) | E49: 100g (3.5oz) bags — OPTIONAL texture garnish; drink works without them
A50: Pickle brine (A Ginger's Pickle + brine shots) | B50: =SUMPRODUCT(('Dirty Soda - Built Drinks'!$F$3:$F$23="Pickle Juice")*'Dirty Soda - Built Drinks'!$G$3:$G$23*'Dirty Soda - Built Drinks'!$B$3:$B$23)+SUMPRODUCT(('Dirty Soda - Built Drinks'!$H$3:$H$23="Pickle Juice")*'Dirty Soda - Built Drinks'!$I$3:$I$23*'Dirty Soda - Built Drinks'!$B$3:$B$23)+Assumptions!$B$209*Assumptions!$B$210 | C50: =B50*(1+Assumptions!$B$5) | D50: =CEILING(C50/Assumptions!$B$211,1) | E50: 32oz jars — sized on DRAINABLE BRINE (Assumptions B211), not jar volume. Covers the pickle juice in every A Ginger's Pickle AND the brine shots on the menu board, which come out of the same jars. DERIVED FROM THE RECIPE as of 10 Aug 2026: the build oz is read straight off 'Dirty Soda - Built Drinks' row 8 (Syrup A = "Pickle Juice"), which went from 0.5 to 1 oz a serving that day. Assumptions B208 is superseded and read by nothing. Change the recipe and this follows.
A51: Watermelon juice (Watermelon Sugar High) | B51: =SUMPRODUCT(('Dirty Soda - Built Drinks'!$F$3:$F$23="Watermelon juice")*'Dirty Soda - Built Drinks'!$G$3:$G$23*'Dirty Soda - Built Drinks'!$B$3:$B$23)+SUMPRODUCT(('Dirty Soda - Built Drinks'!$H$3:$H$23="Watermelon juice")*'Dirty Soda - Built Drinks'!$I$3:$I$23*'Dirty Soda - Built Drinks'!$B$3:$B$23) | C51: =B51*(1+Assumptions!$B$5) | D51: =CEILING(C51/Assumptions!$B$218,1) | E51: 1 L (33.8 oz) cartons — REAL JUICE, not syrup and not the whole melons. The melons on Purchase List row 24 are Monday’s Hard Reset fresca and nothing else. Carton size and price are Assumptions B218/B219.
A54: Guava syrup (Torani, Guavascript) | B54: =SUMPRODUCT(('Dirty Soda - Built Drinks'!$F$3:$F$23="Guava syrup")*'Dirty Soda - Built Drinks'!$G$3:$G$23*'Dirty Soda - Built Drinks'!$B$3:$B$23)+SUMPRODUCT(('Dirty Soda - Built Drinks'!$H$3:$H$23="Guava syrup")*'Dirty Soda - Built Drinks'!$I$3:$I$23*'Dirty Soda - Built Drinks'!$B$3:$B$23) | C54: =B54*(1+Assumptions!$B$5) | D54: =CEILING(C54/Assumptions!$B$270,1) | E54: 25.4oz Torani bottle — SWITCHED FROM 16.9oz REàL PURéE 19 Aug 2026 (Assumptions B270, not the shared B91 squeeze-bottle size, which passion fruit still uses). Amazon only sells Torani Guava in a 3-pack, so the buy is 3 bottles regardless of the ~1-bottle math need.
A55: Paloma mixer (Guavascript) | B55: =SUMPRODUCT(('Dirty Soda - Built Drinks'!$D$3:$D$23="Paloma mixer")*'Dirty Soda - Built Drinks'!$E$3:$E$23*'Dirty Soda - Built Drinks'!$B$3:$B$23)+SUMPRODUCT(('Dirty Soda - Built Drinks'!$F$3:$F$23="Paloma mixer")*'Dirty Soda - Built Drinks'!$G$3:$G$23*'Dirty Soda - Built Drinks'!$B$3:$B$23)+SUMPRODUCT(('Dirty Soda - Built Drinks'!$H$3:$H$23="Paloma mixer")*'Dirty Soda - Built Drinks'!$I$3:$I$23*'Dirty Soda - Built Drinks'!$B$3:$B$23) | C55: =B55*(1+Assumptions!$B$5) | D55: =CEILING(C55/Assumptions!$B$241,1) | E55: 33.8oz (1 L) bottles — Tres Agaves paloma mix. Grapefruit, lime and agave already in it, which is why the recipe adds none of the three. THE EXPENSIVE INGREDIENT ON THIS DRINK: see the note on Assumptions B242. READS THE BASE SODA COLUMN AS WELL, FIXED 10 Aug 2026: Guavascript puts the mixer in the Base soda slot (D23/E23), not Syrup A or B, so the original formula matched nothing and this line read 0 oz / 0 bottles — the drink was on the menu with none of its main ingredient on the shopping list.
A56: Yuzu juice (Clear Cache) | B56: =SUMPRODUCT(('Dirty Soda - Built Drinks'!$F$3:$F$23="Yuzu juice")*'Dirty Soda - Built Drinks'!$G$3:$G$23*'Dirty Soda - Built Drinks'!$B$3:$B$23)+SUMPRODUCT(('Dirty Soda - Built Drinks'!$H$3:$H$23="Yuzu juice")*'Dirty Soda - Built Drinks'!$I$3:$I$23*'Dirty Soda - Built Drinks'!$B$3:$B$23) | C56: =B56*(1+Assumptions!$B$5) | D56: =CEILING(B56/Assumptions!$B$245,1) | E56: 13 oz bottles — THE ONLY CITRUS JUICE ON THE BAR THAT IS NOT LIME. Feeds both the SCOBY Mule (0.5 oz x 20) and Clear Cache (0.5 oz x 30), 25 oz between them; it replaced the fresh lemon in Clear Cache and then in the SCOBY Mule on 10 Aug 2026. Derived from the recipe — change the servings or the pour on 'Dirty Soda - Built Drinks' rows 11 and 14 and this follows. Sizing and price are Assumptions B245/B246. *** THIS IS THE ONE LINE IN THE MODEL THAT DOES NOT CARRY THE 15% BUFFER. *** It sizes off column B, not C, DELIBERATELY, decided 11 Aug 2026: 25 oz of requirement fits two 13 oz bottles with 1 oz to spare, and the buffer alone would have bought a third at $20. THE CONSEQUENCE IS REAL — there is no margin for a spilled or over-poured bottle across the whole week, so this one gets jiggered every time and does not go on the rail. Point D56 back at C56 to restore the buffer and the third bottle.
A57: Margarita mixer (Localhost) | B57: =SUMPRODUCT(('Dirty Soda - Built Drinks'!$D$3:$D$23="Margarita mixer")*'Dirty Soda - Built Drinks'!$E$3:$E$23*'Dirty Soda - Built Drinks'!$B$3:$B$23)+SUMPRODUCT(('Dirty Soda - Built Drinks'!$F$3:$F$23="Margarita mixer")*'Dirty Soda - Built Drinks'!$G$3:$G$23*'Dirty Soda - Built Drinks'!$B$3:$B$23)+SUMPRODUCT(('Dirty Soda - Built Drinks'!$H$3:$H$23="Margarita mixer")*'Dirty Soda - Built Drinks'!$I$3:$I$23*'Dirty Soda - Built Drinks'!$B$3:$B$23) | C57: =B57*(1+Assumptions!$B$5) | D57: =CEILING(C57/Assumptions!$B$249,1) | E57: 33.8oz (1 L) bottles — Tres Agaves margarita mix, added 11 Aug 2026 at 2 oz into every Localhost. Sizing and price are Assumptions B249/B250, priced the same as the paloma mix. LIKE THE PALOMA LINE, THIS READS THE BASE SODA COLUMN TOO: Localhost carries the mixer in the D/E slot, not Syrup A or B. THE FRESH LIME AND THE AGAVE ARE OPTIONAL. The margarita mixer already contains both, so start with tea + mixer + tequila, taste, and add the lime and agave only if it needs them. Both stay fully costed and on the shopping list — they are bought either way and they serve other drinks — so leaving them out of a build costs nothing and wastes nothing. Both are still sized at full rate on rows 45 and 47, so the model buys for the fullest version of the build and any restraint at the bar is headroom, not a shortfall.
A58: Tres Agaves Bloody Mary Mix (Michelada) | B58: =SUMPRODUCT(('Dirty Soda - Built Drinks'!$F$3:$F$23="Tres Agaves Bloody Mary Mix")*'Dirty Soda - Built Drinks'!$G$3:$G$23*'Dirty Soda - Built Drinks'!$B$3:$B$23)+SUMPRODUCT(('Dirty Soda - Built Drinks'!$H$3:$H$23="Tres Agaves Bloody Mary Mix")*'Dirty Soda - Built Drinks'!$I$3:$I$23*'Dirty Soda - Built Drinks'!$B$3:$B$23) | C58: =B58*(1+Assumptions!$B$5) | D58: =CEILING(C58/Assumptions!$B$268,1) | E58: ADDED 18 Aug 2026. 750 ml (25.4 oz) bottles — Tres Agaves Organic Bloody Mary Mix, confirmed real and on Amazon, same brand/shelf as the Paloma and Margarita mixes already on this order. Tomato, lime, chili pepper, onion, garlic, organic spices — already seasoned, which is why the separate hot sauce line is retired.
A59: Cranberry juice (Secret Party) | B59: =Assumptions!$B$297 | C59: =B59*(1+Assumptions!$B$5) | D59: =CEILING(C59/Assumptions!$B$295,1) | E59: 64oz jugs — sized off the 21 Aug 2026 vodka-party split (Assumptions rows 279-284), not the regular board. UNCHECKED product/price — confirm at checkout.
A60: Orange juice (Secret Party) | B60: =Assumptions!$B$298 | C60: =B60*(1+Assumptions!$B$5) | D60: =CEILING(C60/Assumptions!$B$69,1) | E60: 64oz cartons — same OJ product/price as the retired Catboy Café line (Assumptions B69/B70), just a fresh draw for the vodka party, kept as its own line rather than reactivating the retired one.

Sheet Purchase List
A1: Purchase List — Burning Man 2026 Dirty Soda Bar
A2: PACKAGED (POST-KEG) VERSION. Rows 13, 21, 22, 42, 74, 75, 77 are packaged beer, cider, kombucha and tea, sized on the 'Packaged Sizing' tab. The retired keg infrastructure lines (jockey box, CO2, deposits, lines) have been deleted outright. Everything else pulls live from the model. | B2: PACKAGED (POST-KEG) VERSION. Rows 13, 21, 22, 42, 74, 75, 77 are packaged beer/cider/kombucha/tea sized on the 'Packaged Sizing' tab to fill the same servings the kegs used to. The keg infrastructure lines (jockey box, CO2, deposits, lines) have been deleted. Everything else is untouched. Quantities still pull live from the model. | L2: PARKED (was pasted over the Category column and broke the rollups): Sunday, August 2, 2026 / Zoom Meeting / (Meeting ID: 848 0916 4817 Passcode: 533574)
A3: Quantities pull live from the model. Fill Source/Location, then check off as you buy. CANNED ITEMS ARE LISTED AS TOTAL CANS, not packs — pack sizes vary by shop and by trip, so buy the can count and let the format be whatever is on the shelf. BASE SODA IS BROKEN OUT ONE LINE PER FLAVOUR (rows 5-11, plus Orange Fanta on row 89 — split out because it is not a Costco buy) as of 10 Aug 2026, with the oz requirement in columns I-M so the buy does not have to be all cans. COLUMN K IS THE NUMBER THAT MATTERS AT THE SHOP: the oz that still has to be sourced, after the 2 L bottles already bought for the jugs (row 91) are netted off. Columns L and M answer it in each format, and they are NOT the same oz per container, because the formats waste differently — a 12 oz can pouring 3-4 oz at a time goes flat before you finish it (70% usable, Assumptions B157) while a screw-cap bottle recaps and holds pressure (90%, Assumptions B238). MIXING IS FINE: any combination clears the line as long as cans x 8.4 oz + 2 L bottles x 60.8 oz reaches column K. Qty and cost stay on the all-cans answer, so the $ moves if you buy a dearer format.
A4: ✓ | B4: Item | C4: Category | D4: Qty | E4: Unit | F4: Est. $ | G4: Source / Location | H4: Ordered | I4: Status | J4: Ordered as | K4: Link | L4: Notes | R4: Oz — recipe draw | S4: Oz — +15% buffer | T4: OZ TO SOURCE | U4: …as 12 oz cans | V4: …as 2 L bottles
A5: ☐ | B5: Jigger (1oz/2oz) | C5: Hardware | D5: 1 | E5: each | G5: TBD — Walmart/Target (SF or Reno, whichever trip is more convenient) | I5: =IF(AND($H5="",$J5=""),"· not ordered",IF($H5="","⚠ REVIEW",IF(N($H5)>=N($D5),"✅ MET","⚠ SHORT "&TEXT(N($D5)-N($H5),"0")&" "&$E5))) | L5: [[ NEEDS VENDOR ASSIGNMENT ]] ADDED 19 Aug 2026 — equipment carried over from the Supplies checklist that wasn't yet on the shopping list. Pours liquor shots accurately — the only pour control on 27+ bottles of liquor besides the spouts on row 67 (renumbered). Supplies row 5.
A6: ☐ | B6: Muddler | C6: Hardware | D6: 1 | E6: each | G6: TBD — Walmart/Target (SF or Reno, whichever trip is more convenient) | I6: =IF(AND($H6="",$J6=""),"· not ordered",IF($H6="","⚠ REVIEW",IF(N($H6)>=N($D6),"✅ MET","⚠ SHORT "&TEXT(N($D6)-N($H6),"0")&" "&$E6))) | L6: ADDED 19 Aug 2026 — equipment carried over from the Supplies checklist that wasn't yet on the shopping list. For the Hard Reset melon-mint muddle and any other built drink that wants one. Supplies row 7.
A7: ☐ | B7: Blender (12V or battery) | C7: Hardware | D7: 1 | E7: each | G7: TBD — Walmart/Target (SF or Reno, whichever trip is more convenient) | I7: =IF(AND($H7="",$J7=""),"· not ordered",IF($H7="","⚠ REVIEW",IF(N($H7)>=N($D7),"✅ MET","⚠ SHORT "&TEXT(N($D7)-N($H7),"0")&" "&$E7))) | L7: ADDED 19 Aug 2026 — equipment carried over from the Supplies checklist that wasn't yet on the shopping list. Monday's Hard Reset (Watermelon-Mint Aqua Fresca) is blended in batches — Jug Build Steps row 7 assumes a small 12V blender, 4-6 rounds. Supplies row 9.
A8: ☐ | B8: Cocktail shaker tin (Boston shaker) | C8: Hardware | D8: 1 | E8: each | G8: TBD — Walmart/Target (SF or Reno, whichever trip is more convenient) | I8: =IF(AND($H8="",$J8=""),"· not ordered",IF($H8="","⚠ REVIEW",IF(N($H8)>=N($D8),"✅ MET","⚠ SHORT "&TEXT(N($D8)-N($H8),"0")&" "&$E8))) | L8: ADDED 19 Aug 2026 — equipment carried over from the Supplies checklist that wasn't yet on the shopping list. General bar equipment, no single recipe depends on it. Supplies row 10.
A9: ☐ | B9: Measuring cups (1-4 cup set) | C9: Hardware | D9: 1 | E9: set | G9: TBD — Walmart/Target (SF or Reno, whichever trip is more convenient) | I9: =IF(AND($H9="",$J9=""),"· not ordered",IF($H9="","⚠ REVIEW",IF(N($H9)>=N($D9),"✅ MET","⚠ SHORT "&TEXT(N($D9)-N($H9),"0")&" "&$E9))) | L9: ADDED 19 Aug 2026 — equipment carried over from the Supplies checklist that wasn't yet on the shopping list. For batching jugs and syrups to spec rather than eyeballing. Supplies row 11.
A10: ☐ | B10: Cutting board | C10: Hardware | D10: 1 | E10: each | G10: TBD — Walmart/Target (SF or Reno, whichever trip is more convenient) | I10: =IF(AND($H10="",$J10=""),"· not ordered",IF($H10="","⚠ REVIEW",IF(N($H10)>=N($D10),"✅ MET","⚠ SHORT "&TEXT(N($D10)-N($H10),"0")&" "&$E10))) | L10: ADDED 19 Aug 2026 — equipment carried over from the Supplies checklist that wasn't yet on the shopping list. Garnish prep — citrus wheels, apple/pear, cucumber, candied ginger, mint sprigs. Supplies row 13.
A11: ☐ | B11: Fine mesh strainer | C11: Hardware | D11: 1 | E11: each | G11: TBD — Walmart/Target (SF or Reno, whichever trip is more convenient) | I11: =IF(AND($H11="",$J11=""),"· not ordered",IF($H11="","⚠ REVIEW",IF(N($H11)>=N($D11),"✅ MET","⚠ SHORT "&TEXT(N($D11)-N($H11),"0")&" "&$E11))) | L11: ADDED 19 Aug 2026 — equipment carried over from the Supplies checklist that wasn't yet on the shopping list. Straining the Hard Reset watermelon blend (Jug Build Steps row 7: 'strain rough through the fine mesh into a gallon container'). Distinct from the 5 gal strainer bags on row 92, which are for steeping, not straining pulp. Supplies row 15.
A12: ☐ | B12: Squeeze bottles (set of 6) | C12: Hardware | D12: 1 | E12: set | G12: TBD — Walmart/Target (SF or Reno, whichever trip is more convenient) | I12: =IF(AND($H12="",$J12=""),"· not ordered",IF($H12="","⚠ REVIEW",IF(N($H12)>=N($D12),"✅ MET","⚠ SHORT "&TEXT(N($D12)-N($H12),"0")&" "&$E12))) | L12: ADDED 19 Aug 2026 — equipment carried over from the Supplies checklist that wasn't yet on the shopping list. General bar equipment for syrups/juices at the rail. Supplies row 17.
A13: ☐ | B13: Garnish caddy (multi-compartment) | C13: Hardware | D13: 1 | E13: each | G13: TBD — Walmart/Target (SF or Reno, whichever trip is more convenient) | I13: =IF(AND($H13="",$J13=""),"· not ordered",IF($H13="","⚠ REVIEW",IF(N($H13)>=N($D13),"✅ MET","⚠ SHORT "&TEXT(N($D13)-N($H13),"0")&" "&$E13))) | L13: ADDED 19 Aug 2026 — equipment carried over from the Supplies checklist that wasn't yet on the shopping list. Bar-side quick-access caddy for citrus wheels, cherries, mint at point of service — distinct from the bulk 68oz prep/storage containers on row 98, which hold overnight stock, not rail-side garnish. Supplies row 21.
A14: ☐ | B14: Bottle opener | C14: Hardware | D14: 1 | E14: each | G14: TBD — Walmart/Target (SF or Reno, whichever trip is more convenient) | I14: =IF(AND($H14="",$J14=""),"· not ordered",IF($H14="","⚠ REVIEW",IF(N($H14)>=N($D14),"✅ MET","⚠ SHORT "&TEXT(N($D14)-N($H14),"0")&" "&$E14))) | L14: ADDED 19 Aug 2026 — equipment carried over from the Supplies checklist that wasn't yet on the shopping list. For the packaged beer/cider lines (Mexican lager, hard cider, blonde ale). Supplies row 22.
A15: ☐ | B15: Laminating pouches / cardstock (dispenser signs) | C15: Hardware | D15: 1 | E15: set | G15: TBD — Walmart/Target (SF or Reno, whichever trip is more convenient) | I15: =IF(AND($H15="",$J15=""),"· not ordered",IF($H15="","⚠ REVIEW",IF(N($H15)>=N($D15),"✅ MET","⚠ SHORT "&TEXT(N($D15)-N($H15),"0")&" "&$E15))) | L15: ADDED 19 Aug 2026 — equipment carried over from the Supplies checklist that wasn't yet on the shopping list. Materials for the 3x5 dispenser signs (print + laminate before playa) — Supplies row 26, Camp Drinks rows 30-35 have the sign copy ready to print.
A16: ☐ | B16: Tres Agaves Bloody Mary Mix (750 ml) — Michelada | C16: Built drink | D16: ='Other Consumables'!D58 | E16: bottles | F16: =D16*Assumptions!$B$269 | G16: Total Wine (SF) | I16: =IF(AND($H16="",$J16=""),"· not ordered",IF($H16="","⚠ REVIEW",IF(N($H16)>=N($D16),"✅ MET","⚠ SHORT "&TEXT(N($D16)-N($H16),"0")&" "&$E16))) | L16: [[ SF — THIS WEEKEND ]] Michelada — 2.5 oz Bloody Mary Mix + fresh lime, hot sauce retired (see Dirty Soda - Built Drinks row 4). PLANNED FOR THE SF TOTAL WINE RUN 19 Aug 2026 — Tres Agaves brand, same shelf as the Paloma/Margarita mixes below, grab all three together.
A17: ☐ | B17: Passion fruit purée — Reàl infused syrup (16.9oz squeeze) | C17: Syrup | D17: ='Other Consumables'!D17 | E17: bottles | F17: =D17*Assumptions!$B$92 | G17: Total Wine (SF) | H17: 2 | I17: =IF(AND($H17="",$J17=""),"· not ordered",IF($H17="","⚠ REVIEW",IF(N($H17)>=N($D17),"✅ MET","⚠ SHORT "&TEXT(N($D17)-N($H17),"0")&" "&$E17))) | J17: Bought at Total Wine, 19 Aug 2026 — 2 bottles. The +2 Amazon top-up did not go through; retrying in person at Total Wine this weekend instead. | L17: Feeds Tang Dynasty, the Thursday Gradient Descent jug, the Catboy Café green tea, and Catboy Piss (which just got taste-tested and came out great). 2 bottles secured against a buffered need of 5 (78.2 oz / 16.9 oz per bottle) — SHORT 3. Grab the rest at Total Wine this weekend rather than Amazon.
A18: ☐ | B18: Torani Guava Syrup (25.4oz) — Guavascript | C18: Syrup | D18: ='Other Consumables'!D54 | E18: bottles | F18: =D18*Assumptions!$B$232 | G18: Total Wine (SF) | I18: =IF(AND($H18="",$J18=""),"· not ordered",IF($H18="","⚠ REVIEW",IF(N($H18)>=N($D18),"✅ MET","⚠ SHORT "&TEXT(N($D18)-N($H18),"0")&" "&$E18))) | L18: SWITCHED FROM REàL GUAVA PURéE 19 Aug 2026 to Torani Guava Syrup (same 0.5oz dose, see Dirty Soda - Built Drinks row 23) — not at Total Wine, and Amazon only sold the purée in a 3-pack too. MOVED BACK TO TOTAL WINE 19 Aug 2026 — the Amazon order for the Torani syrup didn't go through; retrying in person this weekend. FLAG: Total Wine did NOT have guava purée on the first visit, and Torani flavor selection in physical stores is hit-or-miss — if guava (in either format) isn't there this time either, Amazon remains the fallback. Math need is ~1 bottle (14.4 oz buffered / 25.4 oz Torani format, or /16.9oz if back to purée).
A19: ☐ | B19: Liquor pour spouts (3-packs) | C19: Hardware | D19: 2 | E19: coke | F19: =D19*8.99 | G19: Total Wine (SF) | H19: 2 | I19: =IF(AND($H19="",$J19=""),"· not ordered",IF($H19="","⚠ REVIEW",IF(N($H19)>=N($D19),"✅ MET","⚠ SHORT "&TEXT(N($D19)-N($H19),"0")&" "&$E19))) | J19: BALTRE-style 6-pack of pourers bought at Total Wine, 19 Aug 2026 — matches the 2x3-pack (6 spout) need exactly. | L19: BevMo, $8.99 per 3-pack originally. TWO packs = 6 spouts, one for each spirit on the bar. PLANNED FOR THE SF GROCERY RUN 19 Aug 2026 (moved off the Reno BevMo plan since you're doing SF this weekend instead) — read as "bottle dispensers" in your message; flag if you actually meant something else and I've mis-mapped this.
A20: ☐ | B20: Paloma mixer (33.8oz bottles) — Guavascript | C20: Syrup | D20: ='Other Consumables'!D55 | E20: bottles | F20: =D20*Assumptions!$B$242 | G20: Total Wine (SF) | H20: 2 | I20: =IF(AND($H20="",$J20=""),"· not ordered",IF($H20="","⚠ REVIEW",IF(N($H20)>=N($D20),"✅ MET","⚠ SHORT "&TEXT(N($D20)-N($H20),"0")&" "&$E20))) | J20: Tres Agaves Organic Grapefruit Paloma Mix bought at Total Wine, 19 Aug 2026 — 2 bottles. | L20: Tres Agaves Organic Grapefruit Paloma Mix, 33.8oz — for Guavascript. PLANNED FOR THE SF TOTAL WINE RUN 19 Aug 2026, same shelf as the Margarita mix and the new Bloody Mary mix.
A21: ☐ | B21: Margarita mixer (33.8oz bottles) — Localhost | C21: Syrup | D21: ='Other Consumables'!D57 | E21: bottles | F21: =D21*Assumptions!$B$250 | G21: Total Wine (SF) | H21: 2 | I21: =IF(AND($H21="",$J21=""),"· not ordered",IF($H21="","⚠ REVIEW",IF(N($H21)>=N($D21),"✅ MET","⚠ SHORT "&TEXT(N($D21)-N($H21),"0")&" "&$E21))) | J21: Tres Agaves Organic Lime Margarita Mix bought at Total Wine, 19 Aug 2026 — 2 bottles. | L21: Tres Agaves Organic Lime Margarita Mix, 33.8oz — for Localhost. PLANNED FOR THE SF TOTAL WINE RUN 19 Aug 2026, same shelf as the Paloma mix and the new Bloody Mary mix.
A22: ☐ | B22: Aloe vera juice (1.5 L, with pulp) — Catboy Snot | C22: Built drink | D22: ='Other Consumables'!D48 | E22: bottles | F22: =D22*Assumptions!$B$149 | G22: Rainbow Grocery | I22: =IF(AND($H22="",$J22=""),"· not ordered",IF($H22="","⚠ REVIEW",IF(N($H22)>=N($D22),"✅ MET","⚠ SHORT "&TEXT(N($D22)-N($H22),"0")&" "&$E22))) | L22: Sat Catboy Snot — 1.5oz/serving (Assumptions B147). DRINKING aloe, inner-fillet/decolorized (OKF Aloe Vera King, Grace, Alo) — NOT whole-leaf or supplement aloe. Separate line from the keg-garnish aloe on row 71.
A23: ☐ | B23: Sprite — base soda | C23: Soda | D23: =U23 | E23: cans | F23: ='Base Soda — Cans'!E4*Assumptions!$B$16 | G23: Costco | I23: =IF(AND($H23="",$J23=""),"· not ordered",IF($H23="","⚠ REVIEW",IF(N($H23)>=N($D23),"✅ MET","⚠ SHORT "&TEXT(N($D23)-N($H23),"0")&" "&$E23))) | J23: *** UNIT CHANGED — 7.5 oz MINIS, not 12 oz cans. Qty in column D is 12 oz cans and CANNOT be compared to this. Reconcile upstream (Assumptions B7/B157) before trusting the green. *** 5 x 30-pk variety minis -> 50 x 7.5 oz Sprite = 375 oz. Need 304.7 oz. COVERED on volume. | K23: https://www.costco.com/p/-/coca-cola-mini-variety-pack-75-fl-oz-30-count/100787633?langId=-1 | L23: [[ RENO — NEXT WEEK ]] Shirley Temple of Doom, Shirley Mule and the 2 oz top-up that goes into every Squirt build, plus Sunday's Cherry Bomb jug. THE JUG'S 82.5 oz DOES NOT COME OUT OF CANS — it is poured from the 2 L bottles on row 91, and column K already nets that off, which is why this needs fewer cans than the buffered oz suggests. Shirley Mule moved onto Sprite (it was ginger ale) on 10 Aug 2026, which added 20 oz here. | R23: ='Base Soda — Cans'!B4 | S23: ='Base Soda — Cans'!C4 | T23: =MAX('Base Soda — Cans'!C4-'Base Soda — Cans'!H4,0) | U23: =CEILING(T23/(Assumptions!$B$7*Assumptions!$B$157),1) | V23: =CEILING(T23/(Assumptions!$B$165*Assumptions!$B$238),1)
A24: ☐ | B24: Coke — base soda | C24: Soda | D24: =U24 | E24: cans | F24: ='Base Soda — Cans'!E5*Assumptions!$B$16 | G24: Costco | I24: =IF(AND($H24="",$J24=""),"· not ordered",IF($H24="","⚠ REVIEW",IF(N($H24)>=N($D24),"✅ MET","⚠ SHORT "&TEXT(N($D24)-N($H24),"0")&" "&$E24))) | J24: *** UNIT CHANGED — 7.5 oz MINIS, not 12 oz cans. Qty in column D is 12 oz cans and CANNOT be compared to this. Reconcile upstream (Assumptions B7/B157) before trusting the green. *** 50 Cherry Coke minis (variety) + 2 x 30-pk plain Coke minis = 110 x 7.5 oz = 825 oz. Need 598 oz. COVERED on volume. Cherry Coke into the regular Coke bin — see the Vanilla Cherry Grove cherry-on-cherry question. | K24: https://www.costco.com/p/-/coca-cola-mini-variety-pack-75-fl-oz-30-count/100787633?langId=-1 https://www.costco.com/p/-/coca-cola-mini-75-fl-oz-30-count/100735424?langId=-1 | L24: Vanilla Cherry Grove only — 4 oz x 130 servings. The single biggest base-soda draw on the bar. | R24: ='Base Soda — Cans'!B5 | S24: ='Base Soda — Cans'!C5 | T24: =MAX('Base Soda — Cans'!C5-'Base Soda — Cans'!H5,0) | U24: =CEILING(T24/(Assumptions!$B$7*Assumptions!$B$157),1) | V24: =CEILING(T24/(Assumptions!$B$165*Assumptions!$B$238),1)
A25: ☐ | B25: Dr Pepper — base soda | C25: Soda | D25: =U25 | E25: cans | F25: ='Base Soda — Cans'!E8*Assumptions!$B$16 | G25: Grocery (Reno) | I25: =IF(AND($H25="",$J25=""),"· not ordered",IF($H25="","⚠ REVIEW",IF(N($H25)>=N($D25),"✅ MET","⚠ SHORT "&TEXT(N($D25)-N($H25),"0")&" "&$E25))) | J25: *** NOT CARRIED AT RENO COSTCO — moved to Grocery (Reno) 14 Aug 2026. *** Still to buy; the mini-can format on Sprite/Fanta/Coke does NOT apply here unless you find minis for this flavour too. | L25: The Dr's Cream + The Dr's Peach Exam — 4 oz x 80 servings between them. | R25: ='Base Soda — Cans'!B8 | S25: ='Base Soda — Cans'!C8 | T25: =MAX('Base Soda — Cans'!C8-'Base Soda — Cans'!H8,0) | U25: =CEILING(T25/(Assumptions!$B$7*Assumptions!$B$157),1) | V25: =CEILING(T25/(Assumptions!$B$165*Assumptions!$B$238),1)
A26: ☐ | B26: Ginger ale — base soda | C26: Soda | D26: =U26 | E26: cans | F26: ='Base Soda — Cans'!E9*Assumptions!$B$16 | G26: Grocery (Reno) | I26: =IF(AND($H26="",$J26=""),"· not ordered",IF($H26="","⚠ REVIEW",IF(N($H26)>=N($D26),"✅ MET","⚠ SHORT "&TEXT(N($D26)-N($H26),"0")&" "&$E26))) | J26: *** NOT CARRIED AT RENO COSTCO — moved to Grocery (Reno) 14 Aug 2026. *** Still to buy; the mini-can format on Sprite/Fanta/Coke does NOT apply here unless you find minis for this flavour too. | L26: A Ginger's Pickle ONLY as of 10 Aug 2026 — the Shirley Mule moved onto Sprite that day and takes its ginger from the ginger beer instead, which halved this line from 320 oz to 160. *** VENDOR CHECK 13 Aug 2026: Costco #779330, 36 x 12 oz, TRUE SINGLE-FLAVOUR. Do not let the shopper grab the seasonal Winter/Summer variety packs by mistake. *** | R26: ='Base Soda — Cans'!B9 | S26: ='Base Soda — Cans'!C9 | T26: =MAX('Base Soda — Cans'!C9-'Base Soda — Cans'!H9,0) | U26: =CEILING(T26/(Assumptions!$B$7*Assumptions!$B$157),1) | V26: =CEILING(T26/(Assumptions!$B$165*Assumptions!$B$238),1)
A27: ☐ | B27: Squirt — base soda | C27: Soda | D27: =U27 | E27: cans | F27: ='Base Soda — Cans'!E10*Assumptions!$B$16 | G27: Grocery (Reno) | I27: =IF(AND($H27="",$J27=""),"· not ordered",IF($H27="","⚠ REVIEW",IF(N($H27)>=N($D27),"✅ MET","⚠ SHORT "&TEXT(N($D27)-N($H27),"0")&" "&$E27))) | J27: *** NOT CARRIED AT RENO COSTCO — moved to Grocery (Reno) 14 Aug 2026. *** Still to buy; the mini-can format on Sprite/Fanta/Coke does NOT apply here unless you find minis for this flavour too. | L27: Thirst Trap (5 oz) + Catboy Snot (4 oz). Each of those builds also takes 2 oz of Sprite, which is charged to the Sprite line on row 5, not here. *** VENDOR CHECK 13 Aug 2026: Costco #246605, 36 x 12 oz. REGIONAL SKU — only ~183 warehouses, though the Southwest is its strong market. Phone Reno (775) 689-2200 with the item number before the drive. *** | R27: ='Base Soda — Cans'!B10 | S27: ='Base Soda — Cans'!C10 | T27: =MAX('Base Soda — Cans'!C10-'Base Soda — Cans'!H10,0) | U27: =CEILING(T27/(Assumptions!$B$7*Assumptions!$B$157),1) | V27: =CEILING(T27/(Assumptions!$B$165*Assumptions!$B$238),1)
A28: ☐ | B28: Root beer — base soda | C28: Soda | D28: =U28 | E28: cans | F28: ='Base Soda — Cans'!E13*Assumptions!$B$16 | G28: Grocery (Reno) | I28: =IF(AND($H28="",$J28=""),"· not ordered",IF($H28="","⚠ REVIEW",IF(N($H28)>=N($D28),"✅ MET","⚠ SHORT "&TEXT(N($D28)-N($H28),"0")&" "&$E28))) | J28: *** NOT CARRIED AT RENO COSTCO — moved to Grocery (Reno) 14 Aug 2026. *** Still to buy; the mini-can format on Sprite/Fanta/Coke does NOT apply here unless you find minis for this flavour too. | L28: Root Access only — 4 oz x 40 servings. A&W 36-pack is $15.99 at Costco, $0.44/can: the cheapest base on the board and effectively identical to the 35-pack price the model assumes. *** VENDOR CHECK 13 Aug 2026: Costco #779320, 36 x 12 oz. THIN DISTRIBUTION — only ~7 warehouses reporting stock. Confirm by phone or plan a grocery fallback. *** | R28: ='Base Soda — Cans'!B13 | S28: ='Base Soda — Cans'!C13 | T28: =MAX('Base Soda — Cans'!C13-'Base Soda — Cans'!H13,0) | U28: =CEILING(T28/(Assumptions!$B$7*Assumptions!$B$157),1) | V28: =CEILING(T28/(Assumptions!$B$165*Assumptions!$B$238),1)
A29: ☐ | B29: Lemonade — Kirkland Organic, 96 oz bottles | C29: Soda | D29: ='Other Consumables'!D19 | E29: 96 oz bottles (2-count packs) | F29: =D29*Assumptions!$B$17 | G29: Costco | H29: 4 | I29: =IF(AND($H29="",$J29=""),"· not ordered",IF($H29="","⚠ REVIEW",IF(N($H29)>=N($D29),"✅ MET","⚠ SHORT "&TEXT(N($D29)-N($H29),"0")&" "&$E29))) | J29: 2 x 2-count packs = 4 x 96 oz bottles. Exactly the 4 needed. | K29: https://www.costco.com/p/-/kirkland-signature-organic-lemonade-96-fl-oz-2-count/100384650?langId=-1 | L29: BUY 2 PACKS = 4 x 96 oz BOTTLES = 384 oz. Requirement is 299 oz raw (200 oz Watermelon Sugar High + 99 oz Tuesday Smoke Test) and 343.9 oz with the 15% buffer, so 4 bottles clears it with ~40 oz spare. Holds at 2 packs even if the base pour drops to 3.75 oz. READY-TO-DRINK AS OF 14 Aug 2026 — NO MIXING. The powder and the mix-on-arrival session are both gone; open a bottle when the bar needs one. Shelf-stable until opened, so it travels dry and only wants cooler space once cracked. NOTE THE TRADE: an opened 96 oz bottle now serves the Watermelon Sugar High 4 oz at a time across eight days, so there will be an open bottle in the cooler most of the week — the powder had no such open container. Tuesday’s jug drinks 99 oz in one go, so that one is clean.
